Workbook

Sheet Test Summary
A1: TenantEcom: manual and regression test summary
A2: Generated 2026-10-13 from docs/qa/tools. Figures recalculate as Status cells change.
A4: Portal | B4: Total cases | C4: Executed (Pass + Fail) | D4: Passed | E4: Failed | F4: Blocked | G4: Not Run | H4: Not Applicable | I4: Pass % | J4: Critical cases | K4: Smoke cases
A5: Super Admin | B5: =COUNTA('Super Admin'!A:A)-1 | C5: =D5+E5 | D5: =COUNTIF('Super Admin'!L:L,"Pass") | E5: =COUNTIF('Super Admin'!L:L,"Fail") | F5: =COUNTIF('Super Admin'!L:L,"Blocked") | G5: =COUNTIF('Super Admin'!L:L,"Not Run") | H5: =COUNTIF('Super Admin'!L:L,"Not Applicable") | I5: =IF(C5=0,0,D5/C5) | J5: =COUNTIF('Super Admin'!M:M,"Critical") | K5: =COUNTIF('Super Admin'!T:T,"Yes")
A6: Vendor CMS | B6: =COUNTA('Vendor CMS'!A:A)-1 | C6: =D6+E6 | D6: =COUNTIF('Vendor CMS'!L:L,"Pass") | E6: =COUNTIF('Vendor CMS'!L:L,"Fail") | F6: =COUNTIF('Vendor CMS'!L:L,"Blocked") | G6: =COUNTIF('Vendor CMS'!L:L,"Not Run") | H6: =COUNTIF('Vendor CMS'!L:L,"Not Applicable") | I6: =IF(C6=0,0,D6/C6) | J6: =COUNTIF('Vendor CMS'!M:M,"Critical") | K6: =COUNTIF('Vendor CMS'!T:T,"Yes")
A7: End-to-End Workflows | B7: =COUNTA('End-to-End Workflows'!A:A)-1 | C7: =D7+E7 | D7: =COUNTIF('End-to-End Workflows'!L:L,"Pass") | E7: =COUNTIF('End-to-End Workflows'!L:L,"Fail") | F7: =COUNTIF('End-to-End Workflows'!L:L,"Blocked") | G7: =COUNTIF('End-to-End Workflows'!L:L,"Not Run") | H7: =COUNTIF('End-to-End Workflows'!L:L,"Not Applicable") | I7: =IF(C7=0,0,D7/C7) | J7: =COUNTIF('End-to-End Workflows'!M:M,"Critical") | K7: =COUNTIF('End-to-End Workflows'!T:T,"Yes")
A8: All portals | B8: =SUM(B5:B7) | C8: =SUM(C5:C7) | D8: =SUM(D5:D7) | E8: =SUM(E5:E7) | F8: =SUM(F5:F7) | G8: =SUM(G5:G7) | H8: =SUM(H5:H7) | I8: =IF(C8=0,0,D8/C8) | J8: =SUM(J5:J7) | K8: =SUM(K5:K7)
A10: Coverage by module
A11: Module | B11: Portal | C11: Cases | D11: Passed | E11: Failed | F11: Blocked | G11: Not Run | H11: Pass % | I11: Critical | J11: Regression script
A12: SA-01 · Sign in and two-step verification | B12: Super Admin | C12: =COUNTIF('Super Admin'!C:C,A12) | D12: =COUNTIFS('Super Admin'!C:C,A12,'Super Admin'!L:L,"Pass") | E12: =COUNTIFS('Super Admin'!C:C,A12,'Super Admin'!L:L,"Fail") | F12: =COUNTIFS('Super Admin'!C:C,A12,'Super Admin'!L:L,"Blocked") | G12: =COUNTIFS('Super Admin'!C:C,A12,'Super Admin'!L:L,"Not Run") | H12: =IF((D12+E12)=0,0,D12/(D12+E12)) | I12: =COUNTIFS('Super Admin'!C:C,A12,'Super Admin'!M:M,"Critical") | J12: docs/qa/regression/super-admin/SA-01-sign-in.md
A13: SA-02 · Platform dashboard | B13: Super Admin | C13: =COUNTIF('Super Admin'!C:C,A13) | D13: =COUNTIFS('Super Admin'!C:C,A13,'Super Admin'!L:L,"Pass") | E13: =COUNTIFS('Super Admin'!C:C,A13,'Super Admin'!L:L,"Fail") | F13: =COUNTIFS('Super Admin'!C:C,A13,'Super Admin'!L:L,"Blocked") | G13: =COUNTIFS('Super Admin'!C:C,A13,'Super Admin'!L:L,"Not Run") | H13: =IF((D13+E13)=0,0,D13/(D13+E13)) | I13: =COUNTIFS('Super Admin'!C:C,A13,'Super Admin'!M:M,"Critical") | J13: docs/qa/regression/super-admin/SA-02-dashboard.md
A14: SA-03 · All vendors | B14: Super Admin | C14: =COUNTIF('Super Admin'!C:C,A14) | D14: =COUNTIFS('Super Admin'!C:C,A14,'Super Admin'!L:L,"Pass") | E14: =COUNTIFS('Super Admin'!C:C,A14,'Super Admin'!L:L,"Fail") | F14: =COUNTIFS('Super Admin'!C:C,A14,'Super Admin'!L:L,"Blocked") | G14: =COUNTIFS('Super Admin'!C:C,A14,'Super Admin'!L:L,"Not Run") | H14: =IF((D14+E14)=0,0,D14/(D14+E14)) | I14: =COUNTIFS('Super Admin'!C:C,A14,'Super Admin'!M:M,"Critical") | J14: docs/qa/regression/super-admin/SA-03-all-vendors.md
A15: SA-04 · New vendor (onboarding) | B15: Super Admin | C15: =COUNTIF('Super Admin'!C:C,A15) | D15: =COUNTIFS('Super Admin'!C:C,A15,'Super Admin'!L:L,"Pass") | E15: =COUNTIFS('Super Admin'!C:C,A15,'Super Admin'!L:L,"Fail") | F15: =COUNTIFS('Super Admin'!C:C,A15,'Super Admin'!L:L,"Blocked") | G15: =COUNTIFS('Super Admin'!C:C,A15,'Super Admin'!L:L,"Not Run") | H15: =IF((D15+E15)=0,0,D15/(D15+E15)) | I15: =COUNTIFS('Super Admin'!C:C,A15,'Super Admin'!M:M,"Critical") | J15: docs/qa/regression/super-admin/SA-04-new-vendor.md
A16: SA-05 · Vendor overview and store status | B16: Super Admin | C16: =COUNTIF('Super Admin'!C:C,A16) | D16: =COUNTIFS('Super Admin'!C:C,A16,'Super Admin'!L:L,"Pass") | E16: =COUNTIFS('Super Admin'!C:C,A16,'Super Admin'!L:L,"Fail") | F16: =COUNTIFS('Super Admin'!C:C,A16,'Super Admin'!L:L,"Blocked") | G16: =COUNTIFS('Super Admin'!C:C,A16,'Super Admin'!L:L,"Not Run") | H16: =IF((D16+E16)=0,0,D16/(D16+E16)) | I16: =COUNTIFS('Super Admin'!C:C,A16,'Super Admin'!M:M,"Critical") | J16: docs/qa/regression/super-admin/SA-05-vendor-overview.md
A17: SA-06 · Store sessions (Manage store, View as support) | B17: Super Admin | C17: =COUNTIF('Super Admin'!C:C,A17) | D17: =COUNTIFS('Super Admin'!C:C,A17,'Super Admin'!L:L,"Pass") | E17: =COUNTIFS('Super Admin'!C:C,A17,'Super Admin'!L:L,"Fail") | F17: =COUNTIFS('Super Admin'!C:C,A17,'Super Admin'!L:L,"Blocked") | G17: =COUNTIFS('Super Admin'!C:C,A17,'Super Admin'!L:L,"Not Run") | H17: =IF((D17+E17)=0,0,D17/(D17+E17)) | I17: =COUNTIFS('Super Admin'!C:C,A17,'Super Admin'!M:M,"Critical") | J17: docs/qa/regression/super-admin/SA-06-store-sessions.md
A18: SA-07 · Vendor features | B18: Super Admin | C18: =COUNTIF('Super Admin'!C:C,A18) | D18: =COUNTIFS('Super Admin'!C:C,A18,'Super Admin'!L:L,"Pass") | E18: =COUNTIFS('Super Admin'!C:C,A18,'Super Admin'!L:L,"Fail") | F18: =COUNTIFS('Super Admin'!C:C,A18,'Super Admin'!L:L,"Blocked") | G18: =COUNTIFS('Super Admin'!C:C,A18,'Super Admin'!L:L,"Not Run") | H18: =IF((D18+E18)=0,0,D18/(D18+E18)) | I18: =COUNTIFS('Super Admin'!C:C,A18,'Super Admin'!M:M,"Critical") | J18: docs/qa/regression/super-admin/SA-07-vendor-features.md
A19: SA-08 · Vendor connectors | B19: Super Admin | C19: =COUNTIF('Super Admin'!C:C,A19) | D19: =COUNTIFS('Super Admin'!C:C,A19,'Super Admin'!L:L,"Pass") | E19: =COUNTIFS('Super Admin'!C:C,A19,'Super Admin'!L:L,"Fail") | F19: =COUNTIFS('Super Admin'!C:C,A19,'Super Admin'!L:L,"Blocked") | G19: =COUNTIFS('Super Admin'!C:C,A19,'Super Admin'!L:L,"Not Run") | H19: =IF((D19+E19)=0,0,D19/(D19+E19)) | I19: =COUNTIFS('Super Admin'!C:C,A19,'Super Admin'!M:M,"Critical") | J19: docs/qa/regression/super-admin/SA-08-vendor-connectors.md
A20: SA-09 · Vendor domains | B20: Super Admin | C20: =COUNTIF('Super Admin'!C:C,A20) | D20: =COUNTIFS('Super Admin'!C:C,A20,'Super Admin'!L:L,"Pass") | E20: =COUNTIFS('Super Admin'!C:C,A20,'Super Admin'!L:L,"Fail") | F20: =COUNTIFS('Super Admin'!C:C,A20,'Super Admin'!L:L,"Blocked") | G20: =COUNTIFS('Super Admin'!C:C,A20,'Super Admin'!L:L,"Not Run") | H20: =IF((D20+E20)=0,0,D20/(D20+E20)) | I20: =COUNTIFS('Super Admin'!C:C,A20,'Super Admin'!M:M,"Critical") | J20: docs/qa/regression/super-admin/SA-09-vendor-domains.md
A21: SA-10 · Vendor billing | B21: Super Admin | C21: =COUNTIF('Super Admin'!C:C,A21) | D21: =COUNTIFS('Super Admin'!C:C,A21,'Super Admin'!L:L,"Pass") | E21: =COUNTIFS('Super Admin'!C:C,A21,'Super Admin'!L:L,"Fail") | F21: =COUNTIFS('Super Admin'!C:C,A21,'Super Admin'!L:L,"Blocked") | G21: =COUNTIFS('Super Admin'!C:C,A21,'Super Admin'!L:L,"Not Run") | H21: =IF((D21+E21)=0,0,D21/(D21+E21)) | I21: =COUNTIFS('Super Admin'!C:C,A21,'Super Admin'!M:M,"Critical") | J21: docs/qa/regression/super-admin/SA-10-vendor-billing.md
A22: SA-11 · Vendor staff | B22: Super Admin | C22: =COUNTIF('Super Admin'!C:C,A22) | D22: =COUNTIFS('Super Admin'!C:C,A22,'Super Admin'!L:L,"Pass") | E22: =COUNTIFS('Super Admin'!C:C,A22,'Super Admin'!L:L,"Fail") | F22: =COUNTIFS('Super Admin'!C:C,A22,'Super Admin'!L:L,"Blocked") | G22: =COUNTIFS('Super Admin'!C:C,A22,'Super Admin'!L:L,"Not Run") | H22: =IF((D22+E22)=0,0,D22/(D22+E22)) | I22: =COUNTIFS('Super Admin'!C:C,A22,'Super Admin'!M:M,"Critical") | J22: docs/qa/regression/super-admin/SA-11-vendor-staff.md
A23: SA-12 · Plans | B23: Super Admin | C23: =COUNTIF('Super Admin'!C:C,A23) | D23: =COUNTIFS('Super Admin'!C:C,A23,'Super Admin'!L:L,"Pass") | E23: =COUNTIFS('Super Admin'!C:C,A23,'Super Admin'!L:L,"Fail") | F23: =COUNTIFS('Super Admin'!C:C,A23,'Super Admin'!L:L,"Blocked") | G23: =COUNTIFS('Super Admin'!C:C,A23,'Super Admin'!L:L,"Not Run") | H23: =IF((D23+E23)=0,0,D23/(D23+E23)) | I23: =COUNTIFS('Super Admin'!C:C,A23,'Super Admin'!M:M,"Critical") | J23: docs/qa/regression/super-admin/SA-12-plans.md
... A26: SA-15 · Platform permissions and isolation | B26: Super Admin | C26: =COUNTIF('Super Admin'!C:C,A26) | D26: =COUNTIFS('Super Admin'!C:C,A26,'Super Admin'!L:L,"Pass") | E26: =COUNTIFS('Super Admin'!C:C,A26,'Super Admin'!L:L,"Fail") | F26: =COUNTIFS('Super Admin'!C:C,A26,'Super Admin'!L:L,"Blocked") | G26: =COUNTIFS('Super Admin'!C:C,A26,'Super Admin'!L:L,"Not Run") | H26: =IF((D26+E26)=0,0,D26/(D26+E26)) | I26: =COUNTIFS('Super Admin'!C:C,A26,'Super Admin'!M:M,"Critical") | J26: docs/qa/regression/super-admin/SA-15-permissions.md
A27: VC-01 · Sign in, first password and session | B27: Vendor CMS | C27: =COUNTIF('Vendor CMS'!C:C,A27) | D27: =COUNTIFS('Vendor CMS'!C:C,A27,'Vendor CMS'!L:L,"Pass") | E27: =COUNTIFS('Vendor CMS'!C:C,A27,'Vendor CMS'!L:L,"Fail") | F27: =COUNTIFS('Vendor CMS'!C:C,A27,'Vendor CMS'!L:L,"Blocked") | G27: =COUNTIFS('Vendor CMS'!C:C,A27,'Vendor CMS'!L:L,"Not Run") | H27: =IF((D27+E27)=0,0,D27/(D27+E27)) | I27: =COUNTIFS('Vendor CMS'!C:C,A27,'Vendor CMS'!M:M,"Critical") | J27: docs/qa/regression/vendor-cms/VC-01-sign-in.md
A28: VC-02 · Store dashboard and navigation | B28: Vendor CMS | C28: =COUNTIF('Vendor CMS'!C:C,A28) | D28: =COUNTIFS('Vendor CMS'!C:C,A28,'Vendor CMS'!L:L,"Pass") | E28: =COUNTIFS('Vendor CMS'!C:C,A28,'Vendor CMS'!L:L,"Fail") | F28: =COUNTIFS('Vendor CMS'!C:C,A28,'Vendor CMS'!L:L,"Blocked") | G28: =COUNTIFS('Vendor CMS'!C:C,A28,'Vendor CMS'!L:L,"Not Run") | H28: =IF((D28+E28)=0,0,D28/(D28+E28)) | I28: =COUNTIFS('Vendor CMS'!C:C,A28,'Vendor CMS'!M:M,"Critical") | J28: docs/qa/regression/vendor-cms/VC-02-dashboard.md
A29: VC-03 · Store settings | B29: Vendor CMS | C29: =COUNTIF('Vendor CMS'!C:C,A29) | D29: =COUNTIFS('Vendor CMS'!C:C,A29,'Vendor CMS'!L:L,"Pass") | E29: =COUNTIFS('Vendor CMS'!C:C,A29,'Vendor CMS'!L:L,"Fail") | F29: =COUNTIFS('Vendor CMS'!C:C,A29,'Vendor CMS'!L:L,"Blocked") | G29: =COUNTIFS('Vendor CMS'!C:C,A29,'Vendor CMS'!L:L,"Not Run") | H29: =IF((D29+E29)=0,0,D29/(D29+E29)) | I29: =COUNTIFS('Vendor CMS'!C:C,A29,'Vendor CMS'!M:M,"Critical") | J29: docs/qa/regression/vendor-cms/VC-03-store-settings.md
A30: VC-04 · Products and product editor | B30: Vendor CMS | C30: =COUNTIF('Vendor CMS'!C:C,A30) | D30: =COUNTIFS('Vendor CMS'!C:C,A30,'Vendor CMS'!L:L,"Pass") | E30: =COUNTIFS('Vendor CMS'!C:C,A30,'Vendor CMS'!L:L,"Fail") | F30: =COUNTIFS('Vendor CMS'!C:C,A30,'Vendor CMS'!L:L,"Blocked") | G30: =COUNTIFS('Vendor CMS'!C:C,A30,'Vendor CMS'!L:L,"Not Run") | H30: =IF((D30+E30)=0,0,D30/(D30+E30)) | I30: =COUNTIFS('Vendor CMS'!C:C,A30,'Vendor CMS'!M:M,"Critical") | J30: docs/qa/regression/vendor-cms/VC-04-products.md
A31: VC-05 · Categories | B31: Vendor CMS | C31: =COUNTIF('Vendor CMS'!C:C,A31) | D31: =COUNTIFS('Vendor CMS'!C:C,A31,'Vendor CMS'!L:L,"Pass") | E31: =COUNTIFS('Vendor CMS'!C:C,A31,'Vendor CMS'!L:L,"Fail") | F31: =COUNTIFS('Vendor CMS'!C:C,A31,'Vendor CMS'!L:L,"Blocked") | G31: =COUNTIFS('Vendor CMS'!C:C,A31,'Vendor CMS'!L:L,"Not Run") | H31: =IF((D31+E31)=0,0,D31/(D31+E31)) | I31: =COUNTIFS('Vendor CMS'!C:C,A31,'Vendor CMS'!M:M,"Critical") | J31: docs/qa/regression/vendor-cms/VC-05-categories.md
A32: VC-06 · Attribute sets | B32: Vendor CMS | C32: =COUNTIF('Vendor CMS'!C:C,A32) | D32: =COUNTIFS('Vendor CMS'!C:C,A32,'Vendor CMS'!L:L,"Pass") | E32: =COUNTIFS('Vendor CMS'!C:C,A32,'Vendor CMS'!L:L,"Fail") | F32: =COUNTIFS('Vendor CMS'!C:C,A32,'Vendor CMS'!L:L,"Blocked") | G32: =COUNTIFS('Vendor CMS'!C:C,A32,'Vendor CMS'!L:L,"Not Run") | H32: =IF((D32+E32)=0,0,D32/(D32+E32)) | I32: =COUNTIFS('Vendor CMS'!C:C,A32,'Vendor CMS'!M:M,"Critical") | J32: docs/qa/regression/vendor-cms/VC-06-attribute-sets.md
A33: VC-07 · Brands, Documents and Variants | B33: Vendor CMS | C33: =COUNTIF('Vendor CMS'!C:C,A33) | D33: =COUNTIFS('Vendor CMS'!C:C,A33,'Vendor CMS'!L:L,"Pass") | E33: =COUNTIFS('Vendor CMS'!C:C,A33,'Vendor CMS'!L:L,"Fail") | F33: =COUNTIFS('Vendor CMS'!C:C,A33,'Vendor CMS'!L:L,"Blocked") | G33: =COUNTIFS('Vendor CMS'!C:C,A33,'Vendor CMS'!L:L,"Not Run") | H33: =IF((D33+E33)=0,0,D33/(D33+E33)) | I33: =COUNTIFS('Vendor CMS'!C:C,A33,'Vendor CMS'!M:M,"Critical") | J33: docs/qa/regression/vendor-cms/VC-07-brands-documents.md
A34: VC-08 · Import and export | B34: Vendor CMS | C34: =COUNTIF('Vendor CMS'!C:C,A34) | D34: =COUNTIFS('Vendor CMS'!C:C,A34,'Vendor CMS'!L:L,"Pass") | E34: =COUNTIFS('Vendor CMS'!C:C,A34,'Vendor CMS'!L:L,"Fail") | F34: =COUNTIFS('Vendor CMS'!C:C,A34,'Vendor CMS'!L:L,"Blocked") | G34: =COUNTIFS('Vendor CMS'!C:C,A34,'Vendor CMS'!L:L,"Not Run") | H34: =IF((D34+E34)=0,0,D34/(D34+E34)) | I34: =COUNTIFS('Vendor CMS'!C:C,A34,'Vendor CMS'!M:M,"Critical") | J34: docs/qa/regression/vendor-cms/VC-08-import.md
A35: VC-09 · Media library | B35: Vendor CMS | C35: =COUNTIF('Vendor CMS'!C:C,A35) | D35: =COUNTIFS('Vendor CMS'!C:C,A35,'Vendor CMS'!L:L,"Pass") | E35: =COUNTIFS('Vendor CMS'!C:C,A35,'Vendor CMS'!L:L,"Fail") | F35: =COUNTIFS('Vendor CMS'!C:C,A35,'Vendor CMS'!L:L,"Blocked") | G35: =COUNTIFS('Vendor CMS'!C:C,A35,'Vendor CMS'!L:L,"Not Run") | H35: =IF((D35+E35)=0,0,D35/(D35+E35)) | I35: =COUNTIFS('Vendor CMS'!C:C,A35,'Vendor CMS'!M:M,"Critical") | J35: docs/qa/regression/vendor-cms/VC-09-media.md
A36: VC-10 · Orders and order detail | B36: Vendor CMS | C36: =COUNTIF('Vendor CMS'!C:C,A36) | D36: =COUNTIFS('Vendor CMS'!C:C,A36,'Vendor CMS'!L:L,"Pass") | E36: =COUNTIFS('Vendor CMS'!C:C,A36,'Vendor CMS'!L:L,"Fail") | F36: =COUNTIFS('Vendor CMS'!C:C,A36,'Vendor CMS'!L:L,"Blocked") | G36: =COUNTIFS('Vendor CMS'!C:C,A36,'Vendor CMS'!L:L,"Not Run") | H36: =IF((D36+E36)=0,0,D36/(D36+E36)) | I36: =COUNTIFS('Vendor CMS'!C:C,A36,'Vendor CMS'!M:M,"Critical") | J36: docs/qa/regression/vendor-cms/VC-10-orders.md
A37: VC-11 · Returns | B37: Vendor CMS | C37: =COUNTIF('Vendor CMS'!C:C,A37) | D37: =COUNTIFS('Vendor CMS'!C:C,A37,'Vendor CMS'!L:L,"Pass") | E37: =COUNTIFS('Vendor CMS'!C:C,A37,'Vendor CMS'!L:L,"Fail") | F37: =COUNTIFS('Vendor CMS'!C:C,A37,'Vendor CMS'!L:L,"Blocked") | G37: =COUNTIFS('Vendor CMS'!C:C,A37,'Vendor CMS'!L:L,"Not Run") | H37: =IF((D37+E37)=0,0,D37/(D37+E37)) | I37: =COUNTIFS('Vendor CMS'!C:C,A37,'Vendor CMS'!M:M,"Critical") | J37: docs/qa/regression/vendor-cms/VC-11-returns.md
A38: VC-12 · Customers and privacy requests | B38: Vendor CMS | C38: =COUNTIF('Vendor CMS'!C:C,A38) | D38: =COUNTIFS('Vendor CMS'!C:C,A38,'Vendor CMS'!L:L,"Pass") | E38: =COUNTIFS('Vendor CMS'!C:C,A38,'Vendor CMS'!L:L,"Fail") | F38: =COUNTIFS('Vendor CMS'!C:C,A38,'Vendor CMS'!L:L,"Blocked") | G38: =COUNTIFS('Vendor CMS'!C:C,A38,'Vendor CMS'!L:L,"Not Run") | H38: =IF((D38+E38)=0,0,D38/(D38+E38)) | I38: =COUNTIFS('Vendor CMS'!C:C,A38,'Vendor CMS'!M:M,"Critical") | J38: docs/qa/regression/vendor-cms/VC-12-customers.md
... A55: VC-29 · Reports | B55: Vendor CMS | C55: =COUNTIF('Vendor CMS'!C:C,A55) | D55: =COUNTIFS('Vendor CMS'!C:C,A55,'Vendor CMS'!L:L,"Pass") | E55: =COUNTIFS('Vendor CMS'!C:C,A55,'Vendor CMS'!L:L,"Fail") | F55: =COUNTIFS('Vendor CMS'!C:C,A55,'Vendor CMS'!L:L,"Blocked") | G55: =COUNTIFS('Vendor CMS'!C:C,A55,'Vendor CMS'!L:L,"Not Run") | H55: =IF((D55+E55)=0,0,D55/(D55+E55)) | I55: =COUNTIFS('Vendor CMS'!C:C,A55,'Vendor CMS'!M:M,"Critical") | J55: docs/qa/regression/vendor-cms/VC-29-reports.md
A56: E2E-01 · Vendor onboarding to first store preview | B56: End-to-End | C56: =COUNTIF('End-to-End Workflows'!C:C,A56) | D56: =COUNTIFS('End-to-End Workflows'!C:C,A56,'End-to-End Workflows'!L:L,"Pass") | E56: =COUNTIFS('End-to-End Workflows'!C:C,A56,'End-to-End Workflows'!L:L,"Fail") | F56: =COUNTIFS('End-to-End Workflows'!C:C,A56,'End-to-End Workflows'!L:L,"Blocked") | G56: =COUNTIFS('End-to-End Workflows'!C:C,A56,'End-to-End Workflows'!L:L,"Not Run") | H56: =IF((D56+E56)=0,0,D56/(D56+E56)) | I56: =COUNTIFS('End-to-End Workflows'!C:C,A56,'End-to-End Workflows'!M:M,"Critical") | J56: docs/qa/regression/e2e/E2E-01-onboarding.md
A57: E2E-02 · Feature switches across portals | B57: End-to-End | C57: =COUNTIF('End-to-End Workflows'!C:C,A57) | D57: =COUNTIFS('End-to-End Workflows'!C:C,A57,'End-to-End Workflows'!L:L,"Pass") | E57: =COUNTIFS('End-to-End Workflows'!C:C,A57,'End-to-End Workflows'!L:L,"Fail") | F57: =COUNTIFS('End-to-End Workflows'!C:C,A57,'End-to-End Workflows'!L:L,"Blocked") | G57: =COUNTIFS('End-to-End Workflows'!C:C,A57,'End-to-End Workflows'!L:L,"Not Run") | H57: =IF((D57+E57)=0,0,D57/(D57+E57)) | I57: =COUNTIFS('End-to-End Workflows'!C:C,A57,'End-to-End Workflows'!M:M,"Critical") | J57: docs/qa/regression/e2e/E2E-02-features.md
A58: E2E-03 · Catalogue to storefront | B58: End-to-End | C58: =COUNTIF('End-to-End Workflows'!C:C,A58) | D58: =COUNTIFS('End-to-End Workflows'!C:C,A58,'End-to-End Workflows'!L:L,"Pass") | E58: =COUNTIFS('End-to-End Workflows'!C:C,A58,'End-to-End Workflows'!L:L,"Fail") | F58: =COUNTIFS('End-to-End Workflows'!C:C,A58,'End-to-End Workflows'!L:L,"Blocked") | G58: =COUNTIFS('End-to-End Workflows'!C:C,A58,'End-to-End Workflows'!L:L,"Not Run") | H58: =IF((D58+E58)=0,0,D58/(D58+E58)) | I58: =COUNTIFS('End-to-End Workflows'!C:C,A58,'End-to-End Workflows'!M:M,"Critical") | J58: docs/qa/regression/e2e/E2E-03-catalogue.md
A59: E2E-04 · Order to cash (COD) | B59: End-to-End | C59: =COUNTIF('End-to-End Workflows'!C:C,A59) | D59: =COUNTIFS('End-to-End Workflows'!C:C,A59,'End-to-End Workflows'!L:L,"Pass") | E59: =COUNTIFS('End-to-End Workflows'!C:C,A59,'End-to-End Workflows'!L:L,"Fail") | F59: =COUNTIFS('End-to-End Workflows'!C:C,A59,'End-to-End Workflows'!L:L,"Blocked") | G59: =COUNTIFS('End-to-End Workflows'!C:C,A59,'End-to-End Workflows'!L:L,"Not Run") | H59: =IF((D59+E59)=0,0,D59/(D59+E59)) | I59: =COUNTIFS('End-to-End Workflows'!C:C,A59,'End-to-End Workflows'!M:M,"Critical") | J59: docs/qa/regression/e2e/E2E-04-order-to-cash.md
A60: E2E-05 · Schemes and coupons to checkout | B60: End-to-End | C60: =COUNTIF('End-to-End Workflows'!C:C,A60) | D60: =COUNTIFS('End-to-End Workflows'!C:C,A60,'End-to-End Workflows'!L:L,"Pass") | E60: =COUNTIFS('End-to-End Workflows'!C:C,A60,'End-to-End Workflows'!L:L,"Fail") | F60: =COUNTIFS('End-to-End Workflows'!C:C,A60,'End-to-End Workflows'!L:L,"Blocked") | G60: =COUNTIFS('End-to-End Workflows'!C:C,A60,'End-to-End Workflows'!L:L,"Not Run") | H60: =IF((D60+E60)=0,0,D60/(D60+E60)) | I60: =COUNTIFS('End-to-End Workflows'!C:C,A60,'End-to-End Workflows'!M:M,"Critical") | J60: docs/qa/regression/e2e/E2E-05-offers.md
A61: E2E-06 · Review lifecycle | B61: End-to-End | C61: =COUNTIF('End-to-End Workflows'!C:C,A61) | D61: =COUNTIFS('End-to-End Workflows'!C:C,A61,'End-to-End Workflows'!L:L,"Pass") | E61: =COUNTIFS('End-to-End Workflows'!C:C,A61,'End-to-End Workflows'!L:L,"Fail") | F61: =COUNTIFS('End-to-End Workflows'!C:C,A61,'End-to-End Workflows'!L:L,"Blocked") | G61: =COUNTIFS('End-to-End Workflows'!C:C,A61,'End-to-End Workflows'!L:L,"Not Run") | H61: =IF((D61+E61)=0,0,D61/(D61+E61)) | I61: =COUNTIFS('End-to-End Workflows'!C:C,A61,'End-to-End Workflows'!M:M,"Critical") | J61: docs/qa/regression/e2e/E2E-06-reviews.md
A62: E2E-07 · Store status across portals | B62: End-to-End | C62: =COUNTIF('End-to-End Workflows'!C:C,A62) | D62: =COUNTIFS('End-to-End Workflows'!C:C,A62,'End-to-End Workflows'!L:L,"Pass") | E62: =COUNTIFS('End-to-End Workflows'!C:C,A62,'End-to-End Workflows'!L:L,"Fail") | F62: =COUNTIFS('End-to-End Workflows'!C:C,A62,'End-to-End Workflows'!L:L,"Blocked") | G62: =COUNTIFS('End-to-End Workflows'!C:C,A62,'End-to-End Workflows'!L:L,"Not Run") | H62: =IF((D62+E62)=0,0,D62/(D62+E62)) | I62: =COUNTIFS('End-to-End Workflows'!C:C,A62,'End-to-End Workflows'!M:M,"Critical") | J62: docs/qa/regression/e2e/E2E-07-store-status.md
A63: E2E-08 · Platform support session audit | B63: End-to-End | C63: =COUNTIF('End-to-End Workflows'!C:C,A63) | D63: =COUNTIFS('End-to-End Workflows'!C:C,A63,'End-to-End Workflows'!L:L,"Pass") | E63: =COUNTIFS('End-to-End Workflows'!C:C,A63,'End-to-End Workflows'!L:L,"Fail") | F63: =COUNTIFS('End-to-End Workflows'!C:C,A63,'End-to-End Workflows'!L:L,"Blocked") | G63: =COUNTIFS('End-to-End Workflows'!C:C,A63,'End-to-End Workflows'!L:L,"Not Run") | H63: =IF((D63+E63)=0,0,D63/(D63+E63)) | I63: =COUNTIFS('End-to-End Workflows'!C:C,A63,'End-to-End Workflows'!M:M,"Critical") | J63: docs/qa/regression/e2e/E2E-08-support-session.md
A64: E2E-09 · Connector allowance to checkout | B64: End-to-End | C64: =COUNTIF('End-to-End Workflows'!C:C,A64) | D64: =COUNTIFS('End-to-End Workflows'!C:C,A64,'End-to-End Workflows'!L:L,"Pass") | E64: =COUNTIFS('End-to-End Workflows'!C:C,A64,'End-to-End Workflows'!L:L,"Fail") | F64: =COUNTIFS('End-to-End Workflows'!C:C,A64,'End-to-End Workflows'!L:L,"Blocked") | G64: =COUNTIFS('End-to-End Workflows'!C:C,A64,'End-to-End Workflows'!L:L,"Not Run") | H64: =IF((D64+E64)=0,0,D64/(D64+E64)) | I64: =COUNTIFS('End-to-End Workflows'!C:C,A64,'End-to-End Workflows'!M:M,"Critical") | J64: docs/qa/regression/e2e/E2E-09-connectors.md
A65: E2E-10 · Staff roles and two-step reset | B65: End-to-End | C65: =COUNTIF('End-to-End Workflows'!C:C,A65) | D65: =COUNTIFS('End-to-End Workflows'!C:C,A65,'End-to-End Workflows'!L:L,"Pass") | E65: =COUNTIFS('End-to-End Workflows'!C:C,A65,'End-to-End Workflows'!L:L,"Fail") | F65: =COUNTIFS('End-to-End Workflows'!C:C,A65,'End-to-End Workflows'!L:L,"Blocked") | G65: =COUNTIFS('End-to-End Workflows'!C:C,A65,'End-to-End Workflows'!L:L,"Not Run") | H65: =IF((D65+E65)=0,0,D65/(D65+E65)) | I65: =COUNTIFS('End-to-End Workflows'!C:C,A65,'End-to-End Workflows'!M:M,"Critical") | J65: docs/qa/regression/e2e/E2E-10-staff.md
A66: E2E-11 · Tenant isolation | B66: End-to-End | C66: =COUNTIF('End-to-End Workflows'!C:C,A66) | D66: =COUNTIFS('End-to-End Workflows'!C:C,A66,'End-to-End Workflows'!L:L,"Pass") | E66: =COUNTIFS('End-to-End Workflows'!C:C,A66,'End-to-End Workflows'!L:L,"Fail") | F66: =COUNTIFS('End-to-End Workflows'!C:C,A66,'End-to-End Workflows'!L:L,"Blocked") | G66: =COUNTIFS('End-to-End Workflows'!C:C,A66,'End-to-End Workflows'!L:L,"Not Run") | H66: =IF((D66+E66)=0,0,D66/(D66+E66)) | I66: =COUNTIFS('End-to-End Workflows'!C:C,A66,'End-to-End Workflows'!M:M,"Critical") | J66: docs/qa/regression/e2e/E2E-11-isolation.md
A67: E2E-12 · Enquiry from store to inbox | B67: End-to-End | C67: =COUNTIF('End-to-End Workflows'!C:C,A67) | D67: =COUNTIFS('End-to-End Workflows'!C:C,A67,'End-to-End Workflows'!L:L,"Pass") | E67: =COUNTIFS('End-to-End Workflows'!C:C,A67,'End-to-End Workflows'!L:L,"Fail") | F67: =COUNTIFS('End-to-End Workflows'!C:C,A67,'End-to-End Workflows'!L:L,"Blocked") | G67: =COUNTIFS('End-to-End Workflows'!C:C,A67,'End-to-End Workflows'!L:L,"Not Run") | H67: =IF((D67+E67)=0,0,D67/(D67+E67)) | I67: =COUNTIFS('End-to-End Workflows'!C:C,A67,'End-to-End Workflows'!M:M,"Critical") | J67: docs/qa/regression/e2e/E2E-12-enquiries.md
... A73: E2E-18 · Storefront chrome and search (shop experience) | B73: End-to-End | C73: =COUNTIF('End-to-End Workflows'!C:C,A73) | D73: =COUNTIFS('End-to-End Workflows'!C:C,A73,'End-to-End Workflows'!L:L,"Pass") | E73: =COUNTIFS('End-to-End Workflows'!C:C,A73,'End-to-End Workflows'!L:L,"Fail") | F73: =COUNTIFS('End-to-End Workflows'!C:C,A73,'End-to-End Workflows'!L:L,"Blocked") | G73: =COUNTIFS('End-to-End Workflows'!C:C,A73,'End-to-End Workflows'!L:L,"Not Run") | H73: =IF((D73+E73)=0,0,D73/(D73+E73)) | I73: =COUNTIFS('End-to-End Workflows'!C:C,A73,'End-to-End Workflows'!M:M,"Critical") | J73: docs/qa/regression/e2e/E2E-18-storefront.md

Sheet Vendor CMS
A1: Test Case ID | B1: Application/Portal | C1: Module Name | D1: Submodule/Feature | E1: Functionality | F1: Test Scenario | G1: Preconditions | H1: Test Data | I1: Step-by-Step Instructions | J1: Expected Result | K1: Actual Result | L1: Status | M1: Priority | N1: Test Type | O1: Executed By | P1: Execution Date | Q1: Defect/Bug ID | R1: Remarks/Additional Notes | S1: Role | T1: Smoke Run | U1: Regression Script
A2: VC-01-001 | B2: Vendor CMS | C2: VC-01 · Sign in, first password and session | D2: First password | E2: Short password refused | F2: The set-password page refuses passwords under 10 characters. | G2: Owner invite link open (private window) | H2: Password "Short12" | I2: 1. Type the short password in New Password and Confirm Password 2. Save 3. Verify the expected result. | J2: Refused with the minimum length message; the account stays without a password. | L2: Not Run | M2: High | N2: Validation | R2: Also: Boundary | S2: Store owner | T2: No | U2: docs/qa/regression/vendor-cms/VC-01-sign-in.md
A3: VC-01-002 | B3: Vendor CMS | C3: VC-01 · Sign in, first password and session | D3: First password | E3: Mismatch | F3: New and confirm password must match. | G3: Invite link open | H3: "HomeOrbit@2026" and "HomeOrbit@2027" | I3: 1. Type two different passwords 2. Save 3. Verify the expected result. | J3: Refused with a "passwords do not match" message. | L3: Not Run | M3: Medium | N3: Validation | S3: Store owner | T3: No | U3: docs/qa/regression/vendor-cms/VC-01-sign-in.md
A4: VC-01-003 | B4: Vendor CMS | C4: VC-01 · Sign in, first password and session | D4: First password | E4: Set password and land on dashboard | F4: A valid password signs the owner in. | G4: Invite link open | H4: Password "HomeOrbit@2026" | I4: 1. Type it twice 2. Save 3. Verify the expected result. | J4: Signed in at the store dashboard: greeting, today's date, Home Orbit, View store and Add product. | L4: Not Run | M4: Critical | N4: Functional | S4: Store owner | T4: Yes | U4: docs/qa/regression/vendor-cms/VC-01-sign-in.md
A5: VC-01-004 | B5: Vendor CMS | C5: VC-01 · Sign in, first password and session | D5: First password | E5: Link works once | F5: An invite link cannot be reused. | G5: Password already set with the link | H5: Same link | I5: 1. Open the same invite link again 2. Verify the expected result. | J5: The link is refused as used or expired. | L5: Not Run | M5: High | N5: Security/Permissions | S5: Store owner | T5: No | U5: docs/qa/regression/vendor-cms/VC-01-sign-in.md
A6: VC-01-005 | B6: Vendor CMS | C6: VC-01 · Sign in, first password and session | D6: Sign in | E6: Owner signs in without a code | F6: Two-step is optional for store staff. | G6: Owner has not set up two-step | H6: Owner email and password | I6: 1. Sign out 2. Sign in with email and password 3. Verify the expected result. | J6: The dashboard opens without a code step. | L6: Not Run | M6: High | N6: Functional | S6: Store owner | T6: No | U6: docs/qa/regression/vendor-cms/VC-01-sign-in.md
A7: VC-01-006 | B7: Vendor CMS | C7: VC-01 · Sign in, first password and session | D7: Sign in | E7: Optional two-step | F7: A store owner can turn on two-step and is then asked for the code. | G7: Owner signed in | H7: An authenticator app | I7: 1. Open your account (top bar name) 2. Set up two-step sign-in with the app 3. Sign out and in 4. Verify the expected result. | J7: Step 2 of 2 asks for the code; turning it off again is possible for store staff. | L7: Not Run | M7: Medium | N7: Security/Permissions | S7: Store owner | T7: No | U7: docs/qa/regression/vendor-cms/VC-01-sign-in.md
A8: VC-01-007 | B8: Vendor CMS | C8: VC-01 · Sign in, first password and session | D8: Sign in | E8: Wrong password | F8: A wrong password is refused. | G8: Signed out | H8: Wrong password | I8: 1. Sign in with the wrong password 2. Verify the expected result. | J8: "The email or password provided is incorrect." | L8: Not Run | M8: High | N8: Negative | S8: Store owner | T8: No | U8: docs/qa/regression/vendor-cms/VC-01-sign-in.md
A9: VC-02-001 | B9: Vendor CMS | C9: VC-02 · Store dashboard and navigation | D9: Header | E9: Greeting and actions | F9: The dashboard header matches the wireframe. | G9: Signed in as Home Orbit's owner (or super admin with Manage store on Home Orbit) | H9: — | I9: 1. Open http://localhost:3000/admin 2. Verify the expected result. | J9: "Good morning/afternoon/evening", today's date and Home Orbit, Import CSV (or View store) and Add product; "Your store isn't live yet" while a draft. | K9: "Good morning, Platform", Sat 10 Oct · Home Orbit, Import CSV, Add product, "Your store isn't live yet…"; figures Orders today 1, To ship 8, New enquiries 1. | L9: Pass | M9: High | N9: UI/UX | O9: Claude (Claude in Chrome) | P9: 2026-10-10 | R9: Run as super admin with Manage store. | S9: Store owner | T9: Yes | U9: docs/qa/regression/vendor-cms/VC-02-dashboard.md
A10: VC-02-002 | B10: Vendor CMS | C10: VC-02 · Store dashboard and navigation | D10: Menu | E10: Groups and plan meter | F10: The menu has the store groups and the plan usage. | G10: Signed in as Home Orbit's owner (or super admin with Manage store on Home Orbit) | H10: — | I10: 1. Read the left menu 2. Verify the expected result. | J10: Dashboard, Catalog, Sales, Marketing, Content, Store, Insights; Products 110 / 500 and the plan at the foot; no Vendors or Plans. | K10: Menu: Dashboard; Catalog; Sales; Marketing; Content; Store; Insights; Products 110 / 500 Starter plan; no Vendors or Plans. | L10: Pass | M10: High | N10: UI/UX | O10: Claude (Claude in Chrome) | P10: 2026-10-10 | R10: Also: Security/Permissions | S10: Store owner | T10: Yes | U10: docs/qa/regression/vendor-cms/VC-02-dashboard.md
A11: VC-02-003 | B11: Vendor CMS | C11: VC-02 · Store dashboard and navigation | D11: Menu | E11: Collapse persists | F11: The collapsed menu stays collapsed after reload. | G11: Signed in as Home Orbit's owner (or super admin with Manage store on Home Orbit) | H11: — | I11: 1. Press the collapse button at the bottom of the menu 2. Reload 3. Verify the expected result. | J11: The menu shows icons only (names on hover) and stays collapsed after reload. | L11: Not Run | M11: Low | N11: Data persistence | R11: Also: UI/UX | S11: Store owner | T11: No | U11: docs/qa/regression/vendor-cms/VC-02-dashboard.md
A12: VC-02-004 | B12: Vendor CMS | C12: VC-02 · Store dashboard and navigation | D12: Top bar | E12: Search with Ctrl K | F12: The top bar search jumps to products and other records. | G12: Signed in as Home Orbit's owner (or super admin with Manage store on Home Orbit) | H12: Search "soap" | I12: 1. Press Ctrl K 2. Type soap 3. Press Enter 4. Verify the expected result. | J12: Products opens filtered to soap dishes; arrow keys could pick Enquiries or Pages instead. | L12: Not Run | M12: Medium | N12: Functional | S12: Store owner | T12: No | U12: docs/qa/regression/vendor-cms/VC-02-dashboard.md
A13: VC-02-005 | B13: Vendor CMS | C13: VC-02 · Store dashboard and navigation | D13: Top bar | E13: Enquiry bell | F13: The bell counts new enquiries. | G13: Signed in as Home Orbit's owner (or super admin with Manage store on Home Orbit); new enquiries exist | H13: — | I13: 1. Read the bell number 2. Compare with Enquiries → New 3. Verify the expected result. | J13: The numbers match; the bell opens the inbox. | L13: Not Run | M13: Medium | N13: Integration | S13: Store owner | T13: No | U13: docs/qa/regression/vendor-cms/VC-02-dashboard.md
A14: VC-02-006 | B14: Vendor CMS | C14: VC-02 · Store dashboard and navigation | D14: Checklist | E14: Launch checklist | F14: The checklist shows the wireframe steps with Open links. | G14: Signed in as Home Orbit's owner (or super admin with Manage store on Home Orbit) | H14: — | I14: 1. Read the Launch checklist 2. Press Open on a step to do 3. Verify the expected result. | J14: Store name and logo, GST details, Razorpay connected, Shipping zones, catalogue and content steps; each open step has Open that goes to the right screen. | L14: Not Run | M14: High | N14: Functional | S14: Store owner | T14: No | U14: docs/qa/regression/vendor-cms/VC-02-dashboard.md
A15: VC-02-007 | B15: Vendor CMS | C15: VC-02 · Store dashboard and navigation | D15: Checklist | E15: Step ticks when done | F15: Completing a step ticks it. | G15: Signed in as Home Orbit's owner (or super admin with Manage store on Home Orbit) | H15: Save contact details (VC-03) | I15: 1. Note the checklist count 2. Complete a step 3. Reload the dashboard 4. Verify the expected result. | J15: That step is ticked and the count goes up. | L15: Not Run | M15: Medium | N15: Integration | S15: Store owner | T15: No | U15: docs/qa/regression/vendor-cms/VC-02-dashboard.md
A16: VC-02-008 | B16: Vendor CMS | C16: VC-02 · Store dashboard and navigation | D16: Figures | E16: Figures and charts | F16: Figures and charts use real orders. | G16: Signed in as Home Orbit's owner (or super admin with Manage store on Home Orbit); store selling: `pnpm demo:selling home-orbit` run; `pnpm demo:orders home-orbit` | H16: — | I16: 1. Read Orders today, Sales today, To ship, New enquiries, Low stock 2. Read Sales, last 14 days and Orders to ship 3. Verify the expected result. | J16: Figures show numbers; each figure opens its list; the chart has bars; Orders to ship lists waiting orders with Paid or COD. | L16: Not Run | M16: High | N16: Integration | S16: Store owner | T16: No | U16: docs/qa/regression/vendor-cms/VC-02-dashboard.md
A17: VC-02-009 | B17: Vendor CMS | C17: VC-02 · Store dashboard and navigation | D17: Lists | E17: Needs attention, quick actions, activity | F17: The lower cards show the store's state. | G17: Signed in as Home Orbit's owner (or super admin with Manage store on Home Orbit) | H17: — | I17: 1. Read Needs your attention, Quick actions, Recent activity, Coming up and the plan card 2. Verify the expected result. | J17: Policy pages still drafts are listed; Quick actions has Add product, Create page, Landing page, Upload media, Add category, Log an enquiry, Add dealer, Invite staff, Store settings; Recent activity shows who and when. | L17: Not Run | M17: Medium | N17: UI/UX | S17: Store owner | T17: No | U17: docs/qa/regression/vendor-cms/VC-02-dashboard.md
A18: VC-02-010 | B18: Vendor CMS | C18: VC-02 · Store dashboard and navigation | D18: Roles | E18: Dashboard follows role | F18: A catalog editor's dashboard hides what they cannot use. | G18: Signed in as a Catalog editor (VC-28) | H18: — | I18: 1. Open the dashboard 2. Verify the expected result. | J18: No launch checklist, no enquiry cards and only the quick actions they can use. | L18: Not Run | M18: High | N18: Security/Permissions | S18: Catalog editor | T18: No | U18: docs/qa/regression/vendor-cms/VC-02-dashboard.md
A19: VC-02-011 | B19: Vendor CMS | C19: VC-02 · Store dashboard and navigation | D19: Responsive | E19: Narrow screen | F19: Below 1024 px the menu opens from a button. | G19: Signed in as Home Orbit's owner (or super admin with Manage store on Home Orbit) | H19: Window 800 px wide | I19: 1. Narrow the window 2. Press ☰ 3. Verify the expected result. | J19: The menu opens over the page and closes again; nothing runs off the screen. | L19: Not Run | M19: Low | N19: UI/UX | S19: Store owner | T19: No | U19: docs/qa/regression/vendor-cms/VC-02-dashboard.md
A20: VC-03-001 | B20: Vendor CMS | C20: VC-03 · Store settings | D20: Layout | E20: Section links | F20: Settings is one page with links to each section. | G20: Signed in as Home Orbit's owner (or super admin with Manage store on Home Orbit) | H20: — | I20: 1. Open Store → Settings 2. Press Contact in the links at the top 3. Verify the expected result. | J20: Sections Branding, Contact, Grievance officer and labels, GST and invoices, Checkout and returns, Announcement bar, Policies, Search and analytics, Store status; the page scrolls to Contact. | L20: Not Run | M20: Medium | N20: UI/UX | S20: Store owner | T20: No | U20: docs/qa/regression/vendor-cms/VC-03-store-settings.md
A21: VC-03-002 | B21: Vendor CMS | C21: VC-03 · Store settings | D21: Contact | E21: Save contact and WhatsApp | F21: Contact details save and reach the store. | G21: Signed in as Home Orbit's owner (or super admin with Manage store on Home Orbit) | H21: Phone +91 98765 43210; WhatsApp 98765 43210; email care@homeorbit.example | I21: 1. Fill the Contact section 2. Save 3. Reload a product page on http://home-orbit.localhost:3000 4. Hover Ask on WhatsApp 5. Verify the expected result. | J21: "Updated successfully."; Ask on WhatsApp appears and links to https://wa.me/919876543210?text=… (91 added); /contact shows the phone and email; the footer shows them. | L21: Not Run | M21: Critical | N21: Functional | R21: Also: Integration | S21: Store owner | T21: Yes | U21: docs/qa/regression/vendor-cms/VC-03-store-settings.md
A22: VC-03-003 | B22: Vendor CMS | C22: VC-03 · Store settings | D22: Contact | E22: Invalid email | F22: An invalid contact email is refused. | G22: Signed in as Home Orbit's owner (or super admin with Manage store on Home Orbit) | H22: Email "care@" | I22: 1. Type the email 2. Save 3. Verify the expected result. | J22: Refused with an email format message. | L22: Not Run | M22: Medium | N22: Validation | S22: Store owner | T22: No | U22: docs/qa/regression/vendor-cms/VC-03-store-settings.md
A23: VC-03-004 | B23: Vendor CMS | C23: VC-03 · Store settings | D23: Grievance officer | E23: Shown on the store | F23: The grievance officer shows on contact and footer. | G23: Signed in as Home Orbit's owner (or super admin with Manage store on Home Orbit) | H23: Name Priya Shah, Director, grievance@homeorbit.example, phone | I23: 1. Fill Grievance officer and labels 2. Save 3. Open http://home-orbit.localhost:3000/contact and the footer 4. Verify the expected result. | J23: Both show the grievance officer's name, designation and contact. | L23: Not Run | M23: High | N23: Integration | S23: Store owner | T23: No | U23: docs/qa/regression/vendor-cms/VC-03-store-settings.md
A24: VC-03-005 | B24: Vendor CMS | C24: VC-03 · Store settings | D24: GST | E24: GSTIN read-only | F24: The store's GSTIN cannot be edited here. | G24: Signed in as Home Orbit's owner (or super admin with Manage store on Home Orbit) | H24: — | I24: 1. Open GST and invoices 2. Verify the expected result. | J24: GSTIN shows read-only (changed only by the platform). | L24: Not Run | M24: Medium | N24: Security/Permissions | S24: Store owner | T24: No | U24: docs/qa/regression/vendor-cms/VC-03-store-settings.md
A25: VC-03-006 | B25: Vendor CMS | C25: VC-03 · Store settings | D25: Returns | E25: Return window | F25: The return window shows on product pages. | G25: Signed in as Home Orbit's owner (or super admin with Manage store on Home Orbit); store selling: `pnpm demo:selling home-orbit` run | H25: Return window 10 days | I25: 1. Set Return window to 10 2. Save 3. Open a product on http://home-orbit.localhost:3000 4. Verify the expected result. | J25: "10-day returns" in the promises line; 0 and 91 are refused (0 to 90 allowed). | L25: Not Run | M25: Medium | N25: Integration | R25: Also: Boundary | S25: Store owner | T25: No | U25: docs/qa/regression/vendor-cms/VC-03-store-settings.md
A26: VC-03-007 | B26: Vendor CMS | C26: VC-03 · Store settings | D26: Announcement bar | E26: Store announcement | F26: The announcement bar text shows on the store when on. | G26: Signed in as Home Orbit's owner (or super admin with Manage store on Home Orbit) | H26: Text "Free delivery above ₹999", enabled | I26: 1. Fill and enable Announcement bar 2. Save 3. Reload http://home-orbit.localhost:3000 4. Verify the expected result. | J26: The text shows at the top of every store page (unless a live scheme's announcement replaces it). | L26: Not Run | M26: Medium | N26: Integration | S26: Store owner | T26: No | U26: docs/qa/regression/vendor-cms/VC-03-store-settings.md
A27: VC-03-008 | B27: Vendor CMS | C27: VC-03 · Store settings | D27: Store status | E27: Maintenance mode | F27: Maintenance mode closes the store and warns staff. | G27: Signed in as Home Orbit's owner (or super admin with Manage store on Home Orbit) | H27: Tick Maintenance mode | I27: 1. Tick Maintenance mode 2. Save 3. Open http://home-orbit.localhost:3000 4. Untick and Save 5. Verify the expected result. | J27: A yellow "Maintenance mode is on" bar on every CMS page and in Needs your attention; the store shows "Home Orbit will be back soon"; unticking reopens it. | L27: Not Run | M27: High | N27: Integration | S27: Store owner | T27: No | U27: docs/qa/regression/vendor-cms/VC-03-store-settings.md
A28: VC-03-009 | B28: Vendor CMS | C28: VC-03 · Store settings | D28: Permissions | E28: Read-only for catalog editor | F28: A catalog editor sees settings read-only. | G28: Signed in as Catalog editor | H28: — | I28: 1. Open Store → Settings 2. Verify the expected result. | J28: No Save button; fields cannot be changed. | L28: Not Run | M28: High | N28: Security/Permissions | S28: Catalog editor | T28: No | U28: docs/qa/regression/vendor-cms/VC-03-store-settings.md
A29: VC-04-001 | B29: Vendor CMS | C29: VC-04 · Products and product editor | D29: List | E29: Header, tabs and columns | F29: The product list matches the wireframe. | G29: Signed in as Home Orbit's owner (or super admin with Manage store on Home Orbit) | H29: — | I29: 1. Open Catalog → Products 2. Verify the expected result. | J29: "110 products · 500 allowed on Starter", Import, Export, Add product; tabs All, Active, Draft, Archived with counts; rows with photo, model number, category, finishes, price or range, stock, status, updated. | K29: "110 products · 500 allowed on Starter", Import, Export, Add product, tabs All 110 / Active 110 / Draft 0 / Archived 0, Category filter with subcategories. | L29: Pass | M29: High | N29: UI/UX | O29: Claude (Claude in Chrome) | P29: 2026-10-10 | S29: Store owner | T29: Yes | U29: docs/qa/regression/vendor-cms/VC-04-products.md
A30: VC-04-002 | B30: Vendor CMS | C30: VC-04 · Products and product editor | D30: List | E30: Search by model number | F30: Search finds a product by model number. | G30: Signed in as Home Orbit's owner (or super admin with Manage store on Home Orbit) | H30: HOPH-504 | I30: 1. Type HOPH-504 in the search 2. Verify the expected result. | J30: One result: the Feather pull handle. | L30: Not Run | M30: High | N30: Functional | S30: Store owner | T30: Yes | U30: docs/qa/regression/vendor-cms/VC-04-products.md
A31: VC-04-003 | B31: Vendor CMS | C31: VC-04 · Products and product editor | D31: List | E31: Search by exact SKU | F31: An exact variant SKU finds its product. | G31: Signed in as Home Orbit's owner (or super admin with Manage store on Home Orbit); variants created (VC-04-012) | H31: HOPH-504-8-INCH-ANTIQUE | I31: 1. Search the SKU 2. Verify the expected result. | J31: The parent product is listed. | L31: Not Run | M31: Medium | N31: Functional | S31: Store owner | T31: No | U31: docs/qa/regression/vendor-cms/VC-04-products.md
A32: VC-04-004 | B32: Vendor CMS | C32: VC-04 · Products and product editor | D32: List | E32: Category filter with subcategories | F32: Filtering by a parent category includes its children. | G32: Signed in as Home Orbit's owner (or super admin with Manage store on Home Orbit) | H32: Category Door hardware | I32: 1. Pick Category = Door hardware 2. Verify the expected result. | J32: 50 products from Aldrops, Pull handles, Glass door handles and Door stoppers. | L32: Not Run | M32: Medium | N32: Functional | S32: Store owner | T32: No | U32: docs/qa/regression/vendor-cms/VC-04-products.md
A33: VC-04-005 | B33: Vendor CMS | C33: VC-04 · Products and product editor | D33: List | E33: Stock filter | F33: The stock filter shows low and out-of-stock products. | G33: Signed in as Home Orbit's owner (or super admin with Manage store on Home Orbit); store selling: `pnpm demo:selling home-orbit` run | H33: Stock = Out of stock | I33: 1. Pick the stock filter 2. Verify the expected result. | J33: Only products whose variants are out of stock; an empty state when none. | L33: Not Run | M33: Low | N33: Functional | S33: Store owner | T33: No | U33: docs/qa/regression/vendor-cms/VC-04-products.md
A34: VC-04-006 | B34: Vendor CMS | C34: VC-04 · Products and product editor | D34: Bulk | E34: Publish and archive selected | F34: Bulk actions act on ticked rows and report failures. | G34: Signed in as Home Orbit's owner (or super admin with Manage store on Home Orbit) | H34: Tick two products, one without a photo | I34: 1. Tick two rows 2. Press Archive 3. Then tick them and Publish 4. Verify the expected result. | J34: Archive moves both to Archived; Publish activates the one that can and lists the other with the reason (no photo). | L34: Not Run | M34: High | N34: Functional | R34: Also: Negative | S34: Store owner | T34: No | U34: docs/qa/regression/vendor-cms/VC-04-products.md
A35: VC-04-007 | B35: Vendor CMS | C35: VC-04 · Products and product editor | D35: Bulk | E35: Change category | F35: Bulk change category moves products. | G35: Signed in as Home Orbit's owner (or super admin with Manage store on Home Orbit) | H35: Two products → Towel rings | I35: 1. Tick two products 2. Press Change category 3. Pick Towel rings and confirm 4. Verify the expected result. | J35: Both now show Towel rings as their category. | L35: Not Run | M35: Medium | N35: Functional | S35: Store owner | T35: No | U35: docs/qa/regression/vendor-cms/VC-04-products.md
A36: VC-04-008 | B36: Vendor CMS | C36: VC-04 · Products and product editor | D36: Export | E36: Export and export selected | F36: Export gives the import template's columns. | G36: Signed in as Home Orbit's owner (or super admin with Manage store on Home Orbit) | H36: — | I36: 1. Press Export 2. Tick two rows and press Export selected 3. Verify the expected result. | J36: CSVs in the template columns (with option.<axis> columns); the selected export has only those two; importing the file unchanged reports no changes. | L36: Not Run | M36: Medium | N36: Functional | R36: Also: Integration | S36: Store owner | T36: No | U36: docs/qa/regression/vendor-cms/VC-04-products.md
A37: VC-04-009 | B37: Vendor CMS | C37: VC-04 · Products and product editor | D37: Editor | E37: Sections and side column | F37: The editor has the wireframe's sections. | G37: Signed in as Home Orbit's owner (or super admin with Manage store on Home Orbit) | H37: Open HOPH-504 | I37: 1. Open the product 2. Verify the expected result. | J37: Basics, Photos and videos, Specifications, Finishes prices and stock, Price and GST, Documents, Spare parts and related products, Search engines; side: Status, How shoppers buy, Legal details, weight and box size, Featured, Offers and reviews. | L37: Not Run | M37: Medium | N37: UI/UX | S37: Store owner | T37: No | U37: docs/qa/regression/vendor-cms/VC-04-products.md
A38: VC-04-010 | B38: Vendor CMS | C38: VC-04 · Products and product editor | D38: Editor | E38: GST preview | F38: The GST split preview follows the price. | G38: Signed in as Home Orbit's owner (or super admin with Manage store on Home Orbit) | H38: Price ₹1,849, GST 18% | I38: 1. Enter the price 2. Read the line under Price and GST 3. Verify the expected result. | J38: "For ₹1,849.00 the taxable value is ₹1,566.95 and GST is ₹282.05" (prices include GST). | L38: Not Run | M38: Medium | N38: Functional | S38: Store owner | T38: No | U38: docs/qa/regression/vendor-cms/VC-04-products.md
A39: VC-04-011 | B39: Vendor CMS | C39: VC-04 · Products and product editor | D39: Editor | E39: Finish offered reaches the store | F39: Unticking a finish removes it from the store. | G39: Signed in as Home Orbit's owner (or super admin with Manage store on Home Orbit) | H39: HOPH-504: untick Black matt | I39: 1. Untick Black matt under Specifications 2. Save 3. Open the product on http://home-orbit.localhost:3000 4. Tick it again and Save 5. Verify the expected result. | J39: Black matt is gone from the finish choices, then back. | L39: Not Run | M39: High | N39: Integration | S39: Store owner | T39: No | U39: docs/qa/regression/vendor-cms/VC-04-products.md
A40: VC-04-012 | B40: Vendor CMS | C40: VC-04 · Products and product editor | D40: Variants | E40: Create variants | F40: Variants are created for every combination once. | G40: Signed in as Home Orbit's owner (or super admin with Manage store on Home Orbit) | H40: HOPH-504 with 3 sizes and 5 finishes | I40: 1. Press Create variants for every combination 2. Press it again 3. Verify the expected result. | J40: "15 variants created" with codes like HOPH-504-8-INCH-ANTIQUE; the second press says "Every combination already has a variant". | L40: Not Run | M40: High | N40: Functional | S40: Store owner | T40: No | U40: docs/qa/regression/vendor-cms/VC-04-products.md
A41: VC-04-013 | B41: Vendor CMS | C41: VC-04 · Products and product editor | D41: Rules | E41: Active needs a photo | F41: A product cannot be active without a photo. | G41: Signed in as Home Orbit's owner (or super admin with Manage store on Home Orbit) | H41: Test handle, TEST-1, Aldrops, Active, no photo | I41: 1. Add product with these values 2. Save 3. Verify the expected result. | J41: Refused with "Add at least one photo before making the product active" (and a label details note); saving as Draft works. | L41: Not Run | M41: Critical | N41: Validation | S41: Store owner | T41: Yes | U41: docs/qa/regression/vendor-cms/VC-04-products.md
A42: VC-04-014 | B42: Vendor CMS | C42: VC-04 · Products and product editor | D42: Rules | E42: Online selling needs price and HSN | F42: Buy online needs a selling price and HSN. | G42: Signed in as Home Orbit's owner (or super admin with Manage store on Home Orbit) | H42: How shoppers buy = Buy online, no price | I42: 1. Set Buy online without a price 2. Make it Active and Save 3. Verify the expected result. | J42: "Products sold online need a selling price and an HSN code"; back to "Request a quote only" saves. | L42: Not Run | M42: High | N42: Validation | S42: Store owner | T42: No | U42: docs/qa/regression/vendor-cms/VC-04-products.md
A43: VC-04-015 | B43: Vendor CMS | C43: VC-04 · Products and product editor | D43: Rules | E43: Duplicate model number | F43: A model number used by another product is refused. | G43: Signed in as Home Orbit's owner (or super admin with Manage store on Home Orbit) | H43: Model number HOPH-504 on a new product | I43: 1. Create a product with model number HOPH-504 2. Save 3. Verify the expected result. | J43: Refused as already used in this store. | L43: Not Run | M43: High | N43: Validation | R43: Requires confirmation that model numbers are unique per store. | S43: Store owner | T43: No | U43: docs/qa/regression/vendor-cms/VC-04-products.md
A44: VC-04-016 | B44: Vendor CMS | C44: VC-04 · Products and product editor | D44: Rules | E44: Plan product limit | F44: Products beyond the plan limit are refused. | G44: A store at its plan's product limit (lower a test plan's limit) | H44: One more product | I44: 1. Try to add a product past the limit 2. Verify the expected result. | J44: Refused with the plan limit message; the list header shows the limit. | L44: Not Run | M44: Medium | N44: Boundary | R44: Use a test plan with a small limit on a throw-away store. | S44: Store owner | T44: No | U44: docs/qa/regression/vendor-cms/VC-04-products.md
A45: VC-04-017 | B45: Vendor CMS | C45: VC-04 · Products and product editor | D45: Persistence | E45: Edit and reload | F45: Edits persist after reload and appear on the store. | G45: Signed in as Home Orbit's owner (or super admin with Manage store on Home Orbit) | H45: Short description "QA edit" | I45: 1. Change the short description of an active product 2. Save 3. Reload the editor 4. Open it on the store 5. Verify the expected result. | J45: The new text shows in both places. | L45: Not Run | M45: High | N45: Data persistence | R45: Also: Integration | S45: Store owner | T45: No | U45: docs/qa/regression/vendor-cms/VC-04-products.md
A46: VC-04-018 | B46: Vendor CMS | C46: VC-04 · Products and product editor | D46: Versions | E46: Restore a version | F46: An earlier version can be restored. | G46: Signed in as Home Orbit's owner (or super admin with Manage store on Home Orbit) | H46: Product edited twice | I46: 1. Open the Versions tab 2. Restore the earlier version 3. Verify the expected result. | J46: The product returns to the earlier values. | L46: Not Run | M46: Low | N46: Functional | S46: Store owner | T46: No | U46: docs/qa/regression/vendor-cms/VC-04-products.md
A47: VC-05-001 | B47: Vendor CMS | C47: VC-05 · Categories | D47: Tree | E47: Tree with counts | F47: Categories show as a tree with product counts. | G47: Signed in as Home Orbit's owner (or super admin with Manage store on Home Orbit) | H47: — | I47: 1. Open Catalog → Categories 2. Verify the expected result. | J47: Door hardware 50 with its four subcategories, Home decor, Bathroom accessories and children, with counts. | K47: 13 categories; tree with counts (Door hardware 50, Aldrops 18, Pull handles 8, Glass door handles 12, …). | L47: Pass | M47: High | N47: UI/UX | O47: Claude (Claude in Chrome) | P47: 2026-10-10 | S47: Store owner | T47: Yes | U47: docs/qa/regression/vendor-cms/VC-05-categories.md
A48: VC-05-002 | B48: Vendor CMS | C48: VC-05 · Categories | D48: Tree | E48: Drag to reorder | F48: Dragging reorders and the order is kept. | G48: Signed in as Home Orbit's owner (or super admin with Manage store on Home Orbit) | H48: Towel racks above Towel rings | I48: 1. Drag Towel racks above Towel rings 2. Reload 3. Open the store menu on http://home-orbit.localhost:3000 4. Verify the expected result. | J48: The new order stays after reload and is the order of menus and tiles. | L48: Not Run | M48: High | N48: Data persistence | R48: Also: Integration | S48: Store owner | T48: No | U48: docs/qa/regression/vendor-cms/VC-05-categories.md
A49: VC-05-003 | B49: Vendor CMS | C49: VC-05 · Categories | D49: Tree | E49: Nest by dropping | F49: Dropping onto a category nests it; more than 3 levels is refused. | G49: Signed in as Home Orbit's owner (or super admin with Manage store on Home Orbit) | H49: A test category | I49: 1. Drop Test category onto Aldrops (level 3) 2. Try to drop another category onto Test category (level 4) 3. Verify the expected result. | J49: The first works; the 4th level is refused with a message. | L49: Not Run | M49: Medium | N49: Boundary | S49: Store owner | T49: No | U49: docs/qa/regression/vendor-cms/VC-05-categories.md
A50: VC-05-004 | B50: Vendor CMS | C50: VC-05 · Categories | D50: Tree | E50: Keyboard moves | F50: Alt + arrow keys move a category. | G50: Signed in as Home Orbit's owner (or super admin with Manage store on Home Orbit) | H50: — | I50: 1. Focus a category name 2. Press Alt + Up 3. Reload 4. Verify the expected result. | J50: It moves up one place and stays there. | L50: Not Run | M50: Low | N50: Accessibility | S50: Store owner | T50: No | U50: docs/qa/regression/vendor-cms/VC-05-categories.md
A51: VC-05-005 | B51: Vendor CMS | C51: VC-05 · Categories | D51: Form | E51: Slug from name | F51: The slug fills from the name. | G51: Signed in as Home Orbit's owner (or super admin with Manage store on Home Orbit) | H51: Name "Test category" | I51: 1. Create a category with only the name 2. Save 3. Verify the expected result. | J51: Slug test-category; it shows in the tree. | L51: Not Run | M51: Medium | N51: Functional | S51: Store owner | T51: No | U51: docs/qa/regression/vendor-cms/VC-05-categories.md
A52: VC-05-006 | B52: Vendor CMS | C52: VC-05 · Categories | D52: Form | E52: Name required | F52: A category needs a name. | G52: Signed in as Home Orbit's owner (or super admin with Manage store on Home Orbit) | H52: Empty name | I52: 1. Create a category with no name 2. Save 3. Verify the expected result. | J52: Refused with a required field message. | L52: Not Run | M52: Medium | N52: Validation | S52: Store owner | T52: No | U52: docs/qa/regression/vendor-cms/VC-05-categories.md
A53: VC-05-007 | B53: Vendor CMS | C53: VC-05 · Categories | D53: Form | E53: No loops | F53: A category cannot be its own parent or descendant's child. | G53: Signed in as Home Orbit's owner (or super admin with Manage store on Home Orbit) | H53: Door hardware parent = Aldrops | I53: 1. Set Door hardware's parent to Aldrops 2. Save 3. Verify the expected result. | J53: Refused (would create a loop). | L53: Not Run | M53: Medium | N53: Negative | S53: Store owner | T53: No | U53: docs/qa/regression/vendor-cms/VC-05-categories.md
A54: VC-05-008 | B54: Vendor CMS | C54: VC-05 · Categories | D54: Form | E54: View on store | F54: View on store opens the category page. | G54: Signed in as Home Orbit's owner (or super admin with Manage store on Home Orbit) | H54: Aldrops | I54: 1. Open Aldrops 2. Press View on store 3. Verify the expected result. | J54: http://home-orbit.localhost:3000/c/door-hardware/aldrops opens. | L54: Not Run | M54: Low | N54: Integration | S54: Store owner | T54: No | U54: docs/qa/regression/vendor-cms/VC-05-categories.md
A55: VC-05-009 | B55: Vendor CMS | C55: VC-05 · Categories | D55: Form | E55: Hide from store | F55: Unticking Show on store hides the category. | G55: Signed in as Home Orbit's owner (or super admin with Manage store on Home Orbit) | H55: Test category with a product | I55: 1. Untick Show on store 2. Save 3. Open its store address 4. Verify the expected result. | J55: The category is gone from menus and its address shows not found. | L55: Not Run | M55: Medium | N55: Integration | S55: Store owner | T55: No | U55: docs/qa/regression/vendor-cms/VC-05-categories.md
A56: VC-06-001 | B56: Vendor CMS | C56: VC-06 · Attribute sets | D56: Layout | E56: Sets and table | F56: Attribute sets show the sets list and the field table. | G56: Signed in as Home Orbit's owner (or super admin with Manage store on Home Orbit) | H56: Open Aldrops | I56: 1. Open Catalog → Attribute sets 2. Open Aldrops 3. Verify the expected result. | J56: Sets on the left with "N fields · M categories"; a table of fields with Filter, Finish option, Compare and Required ticks; Options for Finish with swatches. | L56: Not Run | M56: Medium | N56: UI/UX | S56: Store owner | T56: No | U56: docs/qa/regression/vendor-cms/VC-06-attribute-sets.md
A57: VC-06-002 | B57: Vendor CMS | C57: VC-06 · Attribute sets | D57: Editor | E57: Live table | F57: The table follows edits before saving. | G57: Signed in as Home Orbit's owner (or super admin with Manage store on Home Orbit) | H57: Rename a field label | I57: 1. Change a field label below the table 2. Verify the expected result. | J57: The table shows the new label as you type. | L57: Not Run | M57: Low | N57: UI/UX | S57: Store owner | T57: No | U57: docs/qa/regression/vendor-cms/VC-06-attribute-sets.md
A58: VC-06-003 | B58: Vendor CMS | C58: VC-06 · Attribute sets | D58: Validation | E58: Unique codes | F58: Two fields cannot share a code. | G58: Signed in as Home Orbit's owner (or super admin with Manage store on Home Orbit) | H58: Two fields with code "finish" | I58: 1. Add a field with an existing code 2. Save 3. Verify the expected result. | J58: Refused naming the duplicate code. | L58: Not Run | M58: High | N58: Validation | S58: Store owner | T58: No | U58: docs/qa/regression/vendor-cms/VC-06-attribute-sets.md
A59: VC-06-004 | B59: Vendor CMS | C59: VC-06 · Attribute sets | D59: Validation | E59: Options required | F59: Select fields need options. | G59: Signed in as Home Orbit's owner (or super admin with Manage store on Home Orbit) | H59: A select field with no options | I59: 1. Add a select field without options 2. Save 3. Verify the expected result. | J59: Refused with a message about missing options. | L59: Not Run | M59: Medium | N59: Validation | S59: Store owner | T59: No | U59: docs/qa/regression/vendor-cms/VC-06-attribute-sets.md
A60: VC-06-005 | B60: Vendor CMS | C60: VC-06 · Attribute sets | D60: Validation | E60: At most 3 variant options | F60: No more than 3 fields can be finish/variant options. | G60: Signed in as Home Orbit's owner (or super admin with Manage store on Home Orbit) | H60: Tick Finish option on a 4th field | I60: 1. Tick a 4th variant option 2. Save 3. Verify the expected result. | J60: Refused: at most 3 variant options. | L60: Not Run | M60: Medium | N60: Boundary | S60: Store owner | T60: No | U60: docs/qa/regression/vendor-cms/VC-06-attribute-sets.md
... A70: VC-08-003 | B70: Vendor CMS | C70: VC-08 · Import and export | D70: Check | E70: Error report | F70: The error report downloads. | G70: A checked file with errors | H70: — | I70: 1. Press Download error report 2. Verify the expected result. | J70: A CSV of the bad rows with reasons. | L70: Not Run | M70: Medium | N70: Functional | S70: Store owner | T70: No | U70: docs/qa/regression/vendor-cms/VC-08-import.md
A71: VC-08-004 | B71: Vendor CMS | C71: VC-08 · Import and export | D71: Import | E71: Import ready rows | F71: Ready rows import in the background. | G71: A checked file | H71: Two new rows with two finishes; one price change | I71: 1. Press Import N ready rows 2. Wait about a minute 3. Read Recent imports and the terminal 4. Verify the expected result. | J71: Status Imported; an email printed in the terminal; the new product is a draft with both finishes; the existing SKU has its new price. | L71: Not Run | M71: High | N71: Functional | R71: Also: Integration | S71: Store owner | T71: No | U71: docs/qa/regression/vendor-cms/VC-08-import.md
A72: VC-08-005 | B72: Vendor CMS | C72: VC-08 · Import and export | D72: Import | E72: Wrong file | F72: A non-CSV or wrong columns file is refused. | G72: Signed in as Home Orbit's owner (or super admin with Manage store on Home Orbit) | H72: A .xlsx or a CSV with other headers | I72: 1. Upload the file 2. Verify the expected result. | J72: Refused with a clear message about the format or missing columns. | L72: Not Run | M72: Medium | N72: Negative | S72: Store owner | T72: No | U72: docs/qa/regression/vendor-cms/VC-08-import.md
A73: VC-08-006 | B73: Vendor CMS | C73: VC-08 · Import and export | D73: Import | E73: Stock and prices only | F73: The stock and prices import updates existing SKUs. | G73: Signed in as Home Orbit's owner (or super admin with Manage store on Home Orbit); variants exist | H73: sku,price,mrp,stock_qty for 2 SKUs; 1 unknown SKU | I73: 1. Choose Stock and prices only 2. Upload and import 3. Verify the expected result. | J73: Known SKUs update; the unknown SKU is listed as an error. | L73: Not Run | M73: Medium | N73: Functional | R73: Also: Negative | S73: Store owner | T73: No | U73: docs/qa/regression/vendor-cms/VC-08-import.md
A74: VC-08-007 | B74: Vendor CMS | C74: VC-08 · Import and export | D74: Permissions | E74: Who can import | F74: Only owners, managers and catalog editors import. | G74: Signed in as Order manager | H74: — | I74: 1. Look for Import and export in the menu 2. Open http://localhost:3000/admin/import 3. Verify the expected result. | J74: Not in the menu; the page refuses access. | L74: Not Run | M74: Medium | N74: Security/Permissions | S74: Order manager | T74: No | U74: docs/qa/regression/vendor-cms/VC-08-import.md
A75: VC-09-001 | B75: Vendor CMS | C75: VC-09 · Media library | D75: Library | E75: Grid and tabs | F75: The media library shows a grid with tabs and storage. | G75: Signed in as Home Orbit's owner (or super admin with Manage store on Home Orbit) | H75: — | I75: 1. Open Catalog → Media 2. Verify the expected result. | J75: Tabs All, Images, Documents, Videos; search; storage meter against the plan; a grid of files. | L75: Not Run | M75: Medium | N75: UI/UX | S75: Store owner | T75: No | U75: docs/qa/regression/vendor-cms/VC-09-media.md
A76: VC-09-002 | B76: Vendor CMS | C76: VC-09 · Media library | D76: Detail | E76: Where used and alt text | F76: Selecting a file shows its details and where it is used. | G76: Signed in as Home Orbit's owner (or super admin with Manage store on Home Orbit) | H76: A product photo | I76: 1. Click a photo 2. Edit Alt text and Save in place 3. Reload 4. Verify the expected result. | J76: Preview, alt text, type and size, sizes made, used by products/categories; the new alt text stays after reload. | L76: Not Run | M76: Medium | N76: Data persistence | S76: Store owner | T76: No | U76: docs/qa/regression/vendor-cms/VC-09-media.md
A77: VC-09-003 | B77: Vendor CMS | C77: VC-09 · Media library | D77: Upload | E77: Alt text required | F77: An image cannot be saved without alt text. | G77: Signed in as Home Orbit's owner (or super admin with Manage store on Home Orbit) | H77: A JPG, no alt text | I77: 1. Upload the image without alt text 2. Save 3. Verify the expected result. | J77: Refused; with alt text it saves and the storage meter goes up. | L77: Not Run | M77: High | N77: Validation | S77: Store owner | T77: No | U77: docs/qa/regression/vendor-cms/VC-09-media.md
A78: VC-09-004 | B78: Vendor CMS | C78: VC-09 · Media library | D78: Upload | E78: Unsupported file | F78: Files that are not images, PDFs or allowed types are refused. | G78: Signed in as Home Orbit's owner (or super admin with Manage store on Home Orbit) | H78: An .exe or .zip | I78: 1. Try to upload it 2. Verify the expected result. | J78: Refused with the allowed types. | L78: Not Run | M78: Medium | N78: Negative | S78: Store owner | T78: No | U78: docs/qa/regression/vendor-cms/VC-09-media.md
A79: VC-09-005 | B79: Vendor CMS | C79: VC-09 · Media library | D79: Delete | E79: Delete a file in use | F79: Deleting warns when a file is used. | G79: Signed in as Home Orbit's owner (or super admin with Manage store on Home Orbit) | H79: A photo used by a product | I79: 1. Select it 2. Press Delete 3. Verify the expected result. | J79: A warning lists where it is used before confirming. | L79: Not Run | M79: Medium | N79: Negative | R79: Requires confirmation of whether deleting in-use files is blocked or only warned. | S79: Store owner | T79: No | U79: docs/qa/regression/vendor-cms/VC-09-media.md
A80: VC-09-006 | B80: Vendor CMS | C80: VC-09 · Media library | D80: Search | E80: Search media | F80: Search filters by name or alt text. | G80: Signed in as Home Orbit's owner (or super admin with Manage store on Home Orbit) | H80: "towel" | I80: 1. Type towel 2. Verify the expected result. | J80: Only matching files remain. | L80: Not Run | M80: Low | N80: Functional | S80: Store owner | T80: No | U80: docs/qa/regression/vendor-cms/VC-09-media.md
A81: VC-10-001 | B81: Vendor CMS | C81: VC-10 · Orders and order detail | D81: List | E81: Tabs and columns | F81: Orders list shows tabs and separate order, payment and delivery state. | G81: Signed in as Home Orbit's owner (or super admin with Manage store on Home Orbit); store selling: `pnpm demo:selling home-orbit` run; an order from E2E-04 | H81: — | I81: 1. Open Sales → Orders 2. Verify the expected result. | J81: Tabs All, To pack, Packed, Shipped, Out for delivery, Delivered, Awaiting payment, Cancelled, Returns with counts; the new order shows "COD, to collect" and "Not shipped". | K81: Tabs All 23, To pack 4, Packed 4, Shipped 3, Out for delivery 0, Delivered 12, Awaiting payment 0, Cancelled 0, Returns 0; search, Placed, Payment and State filters; Mark packed, Shipped from CSV, Download invoices. | L81: Pass | M81: Critical | N81: UI/UX | O81: Claude (Claude in Chrome) | P81: 2026-10-10 | S81: Store owner | T81: Yes | U81: docs/qa/regression/vendor-cms/VC-10-orders.md
A82: VC-10-002 | B82: Vendor CMS | C82: VC-10 · Orders and order detail | D82: List | E82: Search by number and phone | F82: Search finds orders by number and phone. | G82: An order exists | H82: Order number; phone 98765 | I82: 1. Search the order number 2. Search 98765 3. Verify the expected result. | J82: The order is found both ways. | L82: Not Run | M82: High | N82: Functional | S82: Store owner | T82: No | U82: docs/qa/regression/vendor-cms/VC-10-orders.md
A83: VC-10-003 | B83: Vendor CMS | C83: VC-10 · Orders and order detail | D83: List | E83: Filters | F83: Placed, payment and state filters narrow the list. | G83: Several orders | H83: Payment = COD | I83: 1. Pick each filter 2. Verify the expected result. | J83: Rows and counts follow the filters; clearing restores the list. | L83: Not Run | M83: Medium | N83: Functional | S83: Store owner | T83: No | U83: docs/qa/regression/vendor-cms/VC-10-orders.md
A84: VC-10-004 | B84: Vendor CMS | C84: VC-10 · Orders and order detail | D84: Detail | E84: GST split by place of supply | F84: An order within the store's state shows CGST and SGST. | G84: Order to pincode 411045 (Maharashtra) from a Maharashtra GSTIN | H84: — | I84: 1. Open the order 2. Verify the expected result. | J84: Items with CGST and SGST, the place of supply line, the customer ("first order"), address and payment. | L84: Not Run | M84: High | N84: Functional | S84: Store owner | T84: No | U84: docs/qa/regression/vendor-cms/VC-10-orders.md
A85: VC-10-005 | B85: Vendor CMS | C85: VC-10 · Orders and order detail | D85: Fulfilment | E85: Mark as packed creates the invoice | F85: Packing issues the GST invoice. | G85: A confirmed order | H85: — | I85: 1. Press Mark as packed and confirm 2. Read Invoice 3. Press Download invoice 4. Verify the expected result. | J85: The parcel shows Packed; Invoice lists INV/26-27/00001 (next number); the GST invoice opens. | L85: Not Run | M85: Critical | N85: Functional | S85: Store owner | T85: Yes | U85: docs/qa/regression/vendor-cms/VC-10-orders.md
A86: VC-10-006 | B86: Vendor CMS | C86: VC-10 · Orders and order detail | D86: Fulfilment | E86: Ship, out for delivery, delivered | F86: The parcel moves through shipping to delivered. | G86: A packed order | H86: Tracking number 12345, courier Delhivery | I86: 1. Type the tracking number 2. Press Save and tell the shopper it shipped 3. Press Out for delivery 4. Press Delivered 5. Verify the expected result. | J86: The order reads Completed, Paid, Delivered; the timeline ends with "₹… collected in cash on delivery"; messages are queued for each step. | L86: Not Run | M86: Critical | N86: Functional | R86: Also: Integration | S86: Store owner | T86: Yes | U86: docs/qa/regression/vendor-cms/VC-10-orders.md
A87: VC-10-007 | B87: Vendor CMS | C87: VC-10 · Orders and order detail | D87: Fulfilment | E87: Steps cannot be skipped backwards | F87: A delivered parcel cannot go back to packed. | G87: A delivered order | H87: — | I87: 1. Look for actions that move it back 2. Verify the expected result. | J87: No backwards actions; the state stays Delivered. | L87: Not Run | M87: Medium | N87: Negative | S87: Store owner | T87: No | U87: docs/qa/regression/vendor-cms/VC-10-orders.md
A88: VC-10-008 | B88: Vendor CMS | C88: VC-10 · Orders and order detail | D88: Refund | E88: Partial refund | F88: A partial refund records a credit note. | G88: A delivered order | H88: ₹100, reason, UPI reference | I88: 1. Press Refund 2. Enter ₹100, a reason and the reference 3. Confirm 4. Verify the expected result. | J88: Payment shows Partly refunded; the invoice card lists credit note CN/26-27/00001. | L88: Not Run | M88: High | N88: Functional | S88: Store owner | T88: No | U88: docs/qa/regression/vendor-cms/VC-10-orders.md
A89: VC-10-009 | B89: Vendor CMS | C89: VC-10 · Orders and order detail | D89: Refund | E89: Refund over the amount | F89: A refund larger than the amount paid is refused. | G89: A delivered order of ₹X | H89: Refund ₹X + 1 | I89: 1. Try to refund more than paid 2. Verify the expected result. | J89: Refused with a message. | L89: Not Run | M89: High | N89: Boundary | R89: Also: Negative | S89: Store owner | T89: No | U89: docs/qa/regression/vendor-cms/VC-10-orders.md
A90: VC-10-010 | B90: Vendor CMS | C90: VC-10 · Orders and order detail | D90: Cancel | E90: Cancel order | F90: Cancelling returns stock and needs a reason. | G90: A new COD order | H90: Reason "Customer asked" | I90: 1. Press Cancel order 2. Try without a reason, then with one 3. Verify the expected result. | J90: Without a reason it waits; with one the order reads Cancelled and stock goes back. | L90: Not Run | M90: High | N90: Functional | R90: Also: Validation | S90: Store owner | T90: No | U90: docs/qa/regression/vendor-cms/VC-10-orders.md
A91: VC-10-011 | B91: Vendor CMS | C91: VC-10 · Orders and order detail | D91: Bulk | E91: Download invoices and shipped from CSV | F91: Bulk invoice download and CSV shipping. | G91: Two invoiced orders | H91: CSV line "HOM-10003, Delhivery, 12345" | I91: 1. Tick two orders and Download invoices 2. Use Shipped from CSV with the line 3. Press Export CSV 4. Verify the expected result. | J91: Invoices print for invoiced orders only; the CSV marks the order shipped with courier and tracking; Export CSV downloads the list. | L91: Not Run | M91: Medium | N91: Functional | S91: Store owner | T91: No | U91: docs/qa/regression/vendor-cms/VC-10-orders.md
A92: VC-10-012 | B92: Vendor CMS | C92: VC-10 · Orders and order detail | D92: Permissions | E92: Catalog editor has no orders | F92: Orders are hidden from catalog editors; support sees no actions. | G92: Signed in as Catalog editor; then as store Support | H92: — | I92: 1. Look for Orders 2. Open http://localhost:3000/admin/collections/orders 3. Verify the expected result. | J92: Catalog editor: not in the menu and refused. Support: list visible without action buttons. | L92: Not Run | M92: High | N92: Security/Permissions | S92: Catalog editor, Store support | T92: No | U92: docs/qa/regression/vendor-cms/VC-10-orders.md
A93: VC-11-001 | B93: Vendor CMS | C93: VC-11 · Returns | D93: Returns | E93: Return appears in the tab | F93: A shopper's return request lists under Returns. | G93: A delivered order with a return requested (E2E-14) | H93: — | I93: 1. Open Orders → Returns tab 2. Open the order 3. Verify the expected result. | J93: The order is listed; the Returns card shows items, reason, note and photo. | L93: Not Run | M93: High | N93: Integration | S93: Store owner | T93: No | U93: docs/qa/regression/vendor-cms/VC-11-returns.md
A94: VC-11-002 | B94: Vendor CMS | C94: VC-11 · Returns | D94: Returns | E94: Approve with pickup note | F94: Approving shows the pickup note to the shopper. | G94: A requested return | H94: Pickup note "Courier will collect on Monday" | I94: 1. Press Approve with the note 2. Verify the expected result. | J94: Status Approved; the shopper's order page shows the note; a "Return approved" email is queued. | L94: Not Run | M94: High | N94: Functional | R94: Also: Integration | S94: Store owner | T94: No | U94: docs/qa/regression/vendor-cms/VC-11-returns.md
A95: VC-11-003 | B95: Vendor CMS | C95: VC-11 · Returns | D95: Returns | E95: Receive and refund | F95: Receiving then refunding completes the return. | G95: An approved return | H95: Refund the item amount | I95: 1. Press Mark received 2. Press Refund with the amount 3. Verify the expected result. | J95: The return reads Refunded; a credit note is added. | L95: Not Run | M95: High | N95: Functional | S95: Store owner | T95: No | U95: docs/qa/regression/vendor-cms/VC-11-returns.md
A96: VC-11-004 | B96: Vendor CMS | C96: VC-11 · Returns | D96: Returns | E96: Reject needs a reason | F96: Rejecting needs a reason shown to the shopper. | G96: A requested return | H96: Reason "Item used" | I96: 1. Press Reject without a reason 2. Then with the reason 3. Verify the expected result. | J96: Without a reason it is refused; with it the shopper sees why. | L96: Not Run | M96: Medium | N96: Validation | S96: Store owner | T96: No | U96: docs/qa/regression/vendor-cms/VC-11-returns.md
A97: VC-12-001 | B97: Vendor CMS | C97: VC-12 · Customers and privacy requests | D97: List | E97: Customer list | F97: Customers lists shopper accounts with masked phone. | G97: Signed in as Home Orbit's owner (or super admin with Manage store on Home Orbit); store selling: `pnpm demo:selling home-orbit` run; a shopper account | H97: — | I97: 1. Open Sales → Customers 2. Verify the expected result. | J97: Rows with name, email, masked phone, orders link, spent, last order, roles, offers and joined date. | L97: Not Run | M97: High | N97: UI/UX | S97: Store owner | T97: No | U97: docs/qa/regression/vendor-cms/VC-12-customers.md
A98: VC-12-002 | B98: Vendor CMS | C98: VC-12 · Customers and privacy requests | D98: List | E98: Search and export | F98: Search by name, email or phone; export CSV. | G98: A shopper account | H98: Shopper email | I98: 1. Search the email 2. Press Export CSV 3. Verify the expected result. | J98: The account is found; a CSV downloads. | L98: Not Run | M98: Medium | N98: Functional | S98: Store owner | T98: No | U98: docs/qa/regression/vendor-cms/VC-12-customers.md
A99: VC-12-003 | B99: Vendor CMS | C99: VC-12 · Customers and privacy requests | D99: Privacy | E99: Data export request | F99: A data export request is due in 30 days and downloads JSON. | G99: A shopper account | H99: Type Data export | I99: 1. Press Privacy requests → Record a request 2. Pick Data export and the shopper's email 3. Press Download data 4. Verify the expected result. | J99: Shown as Due in 30 days; a JSON file with account, addresses, orders and preferences. | L99: Not Run | M99: High | N99: Functional | S99: Store owner | T99: No | U99: docs/qa/regression/vendor-cms/VC-12-customers.md
A100: VC-12-004 | B100: Vendor CMS | C100: VC-12 · Customers and privacy requests | D100: Privacy | E100: Delete account request | F100: Deleting an account keeps its orders. | G100: A throw-away shopper account | H100: Type Delete account | I100: 1. Record a Delete account request 2. Start 3. Delete account and confirm 4. Verify the expected result. | J100: The account is gone from Customers; its orders stay under Orders. | L100: Not Run | M100: High | N100: Functional | R100: Also: Data persistence | S100: Store owner | T100: No | U100: docs/qa/regression/vendor-cms/VC-12-customers.md
A101: VC-12-005 | B101: Vendor CMS | C101: VC-12 · Customers and privacy requests | D101: Permissions | E101: No privacy actions for order manager | F101: Order managers see customers without request buttons. | G101: Signed in as Order manager | H101: — | I101: 1. Open Customers 2. Verify the expected result. | J101: The list shows without Record a request or delete actions. | L101: Not Run | M101: Medium | N101: Security/Permissions | S101: Order manager | T101: No | U101: docs/qa/regression/vendor-cms/VC-12-customers.md
A102: VC-13-001 | B102: Vendor CMS | C102: VC-13 · Enquiries inbox | D102: Inbox | E102: Tabs, filter and cards | F102: The inbox shows tabs, filter, search and the open enquiry. | G102: Signed in as Home Orbit's owner (or super admin with Manage store on Home Orbit); enquiries from the store | H102: — | I102: 1. Open Sales → Enquiries 2. Verify the expected result. | J102: Tabs New, In progress, Closed with counts, a Type filter, search, cards on the left and the newest open on the right. | L102: Not Run | M102: High | N102: UI/UX | S102: Store owner | T102: Yes | U102: docs/qa/regression/vendor-cms/VC-13-enquiries.md
A103: VC-13-002 | B103: Vendor CMS | C103: VC-13 · Enquiries inbox | D103: Detail | E103: Product enquiry details | F103: A product enquiry shows the product and chosen options. | G103: A quote request sent from a product page with options | H103: — | I103: 1. Click the product enquiry 2. Verify the expected result. | J103: Name, company, phone, email, city, when; the product with photo, model number and quantity; the message with "Options: …". | L103: Not Run | M103: High | N103: Integration | S103: Store owner | T103: No | U103: docs/qa/regression/vendor-cms/VC-13-enquiries.md
A104: VC-13-003 | B104: Vendor CMS | C104: VC-13 · Enquiries inbox | D104: Reply | E104: Reply on WhatsApp and email | F104: Reply buttons open WhatsApp or email. | G104: An enquiry with phone and email | H104: — | I104: 1. Press Reply on WhatsApp 2. Look for Reply by email 3. Verify the expected result. | J104: WhatsApp opens to the shopper's number with a greeting naming the enquiry; Reply by email shows when an email exists; Create formal quote is marked P2. | L104: Not Run | M104: Medium | N104: Functional | S104: Store owner | T104: No | U104: docs/qa/regression/vendor-cms/VC-13-enquiries.md
A105: VC-13-004 | B105: Vendor CMS | C105: VC-13 · Enquiries inbox | D105: Workflow | E105: Assign, status and notes | F105: Assignment, status and notes save at once. | G105: An enquiry under New | H105: Assign to yourself; status Contacted; note "Called back" | I105: 1. Assign it to yourself 2. Set Status to Contacted 3. Add the note with Add note 4. Reload 5. Verify the expected result. | J105: Each saves at once; the note lists with your name; the enquiry moves to In progress. | L105: Not Run | M105: High | N105: Functional | R105: Also: Data persistence | S105: Store owner | T105: No | U105: docs/qa/regression/vendor-cms/VC-13-enquiries.md
A106: VC-13-005 | B106: Vendor CMS | C106: VC-13 · Enquiries inbox | D106: Workflow | E106: Close as won | F106: Won moves the enquiry to Closed. | G106: An enquiry in progress | H106: Status Won | I106: 1. Set Status to Won 2. Verify the expected result. | J106: The enquiry moves to Closed. | L106: Not Run | M106: Medium | N106: Functional | S106: Store owner | T106: No | U106: docs/qa/regression/vendor-cms/VC-13-enquiries.md
A107: VC-13-006 | B107: Vendor CMS | C107: VC-13 · Enquiries inbox | D107: Log | E107: Log a phone enquiry | F107: Staff can log an enquiry by hand. | G107: Signed in as Home Orbit's owner (or super admin with Manage store on Home Orbit) | H107: Name, phone, message | I107: 1. Press Log an enquiry 2. Fill and save 3. Verify the expected result. | J107: It gets the next ENQ number and shows under New. | L107: Not Run | M107: Medium | N107: Functional | S107: Store owner | T107: No | U107: docs/qa/regression/vendor-cms/VC-13-enquiries.md
A108: VC-13-007 | B108: Vendor CMS | C108: VC-13 · Enquiries inbox | D108: Log | E108: Contact required | F108: A logged enquiry needs a phone or email. | G108: Signed in as Home Orbit's owner (or super admin with Manage store on Home Orbit) | H108: Name only | I108: 1. Log an enquiry with only a name 2. Verify the expected result. | J108: Refused asking for a phone or email. | L108: Not Run | M108: Medium | N108: Validation | S108: Store owner | T108: No | U108: docs/qa/regression/vendor-cms/VC-13-enquiries.md
A109: VC-13-008 | B109: Vendor CMS | C109: VC-13 · Enquiries inbox | D109: Permissions | E109: Catalog editor has no enquiries | F109: Catalog editors cannot open enquiries. | G109: Signed in as Catalog editor | H109: http://localhost:3000/admin/collections/enquiries | I109: 1. Open the address 2. Verify the expected result. | J109: "Nothing found"; no Sales group in the menu. | L109: Not Run | M109: High | N109: Security/Permissions | S109: Catalog editor | T109: No | U109: docs/qa/regression/vendor-cms/VC-13-enquiries.md
...

Sheet Super Admin
A1: Test Case ID | B1: Application/Portal | C1: Module Name | D1: Submodule/Feature | E1: Functionality | F1: Test Scenario | G1: Preconditions | H1: Test Data | I1: Step-by-Step Instructions | J1: Expected Result | K1: Actual Result | L1: Status | M1: Priority | N1: Test Type | O1: Executed By | P1: Execution Date | Q1: Defect/Bug ID | R1: Remarks/Additional Notes | S1: Role | T1: Smoke Run | U1: Regression Script
A2: SA-01-001 | B2: Super Admin | C2: SA-01 · Sign in and two-step verification | D2: Sign in | E2: Page layout | F2: The sign-in page shows the platform form with its fields and options. | G2: Signed out | H2: — | I2: 1. Open http://localhost:3000/admin 2. Verify you are sent to the sign-in page 3. Verify the expected result. | J2: Email and Password fields, a Show control on the password, a "Keep me signed in on this device" box and a Sign in button. | K2: Email, Password with Show, Forgot password?, Keep me signed in on this device and Sign in shown. | L2: Pass | M2: Medium | N2: UI/UX | O2: Claude (Claude in Chrome) | P2: 2026-10-10 | S2: Super admin | T2: Yes | U2: docs/qa/regression/super-admin/SA-01-sign-in.md
A3: SA-01-002 | B3: Super Admin | C3: SA-01 · Sign in and two-step verification | D3: Sign in | E3: Wrong password | F3: A wrong password is refused with a message that does not say which part was wrong. | G3: Signed out | H3: Email admin@tenantecom.local; password "wrong-password-1" | I3: 1. Type the email and the wrong password 2. Press Sign in 3. Verify the expected result. | J3: The message "The email or password provided is incorrect." shows; you stay on the sign-in page. | K3: "The email or password provided is incorrect." shown; stayed on sign-in. | L3: Pass | M3: Critical | N3: Negative | O3: Claude (Claude in Chrome) | P3: 2026-10-10 | R3: First try froze while the page was still loading; typing before hydration is lost (see guide). | S3: Super admin | T3: Yes | U3: docs/qa/regression/super-admin/SA-01-sign-in.md
A4: SA-01-003 | B4: Super Admin | C4: SA-01 · Sign in and two-step verification | D4: Sign in | E4: Unknown email | F4: An email with no account gets the same message as a wrong password. | G4: Signed out | H4: Email nobody@tenantecom.local; any password | I4: 1. Type the unknown email and a password 2. Press Sign in 3. Verify the expected result. | J4: The same "The email or password provided is incorrect." message; nothing tells that the account does not exist. | L4: Not Run | M4: High | N4: Security/Permissions | S4: Super admin | T4: No | U4: docs/qa/regression/super-admin/SA-01-sign-in.md
A5: SA-01-004 | B5: Super Admin | C5: SA-01 · Sign in and two-step verification | D5: Sign in | E5: Required fields | F5: Empty fields are caught before sending. | G5: Signed out | H5: Both fields empty | I5: 1. Leave Email and Password empty 2. Press Sign in 3. Verify the expected result. | J5: The form asks for the email and the password; no request signs you in. | K5: Browser asked to fill out the email field; nothing was sent. | L5: Pass | M5: Medium | N5: Validation | O5: Claude (Claude in Chrome) | P5: 2026-10-10 | S5: Super admin | T5: No | U5: docs/qa/regression/super-admin/SA-01-sign-in.md
A6: SA-01-005 | B6: Super Admin | C6: SA-01 · Sign in and two-step verification | D6: Two-step | E6: Step 2 asked | F6: After the right password a platform account is asked for its authenticator code. | G6: Signed out; super admin has two-step set up | H6: Right email and password | I6: 1. Type the right email and password 2. Press Sign in 3. Verify the next screen 4. Verify the expected result. | J6: "Step 2 of 2, Two-step verification" with six code boxes; the dashboard is not shown yet. | K6: "Step 2 of 2, Two-step verification" with six boxes, Verify and continue, Use a different account and the lost-phone note. | L6: Pass | M6: Critical | N6: Security/Permissions | O6: Claude (Claude in Chrome) | P6: 2026-10-10 | S6: Super admin | T6: Yes | U6: docs/qa/regression/super-admin/SA-01-sign-in.md
A7: SA-01-006 | B7: Super Admin | C7: SA-01 · Sign in and two-step verification | D7: Two-step | E7: Wrong code | F7: A wrong 6-digit code is refused. | G7: On Step 2 of 2 | H7: Code 000000 (not the app's current code) | I7: 1. Type 000000 in the six boxes 2. Submit 3. Verify the expected result. | J7: The message "That code didn't work" (or similar) shows; you stay on step 2. | K7: "That code didn't work. Check the time on your phone and try the newest code."; boxes cleared. | L7: Pass | M7: Critical | N7: Negative | O7: Claude (Claude in Chrome) | P7: 2026-10-10 | S7: Super admin | T7: Yes | U7: docs/qa/regression/super-admin/SA-01-sign-in.md
A8: SA-01-007 | B8: Super Admin | C8: SA-01 · Sign in and two-step verification | D8: Two-step | E8: Right code, paste | F8: The authenticator code signs you in; pasting all six digits into the first box fills them all. | G8: On Step 2 of 2 | H8: The current code from the authenticator app | I8: 1. Copy the 6-digit code 2. Paste it into the first box 3. Verify all six boxes are filled 4. Submit if it does not submit by itself 5. Verify the expected result. | J8: You land on the platform dashboard, "Good morning/afternoon/evening, Platform". | K8: Typing the authenticator code submitted at the sixth digit and opened "Good morning, Platform". | L8: Pass | M8: Critical | N8: Functional | O8: Claude (Claude in Chrome) | P8: 2026-10-10 | R8: Paste into the first box is handled in code (CodeBoxes onPaste); a synthetic paste from the extension does not insert text, so paste needs a human check. | S8: Super admin | T8: Yes | U8: docs/qa/regression/super-admin/SA-01-sign-in.md
A9: SA-01-008 | B9: Super Admin | C9: SA-01 · Sign in and two-step verification | D9: Two-step | E9: First-time setup | F9: A platform account without two-step sees only the setup until it is done. | G9: A new Support teammate (SA-14) signed in for the first time | H9: Their email and password; an authenticator app | I9: 1. Sign in as the new teammate 2. Verify the panel is covered by "Set up two-step sign-in" 3. Press it, scan the QR code (or type the setup key) 4. Type the app's 6-digit code and confirm 5. Verify the dashboard shows 6. Verify the expected result. | J9: Until the code is confirmed, no platform screen is usable; after it, the dashboard shows and Team and access lists Two-step On. | L9: Not Run | M9: Critical | N9: Security/Permissions | S9: Super admin | T9: No | U9: docs/qa/regression/super-admin/SA-01-sign-in.md
A10: SA-01-009 | B10: Super Admin | C10: SA-01 · Sign in and two-step verification | D10: Two-step | E10: Setup with a wrong code | F10: Two-step setup is not saved with a wrong confirmation code. | G10: On the setup screen | H10: Code 123456 that the app did not show | I10: 1. Type a wrong code on the setup screen 2. Confirm 3. Verify the expected result. | J10: An error says the code did not match; two-step stays off and the setup screen stays. | L10: Not Run | M10: High | N10: Negative | S10: Super admin | T10: No | U10: docs/qa/regression/super-admin/SA-01-sign-in.md
A11: SA-01-010 | B11: Super Admin | C11: SA-01 · Sign in and two-step verification | D11: Sessions | E11: Keep me signed in | F11: Without the tick the session ends with the browser; with it, it survives a restart (8 hours at most). | G11: Signed out | H11: Right credentials and code | I11: 1. Sign in without ticking "Keep me signed in on this device" 2. Close every browser window and reopen the admin 3. Verify you must sign in again 4. Sign in again with the box ticked 5. Close and reopen the browser 6. Verify you are still signed in 7. Verify the expected result. | J11: Unticked: signed out after the browser closes. Ticked: still signed in after reopening. | L11: Not Run | M11: Medium | N11: Data persistence | S11: Super admin | T11: No | U11: docs/qa/regression/super-admin/SA-01-sign-in.md
A12: SA-01-011 | B12: Super Admin | C12: SA-01 · Sign in and two-step verification | D12: Sessions | E12: Sign out | F12: Signing out ends the session. | G12: Signed in | H12: — | I12: 1. Open the account menu and sign out 2. Open http://localhost:3000/admin 3. Verify the expected result. | J12: The sign-in page shows; the browser back button does not reopen admin data. | L12: Not Run | M12: High | N12: Security/Permissions | S12: Super admin | T12: Yes | U12: docs/qa/regression/super-admin/SA-01-sign-in.md
A13: SA-01-012 | B13: Super Admin | C13: SA-01 · Sign in and two-step verification | D13: Lockout | E13: Five wrong passwords | F13: Five wrong passwords lock the account for 15 minutes. | G13: Use a store owner that does not matter (owner@demo-clothing.example), private window | H13: Wrong password 6 times | I13: 1. Sign in with a wrong password 5 times; read the message each time 2. Try a 6th time 3. Verify the expected result. | J13: Tries 1–5: "The email or password provided is incorrect." The 6th: "This user is locked due to having too many failed login attempts." It lifts after 15 minutes. | L13: Not Run | M13: High | N13: Security/Permissions | R13: Also: Boundary | S13: Tester (any) | T13: No | U13: docs/qa/regression/super-admin/SA-01-sign-in.md
A14: SA-01-013 | B14: Super Admin | C14: SA-01 · Sign in and two-step verification | D14: Lockout | E14: Wrong codes | F14: Repeated wrong two-step codes lock sign-in like wrong passwords. | G14: On Step 2 of 2 for a test platform account (not your only super admin) | H14: 5 wrong codes | I14: 1. Type a wrong code 5 times 2. Then type the right code 3. Verify the expected result. | J14: After 5 wrong codes the account is locked for 15 minutes and even the right code is refused until then. | L14: Not Run | M14: Medium | N14: Security/Permissions | R14: Use a throw-away Support account so you are not locked out.; Also: Boundary | S14: Super admin | T14: No | U14: docs/qa/regression/super-admin/SA-01-sign-in.md
A15: SA-01-014 | B15: Super Admin | C15: SA-01 · Sign in and two-step verification | D15: Password reset | E15: Forgot password | F15: The reset link sets a new password; a too-short one is refused. | G15: Signed out; a test account | H15: New password "short1" then a 10+ character one | I15: 1. Use Forgot password with the account's email 2. Open the link printed in the `pnpm dev` terminal ([dev-log email]) 3. Try "short1" 4. Then a 10-character or longer password 5. Verify the expected result. | J15: Short passwords are refused (10 characters at least); a valid one saves and the account signs in with it (still asking for the code when two-step is on). | L15: Not Run | M15: High | N15: Validation | S15: Super admin | T15: No | U15: docs/qa/regression/super-admin/SA-01-sign-in.md
A16: SA-02-001 | B16: Super Admin | C16: SA-02 · Platform dashboard | D16: Figures | E16: Tiles | F16: The five figures show as the wireframe. | G16: Signed in as super admin | H16: Seeded QA data | I16: 1. Open http://localhost:3000/admin 2. Read the figure tiles 3. Verify the expected result. | J16: Live stores, MRR (before GST), Past due, Orders today (all stores) and GMV this month are shown with numbers. | K16: Live stores 2 (1 paying, 1 on trial), MRR ₹6,999 before GST, Past due 0, Orders today 1, GMV October ₹25,273. | L16: Pass | M16: High | N16: UI/UX | O16: Claude (Claude in Chrome) | P16: 2026-10-10 | S16: Super admin | T16: Yes | U16: docs/qa/regression/super-admin/SA-02-dashboard.md
A17: SA-02-002 | B17: Super Admin | C17: SA-02 · Platform dashboard | D17: Figures | E17: Live stores count | F17: Live stores counts active stores only. | G17: Two active stores and Home Orbit as a draft | H17: — | I17: 1. Read Live stores 2. Compare with All vendors → Active tab count 3. Verify the expected result. | J17: Live stores equals the Active count (2 on a fresh seed; 3 after Home Orbit goes live). | L17: Not Run | M17: High | N17: Integration | S17: Super admin | T17: No | U17: docs/qa/regression/super-admin/SA-02-dashboard.md
A18: SA-02-003 | B18: Super Admin | C18: SA-02 · Platform dashboard | D18: Sales | E18: Sales across all stores | F18: The chart has one bar per day of the month and reflects orders. | G18: Demo orders created for Home Orbit | H18: `pnpm demo:orders home-orbit` | I18: 1. Read the Sales across all stores chart 2. Hover or compare bars with Top stores 3. Verify the expected result. | J18: Bars appear on days with sold orders; days without orders are empty; the month total matches GMV this month. | L18: Not Run | M18: Medium | N18: Integration | S18: Super admin | T18: No | U18: docs/qa/regression/super-admin/SA-02-dashboard.md
A19: SA-02-004 | B19: Super Admin | C19: SA-02 · Platform dashboard | D19: Lists | E19: Top stores this month | F19: Stores with orders are ranked by GMV. | G19: Demo orders exist | H19: — | I19: 1. Read Top stores this month 2. Verify the expected result. | J19: Each row shows vendor, industry, orders, GMV and the change against last month to the same day; Home Orbit is listed. | K19: Top stores: Home Orbit, Door and furniture hardware, Home decor, 8 orders, ₹25,273, New. | L19: Pass | M19: Medium | N19: Functional | O19: Claude (Claude in Chrome) | P19: 2026-10-10 | S19: Super admin | T19: No | U19: docs/qa/regression/super-admin/SA-02-dashboard.md
A20: SA-02-005 | B20: Super Admin | C20: SA-02 · Platform dashboard | D20: Lists | E20: Needs attention | F20: Stores needing action are listed with the reason. | G20: Fresh seed | H20: — | I20: 1. Read Needs attention 2. Verify the expected result. | J20: Home Orbit "Store is still a draft" and the owners who have not accepted their invite are listed; each row opens the vendor. | K20: Home Orbit "Store is still a draft" and three owners who have not accepted their invite. | L20: Pass | M20: High | N20: Functional | O20: Claude (Claude in Chrome) | P20: 2026-10-10 | S20: Super admin | T20: No | U20: docs/qa/regression/super-admin/SA-02-dashboard.md
A21: SA-02-006 | B21: Super Admin | C21: SA-02 · Platform dashboard | D21: Lists | E21: Recently onboarded with Resend invite | F21: Recently created stores show with status; Resend invite sends a new link. | G21: Fresh seed | H21: — | I21: 1. Read Recently onboarded 2. Press Resend invite on a store whose owner has not accepted 3. Watch the `pnpm dev` terminal 4. Verify the expected result. | J21: Home Orbit (Draft), Demo Clothing and Demo Sanitary (Active) show; Resend invite prints a [dev-log email] with a set-password link. | L21: Not Run | M21: Medium | N21: Integration | S21: Super admin | T21: No | U21: docs/qa/regression/super-admin/SA-02-dashboard.md
A22: SA-02-007 | B22: Super Admin | C22: SA-02 · Platform dashboard | D22: Navigation | E22: Platform menu | F22: The left menu has only platform sections. | G22: Signed in as super admin, no store session | H22: — | I22: 1. Read the left menu 2. Verify the expected result. | J22: Dashboard; Vendors (All vendors, New vendor); Billing (Plans, Subscriptions); Platform (Team and access, Staff users). No store sections such as Products or Orders. | K22: Menu: Dashboard, All vendors, New vendor, Plans, Subscriptions, Team and access, Staff users; no store sections. | L22: Pass | M22: High | N22: UI/UX | O22: Claude (Claude in Chrome) | P22: 2026-10-10 | R22: Also: Security/Permissions | S22: Super admin | T22: Yes | U22: docs/qa/regression/super-admin/SA-02-dashboard.md
A23: SA-02-008 | B23: Super Admin | C23: SA-02 · Platform dashboard | D23: Gate | E23: Two-step gate | F23: A platform account without two-step sees the setup in place of the menu. | G23: A Support teammate who has not set up two-step | H23: — | I23: 1. Sign in as that teammate 2. Try to open All vendors from the address bar 3. Verify the expected result. | J23: The panel shows only "Set up two-step sign-in"; no vendor data is shown until it is done. | L23: Not Run | M23: High | N23: Security/Permissions | S23: Super admin | T23: No | U23: docs/qa/regression/super-admin/SA-02-dashboard.md
A24: SA-03-001 | B24: Super Admin | C24: SA-03 · All vendors | D24: List | E24: Columns and tabs | F24: The list shows each vendor with the wireframe's columns and tab counts. | G24: Signed in as super admin; fresh seed | H24: — | I24: 1. Open Vendors → All vendors 2. Verify the expected result. | J24: Columns Vendor (with primary domain), Industry, Plan, Store, Subscription, Products (bar against the plan), Orders in 30 days, Created. Tabs All 3, Active 2, Draft 1. | K24: "3 stores · 2 live", tabs All 3, Active 2, Draft 1, Suspended 0, Archived 0; columns as the wireframe. | L24: Pass | M24: High | N24: UI/UX | O24: Claude (Claude in Chrome) | P24: 2026-10-10 | Q24: DEF-001 (fixed and retested) | S24: Super admin | T24: Yes | U24: docs/qa/regression/super-admin/SA-03-all-vendors.md
A25: SA-03-002 | B25: Super Admin | C25: SA-03 · All vendors | D25: Search | E25: By name | F25: Search narrows the list and the tab counts follow. | G25: On All vendors | H25: Search "orbit" | I25: 1. Type orbit in the search box 2. Read the rows and tab counts 3. Verify the expected result. | J25: Only Home Orbit stays; the tabs count 1 under All and Draft. | K25: "orbit" left only Home Orbit; tabs became All 1, Active 0, Draft 1; ?q=orbit in the address. | L25: Pass | M25: High | N25: Functional | O25: Claude (Claude in Chrome) | P25: 2026-10-10 | R25: The extension's type action did not reach this search box; key presses and input events did. A human should type it once. | S25: Super admin | T25: Yes | U25: docs/qa/regression/super-admin/SA-03-all-vendors.md
A26: SA-03-003 | B26: Super Admin | C26: SA-03 · All vendors | D26: Search | E26: By slug, GSTIN or domain | F26: Search also matches slug, GSTIN and domain. | G26: On All vendors | H26: Search "demo-sanitary"; then part of a GSTIN; then "localhost" | I26: 1. Search each value in turn 2. Verify the expected result. | J26: The slug finds Demo Sanitary; a GSTIN fragment finds its store; "localhost" matches stores by their domain. | L26: Not Run | M26: Medium | N26: Functional | S26: Super admin | T26: No | U26: docs/qa/regression/super-admin/SA-03-all-vendors.md
A27: SA-03-004 | B27: Super Admin | C27: SA-03 · All vendors | D27: Search | E27: No match | F27: A search with no match shows an empty state. | G27: On All vendors | H27: Search "zzzz-no-store" | I27: 1. Type the value 2. Verify the expected result. | J27: No rows and an empty-list message; clearing the search brings all vendors back. | L27: Not Run | M27: Low | N27: Negative | S27: Super admin | T27: No | U27: docs/qa/regression/super-admin/SA-03-all-vendors.md
A28: SA-03-005 | B28: Super Admin | C28: SA-03 · All vendors | D28: Filters | E28: Plan, Industry, Subscription | F28: Each filter narrows the list and is kept in the address. | G28: On All vendors | H28: Plan = Starter; Industry = Hardware; Subscription = Trial | I28: 1. Pick each filter in turn 2. Copy the address into a new tab 3. Verify the expected result. | J28: Rows and tab counts follow each filter; the new tab opens with the same filters applied. | L28: Not Run | M28: Medium | N28: Functional | R28: Also: Data persistence | S28: Super admin | T28: No | U28: docs/qa/regression/super-admin/SA-03-all-vendors.md
A29: SA-03-006 | B29: Super Admin | C29: SA-03 · All vendors | D29: Tabs | E29: Status tabs | F29: Each status tab shows only stores in that state. | G29: On All vendors | H29: — | I29: 1. Click Draft 2. Click Active 3. Verify the expected result. | J29: Draft lists only Home Orbit (fresh seed); Active lists Demo Sanitary and Demo Clothing. | L29: Not Run | M29: Medium | N29: Functional | S29: Super admin | T29: No | U29: docs/qa/regression/super-admin/SA-03-all-vendors.md
A30: SA-03-007 | B30: Super Admin | C30: SA-03 · All vendors | D30: Plan usage | E30: Usage bar | F30: Products used against the plan show a bar and a warning at 90%. | G30: Home Orbit on Starter (500 products) with 110 products | H30: — | I30: 1. Read Home Orbit's Products column 2. Verify the expected result. | J30: "110 / 500" with a bar about a fifth full; a store at 90% or more would show "N% used". | L30: Not Run | M30: Low | N30: UI/UX | S30: Super admin | T30: No | U30: docs/qa/regression/super-admin/SA-03-all-vendors.md
A31: SA-03-008 | B31: Super Admin | C31: SA-03 · All vendors | D31: Export | E31: Export CSV | F31: Export downloads the list as filtered. | G31: On All vendors with the Draft tab | H31: — | I31: 1. Press Export CSV 2. Open the file 3. Verify the expected result. | J31: A CSV downloads with one row per vendor shown (only Home Orbit for the Draft tab) and the list's columns. | L31: Not Run | M31: Medium | N31: Functional | S31: Super admin | T31: No | U31: docs/qa/regression/super-admin/SA-03-all-vendors.md
A32: SA-03-009 | B32: Super Admin | C32: SA-03 · All vendors | D32: Navigation | E32: Open a vendor | F32: A row opens the vendor overview. | G32: On All vendors | H32: — | I32: 1. Click Home Orbit 2. Verify the expected result. | J32: The vendor overview opens with the tabs Overview, Features, Connectors, Domains, Billing, Staff. | K32: Home Orbit opened with Features, Connectors, Domains, Billing, Staff tabs. | L32: Pass | M32: High | N32: Functional | O32: Claude (Claude in Chrome) | P32: 2026-10-10 | S32: Super admin | T32: Yes | U32: docs/qa/regression/super-admin/SA-03-all-vendors.md
A33: SA-04-001 | B33: Super Admin | C33: SA-04 · New vendor (onboarding) | D33: Form | E33: Layout | F33: The onboarding page has five sections and a summary. | G33: Signed in as super admin | H33: — | I33: 1. Open Vendors → New vendor 2. Verify the expected result. | J33: Sections 1 Business, 2 Store, 3 Plan and trial, 4 Starting features, 5 Owner login, and a "Will be created" summary on the right. | L33: Not Run | M33: Medium | N33: UI/UX | S33: Super admin | T33: No | U33: docs/qa/regression/super-admin/SA-04-new-vendor.md
A34: SA-04-002 | B34: Super Admin | C34: SA-04 · New vendor (onboarding) | D34: Business | E34: GSTIN checksum | F34: A GSTIN with a wrong last character is refused. | G34: On New vendor | H34: GSTIN 29AABCT1234F1ZN | I34: 1. Type the GSTIN 2. Verify the expected result. | J34: "The last character does not match. Check for a typing mistake" shows under the field. | L34: Not Run | M34: High | N34: Validation | S34: Super admin | T34: Yes | U34: docs/qa/regression/super-admin/SA-04-new-vendor.md
A35: SA-04-003 | B35: Super Admin | C35: SA-04 · New vendor (onboarding) | D35: Business | E35: GSTIN fills PAN and state | F35: A valid GSTIN fills PAN and state. | G35: On New vendor | H35: GSTIN 29AABCT1234F1ZM | I35: 1. Type the GSTIN 2. Verify the expected result. | J35: PAN AABCT1234F and State Karnataka (29) fill in by themselves. | L35: Not Run | M35: High | N35: Functional | S35: Super admin | T35: No | U35: docs/qa/regression/super-admin/SA-04-new-vendor.md
A36: SA-04-004 | B36: Super Admin | C36: SA-04 · New vendor (onboarding) | D36: Business | E36: Required fields | F36: The vendor is not created with required fields empty. | G36: On New vendor | H36: All fields empty | I36: 1. Press Create vendor 2. Verify the expected result. | J36: Errors on Store name, Legal name, Industry, slug, plan and the owner's name and email; nothing is created. | L36: Not Run | M36: High | N36: Validation | S36: Super admin | T36: No | U36: docs/qa/regression/super-admin/SA-04-new-vendor.md
A37: SA-04-005 | B37: Super Admin | C37: SA-04 · New vendor (onboarding) | D37: Store | E37: Slug and address | F37: The slug becomes the store address; a used slug is refused. | G37: On New vendor | H37: Slug test-locks; then home-orbit | I37: 1. Type test-locks 2. Read the summary 3. Change the slug to home-orbit and try to create 4. Verify the expected result. | J37: The summary shows test-locks.localhost; "home-orbit" is refused as already used. | L37: Not Run | M37: High | N37: Validation | S37: Super admin | T37: No | U37: docs/qa/regression/super-admin/SA-04-new-vendor.md
A38: SA-04-006 | B38: Super Admin | C38: SA-04 · New vendor (onboarding) | D38: Plan | E38: Plan and trial | F38: Choosing a plan shows its starting offer and the trial. | G38: On New vendor | H38: Starter; trial 14 days | I38: 1. Pick Starter 2. Set the trial to 14 days 3. Verify the expected result. | J38: "Starts at ₹9,999 for 3 months" shows and the summary lists the trial end date. | L38: Not Run | M38: Medium | N38: Functional | S38: Super admin | T38: No | U38: docs/qa/regression/super-admin/SA-04-new-vendor.md
A39: SA-04-007 | B39: Super Admin | C39: SA-04 · New vendor (onboarding) | D39: Features | E39: Preset within the plan | F39: Starting features come from the industry preset, capped by the plan. | G39: Industry Locks, plan Starter | H39: — | I39: 1. Read section 4 2. Verify the expected result. | J39: Features from the preset are switched on; features outside Starter are locked. | L39: Not Run | M39: Medium | N39: Functional | S39: Super admin | T39: No | U39: docs/qa/regression/super-admin/SA-04-new-vendor.md
A40: SA-04-008 | B40: Super Admin | C40: SA-04 · New vendor (onboarding) | D40: Create | E40: Create vendor with invite | F40: Creating the vendor makes a draft store and emails the owner. | G40: Valid form | H40: Test Locks / Test Locks Pvt Ltd / Locks / 29AABCT1234F1ZM / test-locks / Starter / Test Owner, owner@testlocks.example, "Email the invite now" ticked | I40: 1. Fill the form 2. Press Create vendor 3. Watch the `pnpm dev` terminal 4. Open http://test-locks.localhost:3000 5. Verify the expected result. | J40: You land on the new vendor overview as Store draft; the terminal prints "You're invited to manage Test Locks" with a link; the store opens with a preview banner in the default design and no products. | L40: Not Run | M40: Critical | N40: Functional | R40: Creates a throw-away store; reset the QA database afterwards if needed.; Also: Integration | S40: Super admin | T40: Yes | U40: docs/qa/regression/super-admin/SA-04-new-vendor.md
A41: SA-04-009 | B41: Super Admin | C41: SA-04 · New vendor (onboarding) | D41: Create | E41: Duplicate owner email | F41: An owner email that already has an account is handled. | G41: Valid form | H41: Owner email owner@homeorbit.example | I41: 1. Fill the form with an existing owner email 2. Create 3. Verify the expected result. | J41: Either the existing user is added as owner of the new store or a clear message explains; no duplicate account is made. | L41: Not Run | M41: Medium | N41: Negative | R41: Requires confirmation of the intended behaviour. | S41: Super admin | T41: No | U41: docs/qa/regression/super-admin/SA-04-new-vendor.md
A42: SA-05-001 | B42: Super Admin | C42: SA-05 · Vendor overview and store status | D42: Header | E42: Status and actions | F42: The header shows the store's state and actions. | G42: Home Orbit as a draft | H42: — | I42: 1. Open All vendors → Home Orbit 2. Verify the expected result. | J42: Logo or initials, "Store draft", "Starter plan", home-orbit.localhost, View store and Go live. | K42: Store draft, Starter plan, home-orbit.localhost, View store, Go live, Manage store, View as support. | L42: Pass | M42: High | N42: UI/UX | O42: Claude (Claude in Chrome) | P42: 2026-10-10 | S42: Super admin | T42: Yes | U42: docs/qa/regression/super-admin/SA-05-vendor-overview.md
A43: SA-05-002 | B43: Super Admin | C43: SA-05 · Vendor overview and store status | D43: Business details | E43: Read-only then Edit | F43: Business details are read-only until Edit is pressed. | G43: On the overview | H43: — | I43: 1. Read Business details 2. Press Edit 3. Verify the expected result. | J43: Values show as text first; Edit opens the form with the same values. | L43: Not Run | M43: Medium | N43: Functional | S43: Super admin | T43: No | U43: docs/qa/regression/super-admin/SA-05-vendor-overview.md
A44: SA-05-003 | B44: Super Admin | C44: SA-05 · Vendor overview and store status | D44: Business details | E44: GSTIN fills PAN and state | F44: Changing the GSTIN updates PAN and state. | G44: Business details in edit mode | H44: GSTIN 27AAPFU0939F1ZV | I44: 1. Type the GSTIN 2. Save 3. Verify the expected result. | J44: PAN and State (Maharashtra 27) fill in; Save succeeds and the read-only view shows them after a reload. | L44: Not Run | M44: High | N44: Functional | R44: Also: Data persistence | S44: Super admin | T44: No | U44: docs/qa/regression/super-admin/SA-05-vendor-overview.md
A45: SA-05-004 | B45: Super Admin | C45: SA-05 · Vendor overview and store status | D45: Business details | E45: Invalid GSTIN | F45: An invalid GSTIN is not saved. | G45: Edit mode | H45: GSTIN 27AAPFU0939F1ZX | I45: 1. Type the GSTIN 2. Save 3. Verify the expected result. | J45: The checksum error shows and nothing is saved. | L45: Not Run | M45: High | N45: Validation | S45: Super admin | T45: No | U45: docs/qa/regression/super-admin/SA-05-vendor-overview.md
A46: SA-05-005 | B46: Super Admin | C46: SA-05 · Vendor overview and store status | D46: Plan usage | E46: Usage figures | F46: Plan usage shows products and staff against the plan. | G46: On the overview | H46: — | I46: 1. Read Plan usage 2. Verify the expected result. | J46: Products 110 / 500 and Staff users 1 / 3 (fresh seed). | K46: Products 110 / 500, Staff users 1 / 3, Storage 0 GB / 5 GB, Orders this month 18 / 1,000 (after the DEF-002 fix). | L46: Pass | M46: Medium | N46: Functional | O46: Claude (Claude in Chrome) | P46: 2026-10-10 | Q46: DEF-002 (fixed and retested) | S46: Super admin | T46: No | U46: docs/qa/regression/super-admin/SA-05-vendor-overview.md
A47: SA-05-006 | B47: Super Admin | C47: SA-05 · Vendor overview and store status | D47: Store health | E47: Health card | F47: Store health summarises the store's state. | G47: On the overview | H47: — | I47: 1. Read Store health 2. Verify the expected result. | J47: Last order, Razorpay state (and webhook), any failing connector, the primary domain and the storefront design (vendors/home-orbit). | K47: Store health: last order Today 00:13, Razorpay Not connected, primary domain home-orbit.localhost, design vendors/home-orbit. | L47: Pass | M47: Medium | N47: Functional | O47: Claude (Claude in Chrome) | P47: 2026-10-10 | S47: Super admin | T47: No | U47: docs/qa/regression/super-admin/SA-05-vendor-overview.md
A48: SA-05-007 | B48: Super Admin | C48: SA-05 · Vendor overview and store status | D48: Notes | E48: Internal notes and recent changes | F48: An internal note saves and the change is recorded. | G48: On the overview | H48: Note "QA check 1" | I48: 1. Add a line under Internal notes 2. Save 3. Reload 4. Read Recent changes 5. Verify the expected result. | J48: The note is still there after reload; Recent changes lists the edit with who and when. | L48: Not Run | M48: High | N48: Data persistence | S48: Super admin | T48: No | U48: docs/qa/regression/super-admin/SA-05-vendor-overview.md
A49: SA-05-008 | B49: Super Admin | C49: SA-05 · Vendor overview and store status | D49: Status | E49: Go live | F49: Go live makes the store active and indexable. | G49: Home Orbit as a draft | H49: — | I49: 1. Press Go live and confirm 2. Reload http://home-orbit.localhost:3000 3. Open http://home-orbit.localhost:3000/robots.txt 4. Verify the expected result. | J49: Status Active; the preview bar is gone; robots.txt allows search engines and names the sitemap; Live stores on the dashboard goes up by 1. | L49: Not Run | M49: Critical | N49: Functional | R49: Also: Integration | S49: Super admin | T49: Yes | U49: docs/qa/regression/super-admin/SA-05-vendor-overview.md
A50: SA-05-009 | B50: Super Admin | C50: SA-05 · Vendor overview and store status | D50: Status | E50: Suspend needs a reason | F50: Suspend is refused without a reason. | G50: Home Orbit active | H50: Empty reason | I50: 1. Press Suspend store 2. Leave the reason empty and confirm 3. Verify the expected result. | J50: The reason is required; the store stays active. | L50: Not Run | M50: High | N50: Validation | S50: Super admin | T50: No | U50: docs/qa/regression/super-admin/SA-05-vendor-overview.md
A51: SA-05-010 | B51: Super Admin | C51: SA-05 · Vendor overview and store status | D51: Status | E51: Suspend | F51: Suspending closes the store to shoppers. | G51: Home Orbit active | H51: Reason "QA suspend test" | I51: 1. Press Suspend store 2. Type the reason and confirm 3. Reload http://home-orbit.localhost:3000 in a private window 4. Verify the expected result. | J51: "Store unavailable" on the store; /robots.txt says Disallow: /; the overview shows Suspended. | L51: Not Run | M51: Critical | N51: Functional | R51: Also: Integration | S51: Super admin | T51: No | U51: docs/qa/regression/super-admin/SA-05-vendor-overview.md
A52: SA-05-011 | B52: Super Admin | C52: SA-05 · Vendor overview and store status | D52: Status | E52: Resume | F52: Resume reopens a suspended store at once. | G52: Home Orbit suspended | H52: — | I52: 1. Press Resume store 2. Reload http://home-orbit.localhost:3000 3. Verify the expected result. | J52: The store is back immediately; Recent changes lists Go live, Suspend and Resume with reasons. | L52: Not Run | M52: Critical | N52: Functional | S52: Super admin | T52: No | U52: docs/qa/regression/super-admin/SA-05-vendor-overview.md
A53: SA-05-012 | B53: Super Admin | C53: SA-05 · Vendor overview and store status | D53: Status | E53: Archive | F53: Archiving hides the store and keeps its data. | G53: A throw-away store (Test Locks from SA-04) | H53: Reason "QA archive" | I53: 1. Archive Test Locks with a reason 2. Open http://test-locks.localhost:3000 3. Look for it under All vendors → Archived 4. Verify the expected result. | J53: The store address shows not found; the vendor is listed as Archived with its data. | L53: Not Run | M53: Medium | N53: Functional | R53: Do not archive Home Orbit. | S53: Super admin | T53: No | U53: docs/qa/regression/super-admin/SA-05-vendor-overview.md
A54: SA-06-001 | B54: Super Admin | C54: SA-06 · Store sessions (Manage store, View as support) | D54: Isolation | E54: Store screens need a session | F54: Without a store session the platform panel cannot open store records. | G54: Super admin, no store session | H54: Address http://localhost:3000/admin/collections/pages | I54: 1. Type the address 2. Verify the expected result. | J54: "Nothing found" (or equivalent); no store pages are listed. | K54: /admin/collections/pages without a store session: "Nothing found … Back to Dashboard". | L54: Pass | M54: Critical | N54: Security/Permissions | O54: Claude (Claude in Chrome) | P54: 2026-10-10 | S54: Super admin | T54: Yes | U54: docs/qa/regression/super-admin/SA-06-store-sessions.md
A55: SA-06-002 | B55: Super Admin | C55: SA-06 · Store sessions (Manage store, View as support) | D55: Manage store | E55: Reason required | F55: Manage store needs a real reason. | G55: On Home Orbit overview | H55: Reason empty, then "abc" | I55: 1. Press Manage store 2. Try to open with an empty reason, then with "abc" 3. Verify the expected result. | J55: Both are refused; the box explains the 2-hour session. | L55: Not Run | M55: High | N55: Validation | S55: Super admin | T55: No | U55: docs/qa/regression/super-admin/SA-06-store-sessions.md
A56: SA-06-003 | B56: Super Admin | C56: SA-06 · Store sessions (Manage store, View as support) | D56: Manage store | E56: Open the store CMS | F56: A session opens the vendor's CMS with a banner. | G56: On Home Orbit overview | H56: Reason "Vendor asked us to set up the Diwali page" | I56: 1. Press Manage store 2. Type the reason and open 3. Verify the expected result. | J56: A bar on every page: "You are managing Home Orbit as platform admin" with the reason and end time; the menu is Home Orbit's (Catalog, Sales, Marketing, Content, Store, Insights); platform sections are gone. | K56: Bar "You are managing Home Orbit as platform admin (Platform Admin)" with the reason and "ends 13:29"; menu became Home Orbit's (Catalog, Sales, Marketing, Content, Store, Insights). | L56: Pass | M56: Critical | N56: Functional | O56: Claude (Claude in Chrome) | P56: 2026-10-10 | R56: The extension's type action did not reach the reason box; it was filled with form input. | S56: Super admin | T56: Yes | U56: docs/qa/regression/super-admin/SA-06-store-sessions.md
A57: SA-06-004 | B57: Super Admin | C57: SA-06 · Store sessions (Manage store, View as support) | D57: Manage store | E57: Platform screens hidden in session | F57: Platform collections are not reachable during a store session. | G57: In a Manage store session | H57: Address http://localhost:3000/admin/collections/plans | I57: 1. Type the address 2. Verify the expected result. | J57: "Nothing found"; plans are not shown. | L57: Not Run | M57: High | N57: Security/Permissions | S57: Super admin | T57: No | U57: docs/qa/regression/super-admin/SA-06-store-sessions.md
A58: SA-06-005 | B58: Super Admin | C58: SA-06 · Store sessions (Manage store, View as support) | D58: Audit | E58: Changes are attributed | F58: Edits in a session are recorded with the reason. | G58: In a Manage store session | H58: Change a word on About us; Save Draft | I58: 1. Edit the About us page and save a draft 2. End session 3. Open Home Orbit overview → Recent changes 4. Verify the expected result. | J58: Pages list shows "by Platform Admin (platform team)"; Recent changes lists the session and the edit with the reason. | L58: Not Run | M58: High | N58: Integration | R58: Also: Security/Permissions | S58: Super admin | T58: No | U58: docs/qa/regression/super-admin/SA-06-store-sessions.md
A59: SA-06-006 | B59: Super Admin | C59: SA-06 · Store sessions (Manage store, View as support) | D59: End | E59: End session | F59: End session returns to the platform panel. | G59: In a Manage store session | H59: — | I59: 1. Press End session in the bar 2. Verify the expected result. | J59: The platform dashboard shows and the store menu is gone. | K59: End session returned to the platform dashboard with the platform menu. | L59: Pass | M59: High | N59: Functional | O59: Claude (Claude in Chrome) | P59: 2026-10-10 | S59: Super admin | T59: Yes | U59: docs/qa/regression/super-admin/SA-06-store-sessions.md
A60: SA-06-007 | B60: Super Admin | C60: SA-06 · Store sessions (Manage store, View as support) | D60: View as support | E60: Read-only session | F60: View as support shows the store without saving. | G60: On Home Orbit overview | H60: Reason "Support ticket 42" | I60: 1. Press View as support with a reason 2. Open a product 3. Try to change and save 4. Verify the expected result. | J60: Screens open read-only; there is no Save (or saving is refused). | L60: Not Run | M60: High | N60: Security/Permissions | S60: Super admin | T60: No | U60: docs/qa/regression/super-admin/SA-06-store-sessions.md
A61: SA-06-008 | B61: Super Admin | C61: SA-06 · Store sessions (Manage store, View as support) | D61: Timeout | E61: Session ends by itself | F61: A store session ends at its end time. | G61: A Manage store session | H61: Wait past the end time (2 hours) or use a test clock | I61: 1. Leave the session open past the end time 2. Open any store screen 3. Verify the expected result. | J61: The session has ended and you are back in the platform panel. | L61: Not Run | M61: Low | N61: Security/Permissions | R61: Long wait; run when convenient. | S61: Super admin | T61: No | U61: docs/qa/regression/super-admin/SA-06-store-sessions.md
A62: SA-07-001 | B62: Super Admin | C62: SA-07 · Vendor features | D62: Features | E62: Switches and locks | F62: Each feature has a switch; ones outside the plan or Phase 2 are locked. | G62: Home Orbit on Starter | H62: — | I62: 1. Open Home Orbit → Features 2. Verify the expected result. | J62: A row per feature with a switch; rows outside Starter and Phase 2 rows are locked with the reason. | K62: Features tab: Starter plan, preset applied, Always on list, MVP and Growth tables with In plan and On columns. | L62: Pass | M62: High | N62: UI/UX | O62: Claude (Claude in Chrome) | P62: 2026-10-10 | S62: Super admin | T62: Yes | U62: docs/qa/regression/super-admin/SA-07-vendor-features.md
A63: SA-07-002 | B63: Super Admin | C63: SA-07 · Vendor features | D63: Features | E63: Switch off reaches the store | F63: Switching a feature off removes it from the store at once. | G63: Enquiries inbox on | H63: Feature Enquiries inbox | I63: 1. Switch Enquiries inbox off 2. Read the message 3. Open http://home-orbit.localhost:3000/products/feather-stainless-steel-pull-handle-hoph-504 4. Verify the expected result. | J63: "Saved. The live store has the change now." The product page has no Request a quote form. | L63: Not Run | M63: Critical | N63: Integration | S63: Super admin | T63: Yes | U63: docs/qa/regression/super-admin/SA-07-vendor-features.md
A64: SA-07-003 | B64: Super Admin | C64: SA-07 · Vendor features | D64: Features | E64: Switch back on | F64: Switching it on brings the feature back. | G64: Enquiries inbox off | H64: — | I64: 1. Switch Enquiries inbox on 2. Reload the product page 3. Verify the expected result. | J64: The quote form is back. | L64: Not Run | M64: High | N64: Integration | R64: Also: Data persistence | S64: Super admin | T64: No | U64: docs/qa/regression/super-admin/SA-07-vendor-features.md
A65: SA-07-004 | B65: Super Admin | C65: SA-07 · Vendor features | D65: Features | E65: Server check | F65: A switched-off feature is refused on the server, not only hidden. | G65: Enquiries off | H65: Send an enquiry from an open page that still shows the old form | I65: 1. Open a product page with the form 2. Switch Enquiries off in another tab 3. Submit the form on the first tab 4. Verify the expected result. | J65: The submission is refused; no enquiry is created. | L65: Not Run | M65: High | N65: Security/Permissions | S65: Super admin | T65: No | U65: docs/qa/regression/super-admin/SA-07-vendor-features.md
A66: SA-07-005 | B66: Super Admin | C66: SA-07 · Vendor features | D66: Features | E66: Dependencies | F66: Switching on a feature that needs another asks first. | G66: A feature with a dependency (for example WhatsApp offers needs Offer messages) | H66: — | I66: 1. Switch on the dependent feature while its requirement is off 2. Verify the expected result. | J66: A prompt names the feature it needs; confirming switches both on, cancelling changes nothing. | L66: Not Run | M66: Medium | N66: Functional | S66: Super admin | T66: No | U66: docs/qa/regression/super-admin/SA-07-vendor-features.md
A67: SA-07-006 | B67: Super Admin | C67: SA-07 · Vendor features | D67: Features | E67: Menu follows features | F67: The vendor CMS menu follows the features. | G67: Owner signed in (another window) | H67: Switch Reviews off | I67: 1. Switch Reviews off 2. Reload the owner's CMS 3. Verify the expected result. | J67: Marketing → Reviews is gone from the owner's menu; switching it on brings it back. | L67: Not Run | M67: High | N67: Integration | S67: Super admin | T67: No | U67: docs/qa/regression/super-admin/SA-07-vendor-features.md
A68: SA-08-001 | B68: Super Admin | C68: SA-08 · Vendor connectors | D68: Connectors | E68: Layout | F68: Connectors are grouped with an Allowed switch per provider. | G68: On Home Orbit → Connectors | H68: — | I68: 1. Read the tab 2. Verify the expected result. | J68: Payments (Razorpay), Shipping (manual, Shiprocket), Order updates (WhatsApp, SMS "Comes later", email); each provider has Allowed; unconnected ones say "Not connected by the vendor yet". | L68: Not Run | M68: High | N68: UI/UX | S68: Super admin | T68: No | U68: docs/qa/regression/super-admin/SA-08-vendor-connectors.md
A69: SA-08-002 | B69: Super Admin | C69: SA-08 · Vendor connectors | D69: Connectors | E69: Disallow a provider | F69: Switching Allowed off blocks the provider for the store. | G69: Razorpay allowed | H69: — | I69: 1. Switch Razorpay Allowed off 2. Read the message 3. As the owner open Store → Payments 4. Verify the expected result. | J69: "Razorpay switched off for this store"; the owner cannot connect or use Razorpay; switching it back on restores it. | L69: Not Run | M69: High | N69: Integration | R69: Also: Security/Permissions | S69: Super admin | T69: No | U69: docs/qa/regression/super-admin/SA-08-vendor-connectors.md
A70: SA-08-003 | B70: Super Admin | C70: SA-08 · Vendor connectors | D70: Connectors | E70: Secrets never shown | F70: Connected providers show masked keys only. | G70: Owner saved Razorpay test keys (VC-25) | H70: — | I70: 1. Read the Razorpay row 2. Verify the expected result. | J70: "Connected by", mode, masked key ID and "Encrypted, never shown" per secret; no secret value appears anywhere on the page or in its network responses. | L70: Not Run | M70: Critical | N70: Security/Permissions | S70: Super admin | T70: Yes | U70: docs/qa/regression/super-admin/SA-08-vendor-connectors.md
A71: SA-08-004 | B71: Super Admin | C71: SA-08 · Vendor connectors | D71: Connectors | E71: COD rules shown | F71: The vendor's COD rules appear on the tab. | G71: Owner saved COD rules ₹499–₹25,000, fee ₹49 (VC-25) | H71: — | I71: 1. Read the COD line 2. Verify the expected result. | J71: "Vendor rules: orders ₹499.00 to ₹25,000.00, ₹49.00 fee". | L71: Not Run | M71: Medium | N71: Integration | S71: Super admin | T71: No | U71: docs/qa/regression/super-admin/SA-08-vendor-connectors.md
A72: SA-09-001 | B72: Super Admin | C72: SA-09 · Vendor domains | D72: Domains | E72: Primary domain | F72: The store's address is listed as primary. | G72: On Home Orbit → Domains | H72: — | I72: 1. Read the tab 2. Verify the expected result. | J72: home-orbit.localhost is listed as primary. | L72: Not Run | M72: Medium | N72: Functional | S72: Super admin | T72: No | U72: docs/qa/regression/super-admin/SA-09-vendor-domains.md
A73: SA-09-002 | B73: Super Admin | C73: SA-09 · Vendor domains | D73: Domains | E73: Unknown host | F73: An address that belongs to no store never shows a store. | G73: — | H73: http://unknown-store.localhost:3000 | I73: 1. Open the address 2. Verify the expected result. | J73: A plain 404; no store content. | L73: Not Run | M73: High | N73: Security/Permissions | S73: Super admin | T73: No | U73: docs/qa/regression/super-admin/SA-09-vendor-domains.md
A74: SA-10-001 | B74: Super Admin | C74: SA-10 · Vendor billing | D74: Billing | E74: Plan and offer | F74: Billing shows the plan, price and starting offer. | G74: On Home Orbit → Billing | H74: — | I74: 1. Read the tab 2. Verify the expected result. | J74: Starter at ₹3,499 + GST, the ₹9,999 starting offer, and the cards Record payment, Change plan, Pause or cancel. | L74: Not Run | M74: High | N74: UI/UX | S74: Super admin | T74: No | U74: docs/qa/regression/super-admin/SA-10-vendor-billing.md
A75: SA-10-002 | B75: Super Admin | C75: SA-10 · Vendor billing | D75: Billing | E75: Record payment | F75: Recording a payment moves the paid period and adds history. | G75: On Billing | H75: Amount ₹9,999, method and reference | I75: 1. Press Record payment 2. Enter ₹9,999 with a reference 3. Save 4. Reload 5. Verify the expected result. | J75: The paid period moves ahead (first payment covers the offer's 3 months) and the payment shows in History after reload. | L75: Not Run | M75: Critical | N75: Functional | R75: Also: Data persistence | S75: Super admin | T75: Yes | U75: docs/qa/regression/super-admin/SA-10-vendor-billing.md
A76: SA-10-003 | B76: Super Admin | C76: SA-10 · Vendor billing | D76: Billing | E76: Invalid amount | F76: A zero or negative payment is refused. | G76: On Billing | H76: Amount 0, then -100 | I76: 1. Record payment with 0 2. Then with -100 3. Verify the expected result. | J76: Both refused with a message; nothing is added to History. | L76: Not Run | M76: High | N76: Validation | R76: Also: Boundary | S76: Super admin | T76: No | U76: docs/qa/regression/super-admin/SA-10-vendor-billing.md
A77: SA-10-004 | B77: Super Admin | C77: SA-10 · Vendor billing | D77: Billing | E77: Change plan | F77: Changing the plan updates limits. | G77: On Billing | H77: Plan Enterprise | I77: 1. Press Change plan, pick Enterprise, confirm 2. Open Overview → Plan usage 3. Verify the expected result. | J77: The plan reads Enterprise; product limit 10,000; the vendor list shows the new plan. | L77: Not Run | M77: High | N77: Integration | S77: Super admin | T77: No | U77: docs/qa/regression/super-admin/SA-10-vendor-billing.md
A78: SA-10-005 | B78: Super Admin | C78: SA-10 · Vendor billing | D78: Billing | E78: Pause and resume | F78: Pausing and resuming the subscription changes its status. | G78: On Billing | H78: Reason "QA pause" | I78: 1. Press Pause with a reason 2. Read the status 3. Press Resume 4. Verify the expected result. | J78: Status shows Paused then Active; History records both. | L78: Not Run | M78: Medium | N78: Functional | S78: Super admin | T78: No | U78: docs/qa/regression/super-admin/SA-10-vendor-billing.md
A79: SA-10-006 | B79: Super Admin | C79: SA-10 · Vendor billing | D79: Billing | E79: Cancel | F79: Cancelling the subscription asks for confirmation. | G79: A throw-away store (Test Locks) | H79: Reason "QA cancel" | I79: 1. Press Cancel subscription 2. Confirm with a reason 3. Verify the expected result. | J79: Status Cancelled with the end date; Subscriptions lists it under Cancelled. | L79: Not Run | M79: Medium | N79: Functional | R79: Do not cancel Home Orbit. | S79: Super admin | T79: No | U79: docs/qa/regression/super-admin/SA-10-vendor-billing.md
A80: SA-11-001 | B80: Super Admin | C80: SA-11 · Vendor staff | D80: Staff | E80: List | F80: Staff shows the meter, invite and the table. | G80: On Home Orbit → Staff | H80: — | I80: 1. Read the tab 2. Verify the expected result. | J80: Staff meter, + Invite staff, and rows with name, email, roles, Two-step On/Off and last sign-in; the owner owner@homeorbit.example with invite pending. | L80: Not Run | M80: High | N80: UI/UX | S80: Super admin | T80: No | U80: docs/qa/regression/super-admin/SA-11-vendor-staff.md
A81: SA-11-002 | B81: Super Admin | C81: SA-11 · Vendor staff | D81: Staff | E81: Resend invite | F81: Resend invite prints a new link. | G81: Owner invite pending | H81: — | I81: 1. Press Resend invite on the owner 2. Watch the `pnpm dev` terminal 3. Verify the expected result. | J81: A [dev-log email] to owner@homeorbit.example with a fresh set-password link. | L81: Not Run | M81: High | N81: Integration | S81: Super admin | T81: Yes | U81: docs/qa/regression/super-admin/SA-11-vendor-staff.md
A82: SA-11-003 | B82: Super Admin | C82: SA-11 · Vendor staff | D82: Staff | E82: Invite staff | F82: Inviting a staff member with a role. | G82: On Staff | H82: manager@homeorbit.example, role Manager | I82: 1. Press + Invite staff 2. Fill email, name and role 3. Send 4. Verify the expected result. | J82: The person is listed with Manager and invite pending; the invite email prints in the terminal. | L82: Not Run | M82: High | N82: Functional | S82: Super admin | T82: No | U82: docs/qa/regression/super-admin/SA-11-vendor-staff.md
A83: SA-11-004 | B83: Super Admin | C83: SA-11 · Vendor staff | D83: Staff | E83: Staff limit | F83: The plan's staff limit is enforced. | G83: Starter allows 3 staff | H83: Invite until the limit is passed | I83: 1. Invite staff until 3 exist 2. Try a 4th 3. Verify the expected result. | J83: The 4th invite is refused with the plan limit message. | L83: Not Run | M83: Medium | N83: Boundary | S83: Super admin | T83: No | U83: docs/qa/regression/super-admin/SA-11-vendor-staff.md
A84: SA-11-005 | B84: Super Admin | C84: SA-11 · Vendor staff | D84: Staff | E84: Change roles | F84: Changing a staff member's roles saves. | G84: A staff member exists | H84: Add Content editor | I84: 1. Press Change roles 2. Tick Content editor 3. Save 4. Reload 5. Verify the expected result. | J84: The new role shows after reload. | L84: Not Run | M84: Medium | N84: Data persistence | S84: Super admin | T84: No | U84: docs/qa/regression/super-admin/SA-11-vendor-staff.md
A85: SA-11-006 | B85: Super Admin | C85: SA-11 · Vendor staff | D85: Staff | E85: Reset two-step | F85: Resetting a staff member's two-step makes them set it up again. | G85: A staff member with two-step On | H85: — | I85: 1. Press Reset two-step and confirm 2. Sign in as that person 3. Verify the expected result. | J85: Two-step reads Off; the reset is audited; the person signs in without a code and can set it up again. | L85: Not Run | M85: High | N85: Security/Permissions | S85: Super admin | T85: No | U85: docs/qa/regression/super-admin/SA-11-vendor-staff.md
A86: SA-11-007 | B86: Super Admin | C86: SA-11 · Vendor staff | D86: Staff | E86: Last owner protected | F86: The store's last owner cannot be removed. | G86: Only one owner | H86: — | I86: 1. Press Remove on the owner 2. Verify the expected result. | J86: "The store needs at least one owner. Make someone else owner first." | L86: Not Run | M86: High | N86: Negative | S86: Super admin | T86: No | U86: docs/qa/regression/super-admin/SA-11-vendor-staff.md
A87: SA-11-008 | B87: Super Admin | C87: SA-11 · Vendor staff | D87: Staff | E87: Remove staff | F87: Removing a staff member ends their access. | G87: A non-owner staff member signed in elsewhere | H87: — | I87: 1. Press Remove and confirm 2. Reload that person's CMS 3. Verify the expected result. | J87: They lose access to Home Orbit at once. | L87: Not Run | M87: High | N87: Security/Permissions | S87: Super admin | T87: No | U87: docs/qa/regression/super-admin/SA-11-vendor-staff.md
A88: SA-12-001 | B88: Super Admin | C88: SA-12 · Plans | D88: Plans | E88: Plan cards | F88: One card per plan with prices and limits. | G88: Signed in as super admin | H88: — | I88: 1. Open Billing → Plans 2. Verify the expected result. | J88: Starter ₹3,499 / month with the starting offer ₹9,999 for 3 months, 500 products, 3 staff, 5 GB, 1,000 orders a month, vendors on it; Enterprise ₹6,999 / month, 10,000 products. | K88: Starter ₹3,499/month plus GST, starting offer ₹9,999 for 3 months, 500 products, 3 staff, 5 GB, 1,000 orders; Enterprise ₹6,999, 10,000 products, 30 staff, 100 GB, no order limit. | L88: Pass | M88: High | N88: UI/UX | O88: Claude (Claude in Chrome) | P88: 2026-10-10 | S88: Super admin | T88: Yes | U88: docs/qa/regression/super-admin/SA-12-plans.md
A89: SA-12-002 | B89: Super Admin | C89: SA-12 · Plans | D89: Plans | E89: Matrices | F89: Features and connectors allowed per plan. | G89: On Plans | H89: — | I89: 1. Read Features allowed and Connectors allowed 2. Verify the expected result. | J89: A row per feature or group with a tick per plan; Phase 2 rows marked P2. | K89: Features allowed table with Phase and a column per plan. | L89: Pass | M89: Medium | N89: UI/UX | O89: Claude (Claude in Chrome) | P89: 2026-10-10 | R89: Ticks are icons; read from the page structure. | S89: Super admin | T89: No | U89: docs/qa/regression/super-admin/SA-12-plans.md
A90: SA-12-003 | B90: Super Admin | C90: SA-12 · Plans | D90: Plans | E90: Edit plan, no change | F90: Saving a plan without changes works. | G90: On Plans | H90: — | I90: 1. Press Edit plan on Starter 2. Press Save 3. Verify the expected result. | J90: Saves without errors. | L90: Not Run | M90: Medium | N90: Regression | S90: Super admin | T90: No | U90: docs/qa/regression/super-admin/SA-12-plans.md
A91: SA-12-004 | B91: Super Admin | C91: SA-12 · Plans | D91: Plans | E91: Edit price | F91: A price change saves in paise and shows in rupees. | G91: Editing Starter | H91: Monthly price ₹3,599 | I91: 1. Change the monthly price 2. Save 3. Reload Plans 4. Change it back to ₹3,499 5. Verify the expected result. | J91: The card shows ₹3,599 after reload; MRR on the dashboard reflects it; restored afterwards. | L91: Not Run | M91: Medium | N91: Data persistence | S91: Super admin | T91: No | U91: docs/qa/regression/super-admin/SA-12-plans.md
A92: SA-12-005 | B92: Super Admin | C92: SA-12 · Plans | D92: Plans | E92: Invalid limits | F92: Negative or non-numeric limits are refused. | G92: Editing a plan | H92: Products limit -5 | I92: 1. Type -5 in the product limit 2. Save 3. Verify the expected result. | J92: Refused with a validation message. | L92: Not Run | M92: Medium | N92: Validation | S92: Super admin | T92: No | U92: docs/qa/regression/super-admin/SA-12-plans.md
A93: SA-12-006 | B93: Super Admin | C93: SA-12 · Plans | D93: Plans | E93: Create plan | F93: A new plan can be created and shows on the page. | G93: On Plans | H93: Name "QA plan", code qa, ₹999/month, 50 products | I93: 1. Create a new plan with these values 2. Save 3. Open Plans 4. Verify the expected result. | J93: A QA plan card shows with its price and limits; set it inactive afterwards (listed apart). | L93: Not Run | M93: Low | N93: Functional | S93: Super admin | T93: No | U93: docs/qa/regression/super-admin/SA-12-plans.md
A94: SA-13-001 | B94: Super Admin | C94: SA-13 · Subscriptions | D94: Subscriptions | E94: Figures and tabs | F94: Subscriptions shows the money figures and status tabs. | G94: Signed in as super admin | H94: — | I94: 1. Open Billing → Subscriptions 2. Verify the expected result. | J94: MRR, On trial, Past due and Renewing in 7 days; tabs by status with counts; a row per vendor with plan, billing, period end, next amount incl. GST and last payment. | K94: MRR ₹6,999, On trial 2, Past due 0, Renewing in 7 days 0; tabs All 3, Trialing 2, Active 1; amounts incl. GST ₹11,798.82 (₹9,999 offer) and ₹8,258.82. | L94: Pass | M94: High | N94: UI/UX | O94: Claude (Claude in Chrome) | P94: 2026-10-10 | S94: Super admin | T94: Yes | U94: docs/qa/regression/super-admin/SA-13-subscriptions.md
A95: SA-13-002 | B95: Super Admin | C95: SA-13 · Subscriptions | D95: Subscriptions | E95: Record payment on past due | F95: A past-due row offers Record payment. | G95: A past-due subscription (period end in the past) | H95: — | I95: 1. Open the Past due tab 2. Press Record payment on a row 3. Verify the expected result. | J95: The vendor's Billing card opens ready to record the payment. | L95: Not Run | M95: Medium | N95: Integration | S95: Super admin | T95: No | U95: docs/qa/regression/super-admin/SA-13-subscriptions.md
A96: SA-13-003 | B96: Super Admin | C96: SA-13 · Subscriptions | D96: Subscriptions | E96: Export CSV | F96: Export downloads the tab shown. | G96: On Subscriptions | H96: — | I96: 1. Pick a tab 2. Press Export CSV 3. Verify the expected result. | J96: A CSV with the rows of that tab. | L96: Not Run | M96: Low | N96: Functional | S96: Super admin | T96: No | U96: docs/qa/regression/super-admin/SA-13-subscriptions.md
A97: SA-13-004 | B97: Super Admin | C97: SA-13 · Subscriptions | D97: Subscriptions | E97: MRR follows payments | F97: Recording a payment updates the figures. | G97: A trial or past-due subscription | H97: Record a payment (SA-10) | I97: 1. Note MRR and Past due 2. Record a payment on Billing 3. Reload Subscriptions 4. Verify the expected result. | J97: The subscription moves to Active and the figures change accordingly. | L97: Not Run | M97: Medium | N97: Integration | S97: Super admin | T97: No | U97: docs/qa/regression/super-admin/SA-13-subscriptions.md
A98: SA-14-001 | B98: Super Admin | C98: SA-14 · Team and access, Staff users | D98: Team | E98: List and security | F98: Team and access lists the platform team and security rules. | G98: Signed in as super admin | H98: — | I98: 1. Open Platform → Team and access 2. Verify the expected result. | J98: You as Super admin with Two-step On and last sign-in; Security says two-step Required, 8-hour session, lockout and password length. | K98: Platform Admin, Super admin, Two-step On, last sign-in Today 11:13; Security: two-step Required, 8 hours, 5 tries 15 min, 10+ characters. | L98: Pass | M98: High | N98: UI/UX | O98: Claude (Claude in Chrome) | P98: 2026-10-10 | R98: Reset two-step is also offered on your own row; consider hiding it there. | S98: Super admin | T98: Yes | U98: docs/qa/regression/super-admin/SA-14-team.md
A99: SA-14-002 | B99: Super Admin | C99: SA-14 · Team and access, Staff users | D99: Team | E99: Invite teammate | F99: Inviting a Support teammate sends an invite. | G99: On Team and access | H99: support.qa@tenantecom.local, Support | I99: 1. Invite the teammate as Support 2. Watch the terminal 3. Verify the expected result. | J99: Listed as Support, invite pending; the invite email prints in the terminal. | L99: Not Run | M99: High | N99: Functional | S99: Super admin | T99: No | U99: docs/qa/regression/super-admin/SA-14-team.md
A100: SA-14-003 | B100: Super Admin | C100: SA-14 · Team and access, Staff users | D100: Team | E100: Invalid email | F100: An invalid email is refused. | G100: On Team and access | H100: Email "not-an-email" | I100: 1. Invite with the invalid email 2. Verify the expected result. | J100: Refused with an email format message. | L100: Not Run | M100: Medium | N100: Validation | S100: Super admin | T100: No | U100: docs/qa/regression/super-admin/SA-14-team.md
...

Sheet End-to-End Workflows
A1: Test Case ID | B1: Application/Portal | C1: Module Name | D1: Submodule/Feature | E1: Functionality | F1: Test Scenario | G1: Preconditions | H1: Test Data | I1: Step-by-Step Instructions | J1: Expected Result | K1: Actual Result | L1: Status | M1: Priority | N1: Test Type | O1: Executed By | P1: Execution Date | Q1: Defect/Bug ID | R1: Remarks/Additional Notes | S1: Role | T1: Smoke Run | U1: Regression Script
A2: E2E-01-001 | B2: End-to-End | C2: E2E-01 · Vendor onboarding to first store preview | D2: Onboarding | E2: Create, invite, set password, preview | F2: A vendor created by the super admin is usable end to end by its owner. | G2: Super admin signed in; slug e2e-store unused | H2: E2E Store / E2E Store Pvt Ltd / Hardware / 29AABCT1234F1ZM / e2e-store / Starter / e2e.owner@example.com | I2: 1. Super admin: New vendor with the data, invite ticked → Create vendor 2. Copy the set-password link from the `pnpm dev` terminal 3. Private window: open the link, set password "E2eStore@2026" 4. Verify the owner lands on the E2E Store dashboard with the launch checklist 5. Open http://e2e-store.localhost:3000 6. Verify the expected result. | J2: Store draft in All vendors; owner signed in to their own store only; the store opens in the default design with a preview banner. | L2: Not Run | M2: Critical | N2: Integration | S2: Super admin, Store owner | T2: Yes | U2: docs/qa/regression/e2e/E2E-01-onboarding.md
A3: E2E-01-002 | B3: End-to-End | C3: E2E-01 · Vendor onboarding to first store preview | D3: Onboarding | E3: Owner cannot reach the platform | F3: The new owner sees only their store. | G3: E2E-01-001 done | H3: — | I3: 1. As the new owner open /admin/collections/tenants 2. Read the menu 3. Verify the expected result. | J3: "Nothing found"; no Vendors, Billing or Platform in the menu. | L3: Not Run | M3: Critical | N3: Security/Permissions | S3: Store owner | T3: No | U3: docs/qa/regression/e2e/E2E-01-onboarding.md
A4: E2E-01-003 | B4: End-to-End | C4: E2E-01 · Vendor onboarding to first store preview | D4: Onboarding | E4: Dashboard counts follow | F4: The platform dashboard and lists include the new store. | G4: E2E-01-001 done | H4: — | I4: 1. Super admin: open the dashboard and All vendors 2. Verify the expected result. | J4: Recently onboarded lists E2E Store (Draft); Needs attention lists it as a draft; All vendors counts it. | L4: Not Run | M4: High | N4: Integration | S4: Super admin | T4: No | U4: docs/qa/regression/e2e/E2E-01-onboarding.md
A5: E2E-02-001 | B5: End-to-End | C5: E2E-02 · Feature switches across portals | D5: Features | E5: Reviews off everywhere | F5: Switching Reviews off removes it from the CMS, the store and the server. | G5: Reviews on; a published review exists | H5: — | I5: 1. Super admin: Home Orbit → Features → Reviews off 2. Owner: reload the CMS; look for Marketing → Reviews 3. Store: open the reviewed product 4. Try the /review/<token> link from a review email 5. Verify the expected result. | J5: Reviews is gone from the menu; the product page shows no ratings; the review link is refused. Switching it on restores all. | L5: Not Run | M5: Critical | N5: Integration | S5: Super admin, Store owner, Shopper | T5: Yes | U5: docs/qa/regression/e2e/E2E-02-features.md
A6: E2E-02-002 | B6: End-to-End | C6: E2E-02 · Feature switches across portals | D6: Features | E6: Dealer locator off | F6: Switching the dealer locator off hides the page, block, menu and links. | G6: Dealer locator on | H6: — | I6: 1. Super admin: Dealer locator off 2. Open http://home-orbit.localhost:3000/dealers 3. Read the home page and footer 4. On a phone read the bottom bar 5. Verify the expected result. | J6: /dealers is not found; the dealer finder block and Find a dealer links are gone; the bottom bar shows Search in place of Dealers. | L6: Not Run | M6: High | N6: Integration | S6: Super admin, Shopper | T6: No | U6: docs/qa/regression/e2e/E2E-02-features.md
A7: E2E-03-001 | B7: End-to-End | C7: E2E-03 · Catalogue to storefront | D7: Catalogue | E7: New category and product on the store | F7: A category and an active product appear on the store. | G7: Owner signed in; store selling | H7: Category "QA hooks" under Home decor; product "QA hook" QA-HOOK-1, photo, price ₹499, HSN 8302, GST 18%, Buy online and quote, Active | I7: 1. Create the category 2. Create the product with a photo and price; Save Active 3. Open http://home-orbit.localhost:3000/c 4. Open Home decor → QA hooks 5. Verify the expected result. | J7: The category shows on /c and the menu; the product card shows ₹499 with Add to cart. | L7: Not Run | M7: Critical | N7: Integration | S7: Store owner, Shopper | T7: Yes | U7: docs/qa/regression/e2e/E2E-03-catalogue.md
A8: E2E-03-002 | B8: End-to-End | C8: E2E-03 · Catalogue to storefront | D8: Catalogue | E8: Search finds it by model number and typo | F8: Instant search finds the new product. | G8: E2E-03-001 done | H8: "QA-HOOK"; "qahook1"; "qa hok" | I8: 1. Type each in the header search 2. Verify the expected result. | J8: Each lists QA hook in the suggestions; Enter opens Results with it first. | L8: Not Run | M8: High | N8: Integration | S8: Shopper | T8: No | U8: docs/qa/regression/e2e/E2E-03-catalogue.md
A9: E2E-03-003 | B9: End-to-End | C9: E2E-03 · Catalogue to storefront | D9: Catalogue | E9: Filters, sort and Add to cart on the listing | F9: The listing filters by price and sorts by price. | G9: E2E-03-001 done | H9: min 400, max 600; sort Price low to high | I9: 1. Open Home decor 2. Set the price box to 400–600 and Go 3. Sort by Price: low to high 4. Press Add to cart on QA hook 5. Verify the expected result. | J9: Only products ₹400–₹600 show, cheapest first; "Added ✓" and the cart count goes up. | K9: Door hardware sorted Price: low to high (₹249, ₹249, ₹249, ₹349…); Add to cart on HODS-861 made the cart 1 item. | L9: Pass | M9: High | N9: Integration | O9: Claude (in-app browser) | P9: 2026-10-12 | R9: First try failed after an order in the same browser (DEF-003); passed after the fix. | S9: Shopper | T9: No | U9: docs/qa/regression/e2e/E2E-03-catalogue.md
A10: E2E-03-004 | B10: End-to-End | C10: E2E-03 · Catalogue to storefront | D10: Catalogue | E10: Archive removes it from the store | F10: Archiving takes the product off the store. | G10: E2E-03-001 done | H10: — | I10: 1. Owner: archive QA hook 2. Store: reload the category and the product address 3. Verify the expected result. | J10: Gone from the category; the product address shows not found (or redirects if a redirect exists). | L10: Not Run | M10: High | N10: Integration | S10: Store owner, Shopper | T10: No | U10: docs/qa/regression/e2e/E2E-03-catalogue.md
A11: E2E-03-005 | B11: End-to-End | C11: E2E-03 · Catalogue to storefront | D11: Catalogue | E11: Quick add on a home page card | F11: A card on the home page adds a single-finish product without leaving the page. | G11: Store selling; Home Orbit home page from `pnpm seed:home-orbit` | H11: Designed for modern homes: HOGDH-610 | I11: 1. Open the home page 2. Hover the Lotus glass door handle card (phone: tap its + button) 3. Press Add to cart on the photo 4. Verify the expected result. | J11: "Added ✓" on the card and the header cart count goes up; the cart has one Lotus glass door handle at the price the card showed. | L11: Not Run | M11: High | N11: Integration | S11: Shopper | T11: No | U11: docs/qa/regression/e2e/E2E-03-catalogue.md
A12: E2E-03-006 | B12: End-to-End | C12: E2E-03 · Catalogue to storefront | D12: Catalogue | E12: Quick add picker for finishes and sizes | F12: A product sold in several finishes and sizes opens a picker with server prices. | G12: Store selling; variants generated for HOPH-504 in the product editor with stock | H12: Size 12 inch, finish Rose gold | I12: 1. Open the home page 2. Press Quick add on the Feather pull handle card 3. Choose 12 inch and Rose gold 4. Add to cart 5. Verify the expected result. | J12: The picker shows sizes and finish swatches, the price changes with the choice, code HOPH-504-12-INCH-ROSE-GOLD shows; "Added to your cart. View cart" and the count goes up; Esc closes it. | K12: Phone: Quick add on HOPH-504 opened the picker sheet (sizes and finishes, ₹2,049); Add to cart bumped the cart to 1; Escape closed it. | L12: Pass | M12: High | N12: Integration | O12: Claude (in-app browser) | P12: 2026-10-12 | S12: Shopper | T12: No | U12: docs/qa/regression/e2e/E2E-03-catalogue.md
A13: E2E-03-007 | B13: End-to-End | C13: E2E-03 · Catalogue to storefront | D13: Catalogue | E13: Menu dropdown columns from Menus | F13: The header dropdown shows the columns, links and picture set on the Menus screen. | G13: Home Orbit menus from `pnpm seed:home-orbit` | H13: Door hardware: Aldrops and latches, Door handles, Door accessories | I13: 1. Hover Door hardware in the category bar (desktop) 2. Press Laser-cut aldrops 3. Owner: rename the column "Door handles" to "Handles" in Menus and save 4. Reload the store and hover Door hardware 5. Verify the expected result. | J13: Three headed columns, the aldrop picture and Shop all door hardware; Laser-cut aldrops opens Aldrops filtered to the laser-cut range (4 products); after the edit the column reads "Handles". | K13: Focus on Door hardware opened the dropdown: Aldrops and latches with All aldrops, Laser-cut aldrops, BMC-cut aldrops… | L13: Pass | M13: Medium | N13: Integration | O13: Claude (in-app browser) | P13: 2026-10-12 | R13: Menus edit step (owner) not repeated. | S13: Shopper, Store owner | T13: No | U13: docs/qa/regression/e2e/E2E-03-catalogue.md
A14: E2E-04-001 | B14: End-to-End | C14: E2E-04 · Order to cash (COD) | D14: Checkout | E14: Guest COD order | F14: A guest places a COD order. | G14: Store selling; COD on; zones set | H14: Rahul Kulkarni, 98765 43210, rahul.k@example.com, 411045, Flat 12 Shanti Kunj, Baner Road | I14: 1. Open http://home-orbit.localhost:3000/products/feather-stainless-steel-pull-handle-hoph-504 2. Check delivery for 411045 3. Add to cart 4. Cart → Checkout 5. Fill contact and address (state fills from the pincode) 6. Choose Cash on delivery 7. Place order 8. Verify the expected result. | J14: "Thank you, Rahul. Your order is placed." with the order number (HOM-…), amount to pay in cash, delivery date and items; the cart is empty again. | K14: "Thank you, Rahul. Your order is placed." Order HOM-10024 · ₹1,947.00 to pay in cash on delivery, arrives Thu 15 Oct, both items listed; cart empty; email and WhatsApp printed in the dev log. | L14: Pass | M14: Critical | N14: Integration | O14: Claude (in-app browser) | P14: 2026-10-12 | S14: Shopper | T14: Yes | U14: docs/qa/regression/e2e/E2E-04-order-to-cash.md
A15: E2E-04-002 | B15: End-to-End | C15: E2E-04 · Order to cash (COD) | D15: Checkout | E15: Server recomputes totals | F15: Totals cannot be changed from the browser. | G15: An item in the cart | H15: Change a price in the page with DevTools before placing | I15: 1. Edit the shown total in DevTools 2. Place the order 3. Verify the expected result. | J15: The order uses the server's price; the edited number has no effect. | K15: Changed every shown total to ₹1.00 before Place order; the order and messages say ₹1,947 (₹849 + ₹1,049 + ₹49 COD fee). | L15: Pass | M15: Critical | N15: Security/Permissions | O15: Claude (in-app browser) | P15: 2026-10-12 | S15: Shopper | T15: No | U15: docs/qa/regression/e2e/E2E-04-order-to-cash.md
A16: E2E-04-003 | B16: End-to-End | C16: E2E-04 · Order to cash (COD) | D16: Checkout | E16: Confirmation page is private | F16: Only the browser that placed the order sees the confirmation. | G16: E2E-04-001 done | H16: The confirmation address | I16: 1. Open the confirmation address in another browser 2. Verify the expected result. | J16: "We can't show this order here". | K16: The confirmation address fetched without the shopper's cookies: "We can't show this order here". | L16: Pass | M16: High | N16: Security/Permissions | O16: Claude (in-app browser) | P16: 2026-10-12 | S16: Shopper | T16: No | U16: docs/qa/regression/e2e/E2E-04-order-to-cash.md
A17: E2E-04-004 | B17: End-to-End | C17: E2E-04 · Order to cash (COD) | D17: Fulfilment | E17: CMS sees, packs, ships, delivers | F17: The order flows through the CMS and messages. | G17: E2E-04-001 done | H17: Tracking 12345 | I17: 1. Owner: Sales → Orders → open the order 2. Mark as packed 3. Save and tell the shopper it shipped 4. Out for delivery 5. Delivered 6. Read Messages to the shopper 7. Watch the terminal 8. Verify the expected result. | J17: Invoice issued at packing; order Completed, Paid, Delivered; messages queued then "Sent (dev log)" for each step. | L17: Not Run | M17: Critical | N17: Integration | S17: Store owner | T17: Yes | U17: docs/qa/regression/e2e/E2E-04-order-to-cash.md
A18: E2E-04-005 | B18: End-to-End | C18: E2E-04 · Order to cash (COD) | D18: Tracking | E18: No-login tracking page | F18: The tracking link shows progress without personal details. | G18: Shipped order; link from the message | H18: /t/<code> | I18: 1. Open the tracking link 2. Open a made-up code 3. Verify the expected result. | J18: Journey, courier and AWB, items and masked phone; no address or invoice. A made-up code: "We can't find this order". | K18: /t/<code> without cookies: HOM-10024 Confirmed · arriving by Thu 15 Oct with the journey; no address. | L18: Pass | M18: High | N18: Security/Permissions | O18: Claude (in-app browser) | P18: 2026-10-12 | R18: Order not shipped yet, so courier and AWB were not shown. | S18: Shopper | T18: No | U18: docs/qa/regression/e2e/E2E-04-order-to-cash.md
A19: E2E-04-006 | B19: End-to-End | C19: E2E-04 · Order to cash (COD) | D19: Platform | E19: Sale reaches the platform dashboard | F19: The super admin sees the order in figures. | G19: E2E-04-001 done today | H19: — | I19: 1. Super admin: open the dashboard 2. Open All vendors 3. Verify the expected result. | J19: Orders today counts it; GMV this month includes it once delivered/paid; Home Orbit's Orders in 30 days goes up. | L19: Not Run | M19: High | N19: Integration | S19: Super admin | T19: No | U19: docs/qa/regression/e2e/E2E-04-order-to-cash.md
A20: E2E-04-007 | B20: End-to-End | C20: E2E-04 · Order to cash (COD) | D20: Stock | E20: Stock held and released | F20: Stock is held at checkout and returned on cancel. | G20: A variant with stock 2 | H20: Order 2, then cancel | I20: 1. Order both pieces 2. Try to buy one more 3. Owner cancels the order 4. Try again 5. Verify the expected result. | J20: "Only 0 left"/Out of stock while held; buyable again after cancel. | L20: Not Run | M20: High | N20: Boundary | S20: Shopper, Store owner | T20: No | U20: docs/qa/regression/e2e/E2E-04-order-to-cash.md
A21: E2E-04-008 | B21: End-to-End | C21: E2E-04 · Order to cash (COD) | D21: Checkout | E21: Shop again after an order | F21: The browser that placed an order can fill a new cart straight away. | G21: E2E-04-001 done in this browser | H21: Any product | I21: 1. After the confirmation, open a category 2. Press Add to cart on a card 3. Open the cart 4. Verify the expected result. | J21: The cart count goes from 0 to 1 and the cart shows only the new item; the order stays as placed. | K21: After HOM-10024, Add to cart on a listing card made the cart 1 item. | L21: Pass | M21: Critical | N21: Integration | O21: Claude (in-app browser) | P21: 2026-10-12 | R21: Failed before the fix (DEF-003). | S21: Shopper | T21: No | U21: docs/qa/regression/e2e/E2E-04-order-to-cash.md
A22: E2E-05-001 | B22: End-to-End | C22: E2E-05 · Schemes and coupons to checkout | D22: Scheme | E22: Live scheme prices everywhere | F22: A live scheme shows the same price on card, product, cart and order. | G22: Store selling | H22: Diwali 2026, 10% off, max ₹1,500, whole store, live now | I22: 1. Owner: create and schedule the scheme 2. Store: read a card, the product page, the cart, then place a COD order 3. Verify the expected result. | J22: The same offer price on card and product page; the cart shows the scheme line; the order's discount equals the cart's. | L22: Not Run | M22: Critical | N22: Integration | S22: Store owner, Shopper | T22: Yes | U22: docs/qa/regression/e2e/E2E-05-offers.md
A23: E2E-05-002 | B23: End-to-End | C23: E2E-05 · Schemes and coupons to checkout | D23: Coupon | E23: Coupon on product page and cart | F23: A public coupon shows as an offer and applies once. | G23: Coupons on | H23: HOME200, ₹200 off above ₹1,000, public | I23: 1. Owner: create HOME200 2. Store: open a product it covers 3. Read Offers for you 4. Copy the code; apply it in a ₹1,000+ cart 5. Verify the expected result. | J23: Offers for you lists HOME200 with Copy; the cart applies ₹200 once; a second code replaces the first (one coupon per order). | L23: Not Run | M23: High | N23: Integration | S23: Store owner, Shopper | T23: No | U23: docs/qa/regression/e2e/E2E-05-offers.md
A24: E2E-05-003 | B24: End-to-End | C24: E2E-05 · Schemes and coupons to checkout | D24: Scheme | E24: Upcoming scheme shown honestly | F24: A scheduled scheme shows its real start date. | G24: A scheme starting next week with Show before start | H24: — | I24: 1. Store: open a covered product 2. Open /offers 3. Verify the expected result. | J24: Offers for you says "from <real start date>"; /offers lists it as coming up; prices are not changed yet. | L24: Not Run | M24: Medium | N24: Integration | S24: Shopper | T24: No | U24: docs/qa/regression/e2e/E2E-05-offers.md
A25: E2E-06-001 | B25: End-to-End | C25: E2E-06 · Review lifecycle | D25: Reviews | E25: Delivered buyer writes, store approves, store shows | F25: The full review cycle. | G25: A delivered order for shopper rahul.k@example.com with an account | H25: 2 stars, title, text, a photo | I25: 1. Shopper: My account → Write a review on the delivered order 2. Owner: Marketing → Reviews → Approve with reply 3. Store: open the product and a category 4. Verify the expected result. | J25: Product page shows the review with "Verified purchase" and the reply; cards show stars; the home page Reviews block shows it if 4+ stars only. | L25: Not Run | M25: Critical | N25: Integration | S25: Shopper, Store owner | T25: Yes | U25: docs/qa/regression/e2e/E2E-06-reviews.md
A26: E2E-06-002 | B26: End-to-End | C26: E2E-06 · Review lifecycle | D26: Reviews | E26: Non-buyers cannot review | F26: Only delivered items can be reviewed. | G26: A shopper with no delivered order | H26: — | I26: 1. Look for Write a review in My account 2. Open a review link for another order 3. Verify the expected result. | J26: No Write a review; foreign or expired links are refused. | L26: Not Run | M26: High | N26: Security/Permissions | S26: Shopper | T26: No | U26: docs/qa/regression/e2e/E2E-06-reviews.md
A27: E2E-07-001 | B27: End-to-End | C27: E2E-07 · Store status across portals | D27: Status | E27: Go live, suspend, resume | F27: Store status reaches shoppers and search engines. | G27: Home Orbit draft | H27: Reasons for suspend | I27: 1. Super admin: Go live 2. Store: reload; open /robots.txt and /sitemap.xml 3. Super admin: Suspend with a reason 4. Store: reload in a private window 5. Super admin: Resume 6. Verify the expected result. | J27: Live: no preview bar, robots allows, sitemap lists home, 13 categories and 110 products. Suspended: "Store unavailable", robots Disallow, sitemap gone. Resumed: back at once. Recent changes lists all with reasons. | L27: Not Run | M27: Critical | N27: Integration | S27: Super admin, Shopper | T27: Yes | U27: docs/qa/regression/e2e/E2E-07-store-status.md
A28: E2E-07-002 | B28: End-to-End | C28: E2E-07 · Store status across portals | D28: Status | E28: Suspended store refuses orders | F28: A suspended store cannot take orders even from an open checkout. | G28: Checkout open in a tab | H28: — | I28: 1. Open checkout with an item 2. Super admin suspends the store 3. Place the order 4. Verify the expected result. | J28: The order is refused; no order is created. | L28: Not Run | M28: High | N28: Security/Permissions | S28: Shopper, Super admin | T28: No | U28: docs/qa/regression/e2e/E2E-07-store-status.md
A29: E2E-08-001 | B29: End-to-End | C29: E2E-08 · Platform support session audit | D29: Session | E29: Audited manage session | F29: Changes made by the platform inside a store are visible to the store and the platform. | G29: Super admin and owner | H29: Reason "Vendor asked us to set up the Diwali page" | I29: 1. Super admin: Manage store with the reason 2. Edit About us; Save Draft 3. End session 4. Owner: open Pages 5. Super admin: Recent changes 6. Verify the expected result. | J29: Owner sees "by Platform Admin (platform team)"; Recent changes lists the session, reason and edit. | L29: Not Run | M29: High | N29: Integration | S29: Super admin, Store owner | T29: No | U29: docs/qa/regression/e2e/E2E-08-support-session.md
A30: E2E-08-002 | B30: End-to-End | C30: E2E-08 · Platform support session audit | D30: Session | E30: Support view cannot change data | F30: View as support never saves. | G30: View as support session | H30: — | I30: 1. Try to save a product and a setting 2. Verify the expected result. | J30: Nothing saves; no Save buttons or the save is refused. | L30: Not Run | M30: High | N30: Security/Permissions | S30: Super admin | T30: No | U30: docs/qa/regression/e2e/E2E-08-support-session.md
A31: E2E-09-001 | B31: End-to-End | C31: E2E-09 · Connector allowance to checkout | D31: Connectors | E31: Razorpay blocked by the platform | F31: A disallowed provider is unusable for the store. | G31: Razorpay keys saved by the owner | H31: — | I31: 1. Super admin: Connectors → Razorpay Allowed off 2. Owner: open Payments 3. Shopper: open checkout 4. Verify the expected result. | J31: Payments says Razorpay is not allowed; checkout offers no Pay online (COD only if on); switching it back restores. | L31: Not Run | M31: High | N31: Integration | S31: Super admin, Store owner, Shopper | T31: No | U31: docs/qa/regression/e2e/E2E-09-connectors.md
A32: E2E-09-002 | B32: End-to-End | C32: E2E-09 · Connector allowance to checkout | D32: Connectors | E32: COD rules at checkout | F32: COD rules from Payments apply at checkout and show to the platform. | G32: COD ₹499–₹25,000, fee ₹49 | H32: Carts ₹300 and ₹600 | I32: 1. Shopper: checkout with ₹300 then ₹600 2. Super admin: Connectors tab 3. Verify the expected result. | J32: ₹300 has no COD; ₹600 offers COD with ₹49; the platform shows the vendor's rules. | L32: Not Run | M32: High | N32: Boundary | S32: Shopper, Super admin | T32: No | U32: docs/qa/regression/e2e/E2E-09-connectors.md
A33: E2E-10-001 | B33: End-to-End | C33: E2E-10 · Staff roles and two-step reset | D33: Roles | E33: Order manager limits | F33: An order manager handles orders but not keys, staff or catalogue writes. | G33: Owner invites orders@homeorbit.example as Order manager | H33: — | I33: 1. Accept the invite in another browser 2. Pack an order 3. Open /admin/payments, /admin/staff 4. Edit a product 5. Verify the expected result. | J33: Orders work; payments and staff refused; product editing refused or read-only. | L33: Not Run | M33: Critical | N33: Security/Permissions | S33: Store owner, Order manager | T33: Yes | U33: docs/qa/regression/e2e/E2E-10-staff.md
... A38: E2E-12-001 | B38: End-to-End | C38: E2E-12 · Enquiry from store to inbox | D38: Enquiry | E38: Quote to inbox to closed | F38: A product quote request reaches the inbox and is worked. | G38: Enquiries on | H38: Name, 10-digit mobile, city, quantity 50, consent ticked; options picked | I38: 1. Store: product page → Request a bulk quote with the data 2. Owner: dashboard figures and bell 3. Inbox: open it, assign, Contacted, note, Won 4. Verify the expected result. | J38: Store says thanks with ENQ-n; dashboard and bell count it; the inbox shows the options; it moves New → In progress → Closed. | L38: Not Run | M38: Critical | N38: Integration | S38: Shopper, Store owner | T38: Yes | U38: docs/qa/regression/e2e/E2E-12-enquiries.md
A39: E2E-12-002 | B39: End-to-End | C39: E2E-12 · Enquiry from store to inbox | D39: Enquiry | E39: Validation and spam limit | F39: The quote form validates and limits repeats. | G39: — | H39: Empty form; then 6 sends in 10 minutes | I39: 1. Send the form empty 2. Send a valid form 6 times quickly 3. Verify the expected result. | J39: Errors under Name and consent and "Add a mobile number or an email…"; the 6th send is refused with the wait message. | L39: Not Run | M39: High | N39: Validation | R39: Also: Boundary | S39: Shopper | T39: No | U39: docs/qa/regression/e2e/E2E-12-enquiries.md
A40: E2E-13-001 | B40: End-to-End | C40: E2E-13 · Returns and refunds | D40: Returns | E40: Request, approve, receive, refund | F40: A return runs from the shopper to a refund and the report. | G40: A delivered order for a shopper account | H40: Reason, note, a photo | I40: 1. Shopper: order page → Request return 2. Owner: Orders → Returns → Approve with pickup note 3. Mark received; Refund 4. Insights → Reports 5. Verify the expected result. | J40: Shopper sees each state; the return reads Refunded; a credit note lowers the GST summary row. | L40: Not Run | M40: High | N40: Integration | S40: Shopper, Store owner | T40: No | U40: docs/qa/regression/e2e/E2E-13-returns.md
A41: E2E-14-001 | B41: End-to-End | C41: E2E-14 · Offer consent, abandoned cart and unsubscribe | D41: Consent | E41: Consent drives reminders; unsubscribe stops offers only | F41: Offer consent at checkout and unsubscribe behave as promised. | G41: Offer messages and abandoned cart on | H41: Tick "Offers and new launches · By email" | I41: 1. Shopper: checkout, tick offers by email, leave 2. After the delay: reminder in the terminal; Return to your cart restores it 3. Open Unsubscribe and confirm 4. Owner: send an offer message 5. Place and ship an order for the same email 6. Verify the expected result. | J41: Reminder sent with consent; after unsubscribe no offer message is sent to that email, but order updates still are. | L41: Not Run | M41: High | N41: Integration | S41: Shopper, Store owner | T41: No | U41: docs/qa/regression/e2e/E2E-14-abandoned.md
A42: E2E-15-001 | B42: End-to-End | C42: E2E-15 · Affiliate referral to commission | D42: Affiliate | E42: Referral to approved commission | F42: An affiliate link credits the order without exposing the shopper. | G42: Approved affiliate | H42: /r/<CODE>?to=/products/<slug> | I42: 1. Open the link in another browser; place a COD order 2. Affiliate: /affiliate/dashboard 3. Owner: deliver the order; wait the hold days or run the job 4. Verify the expected result. | J42: Dashboard shows the order "Pending: not delivered yet" without shopper details; after delivery and hold it becomes approved; cancelling reverses it. | L42: Not Run | M42: Medium | N42: Integration | S42: Affiliate, Shopper, Store owner | T42: No | U42: docs/qa/regression/e2e/E2E-15-affiliate.md
A43: E2E-16-001 | B43: End-to-End | C43: E2E-16 · Billing to subscriptions | D43: Billing | E43: Payment updates subscriptions and MRR | F43: Recording a vendor payment changes the platform money views. | G43: A trial or past-due vendor | H43: ₹9,999 | I43: 1. Super admin: note Subscriptions and dashboard figures 2. Record a payment on the vendor's Billing 3. Reload Subscriptions and the dashboard 4. Verify the expected result. | J43: The subscription is Active with the new period; Past due and MRR change accordingly. | L43: Not Run | M43: High | N43: Integration | S43: Super admin | T43: No | U43: docs/qa/regression/e2e/E2E-16-billing.md
A44: E2E-17-001 | B44: End-to-End | C44: E2E-17 · Shopper account and wishlist across devices | D44: Account | E44: Guest orders join the account | F44: Logging in with the checkout email shows earlier guest orders. | G44: A guest COD order with rahul.k@example.com | H44: Code from the terminal | I44: 1. Open http://home-orbit.localhost:3000/account → Send code to the email 2. Type the code from the terminal 3. Read Your orders 4. Verify the expected result. | J44: My account "Hi Rahul" lists the guest order with Track order and Invoice. | L44: Not Run | M44: High | N44: Integration | S44: Shopper | T44: No | U44: docs/qa/regression/e2e/E2E-17-account.md
A45: E2E-17-002 | B45: End-to-End | C45: E2E-17 · Shopper account and wishlist across devices | D45: Wishlist | E45: Wishlist follows sign-in | F45: A guest wishlist merges into the account and shows on another browser. | G45: Wishlist on | H45: — | I45: 1. As a guest tap the heart on two cards 2. Log in 3. Open /wishlist in another browser signed in 4. Verify the expected result. | J45: Both products in the wishlist on both browsers; the header heart shows 2. | L45: Not Run | M45: Medium | N45: Data persistence | S45: Shopper | T45: No | U45: docs/qa/regression/e2e/E2E-17-account.md
A46: E2E-17-003 | B46: End-to-End | C46: E2E-17 · Shopper account and wishlist across devices | D46: Account | E46: Log out of all devices | F46: Logging out everywhere ends other sessions. | G46: Signed in on two browsers | H46: — | I46: 1. Press Log out of all devices on one 2. Open a page on the other 3. Verify the expected result. | J46: The other browser is signed out on its next page. | L46: Not Run | M46: Medium | N46: Security/Permissions | S46: Shopper | T46: No | U46: docs/qa/regression/e2e/E2E-17-account.md
A47: E2E-18-001 | B47: End-to-End | C47: E2E-18 · Storefront chrome and search (shop experience) | D47: Header | E47: Desktop header icons and menu | F47: The desktop header has the menu, search and icons and never overflows. | G47: Store selling; wishlist on | H47: Widths 1280 and 1024 | I47: 1. Open http://home-orbit.localhost:3000 at 1280 px 2. Read the header 3. Narrow to 1024 px 4. Verify the expected result. | J47: Menu items on one line, search box, account, wishlist with count and cart with count; at 1024 nothing overlaps (the default header turns the search into an icon; Home Orbit keeps its search bar on its own row). | K47: At 1280 px: menu on one line, 547 px search bar, account, wishlist and cart with count; at 1024 px the menu still fits one line, the search bar (367 px) sits on its own row, no overlaps, no sideways scroll. | L47: Pass | M47: High | N47: UI/UX | O47: Claude (in-app browser) | P47: 2026-10-12 | R47: Expected result updated for Home Orbit's header, whose search has its own row. | S47: Shopper | T47: Yes | U47: docs/qa/regression/e2e/E2E-18-storefront.md
A48: E2E-18-002 | B48: End-to-End | C48: E2E-18 · Storefront chrome and search (shop experience) | D48: Phone | E48: Bottom navigation | F48: The phone bottom bar shows the right tabs and hides on pages with their own bar. | G48: Phone size (375 px) | H48: — | I48: 1. Read the bottom bar on the home page 2. Tap Shop 3. Open a product, the cart and checkout 4. Verify the expected result. | J48: Home, Shop, Dealers, Account, Cart; Shop opens /c with all categories; on product, cart and checkout the page's sticky button replaces the bar. | K48: Phone: bottom bar Home, Shop (/c), Dealers, Account, Cart with count; on a product page the sticky "₹849 Add to cart" bar replaces it. | L48: Pass | M48: High | N48: UI/UX | O48: Claude (in-app browser) | P48: 2026-10-12 | S48: Shopper | T48: Yes | U48: docs/qa/regression/e2e/E2E-18-storefront.md
A49: E2E-18-003 | B49: End-to-End | C49: E2E-18 · Storefront chrome and search (shop experience) | D49: Footer | E49: Footer columns and legal line | F49: The footer matches the wireframe and the store's features. | G49: Store selling; contact and grievance officer saved (VC-03) | H49: — | I49: 1. Scroll to the footer 2. Verify the expected result. | J49: Logo, contact, Get our offers first; Shop with Offers; Help with Track order, published policies, Contact us; Company with Find a dealer and Downloads; legal name, GSTIN, grievance officer and ways to pay. | K49: Footer: Get our offers first; Shop (with Offers); Help (Track order, Privacy policy, Contact us); Company (About us, Contact us, Find a dealer, Downloads); legal line with GSTIN and COD. | L49: Pass | M49: High | N49: UI/UX | O49: Claude (in-app browser) | P49: 2026-10-12 | R49: QA data has placeholder legal name and no grievance officer, so that line was not shown. | S49: Shopper | T49: No | U49: docs/qa/regression/e2e/E2E-18-storefront.md
A50: E2E-18-004 | B50: End-to-End | C50: E2E-18 · Storefront chrome and search (shop experience) | D50: Search | E50: Instant search with typos and recent searches | F50: Suggestions rank model numbers first and forgive typos. | G50: Store with Home Orbit's catalogue | H50: "610"; "hogdh610"; "glas handel" | I50: 1. Type each in the header search 2. Use arrow keys and Enter 3. Clear the box and focus it 4. Verify the expected result. | J50: HOGDH-610 first for the first two; glass door handles for the typo; Enter opens the choice; Recent searches list earlier terms. | K50: "610" and "hogdh610" → HOGDH-610 first; "glas handel" → glass door handles; ArrowDown + Enter opened HOGDH-610; clearing the box showed Recent searches "hogdh610". | L50: Pass | M50: High | N50: Functional | O50: Claude (in-app browser) | P50: 2026-10-12 | S50: Shopper | T50: Yes | U50: docs/qa/regression/e2e/E2E-18-storefront.md
A51: E2E-18-005 | B51: End-to-End | C51: E2E-18 · Storefront chrome and search (shop experience) | D51: Listing | E51: Filter sheet on phones | F51: The phone filter sheet works and reports the count. | G51: Phone size; store selling | H51: Price 500–1000 | I51: 1. Open a category 2. Tap Filter 3. Enter the price and Go 4. Tap Show N products 5. Verify the expected result. | J51: A sheet over a dimmed page with Close and Clear; the count matches the list; Filter (1) after closing. | K51: Phone: Filter opened a sheet with Close and Clear; max ₹1,000 + Go → "Show 32 products" and 32 in the list (all ≤ ₹1,000); Filter (1) after closing. | L51: Pass | M51: Medium | N51: UI/UX | O51: Claude (in-app browser) | P51: 2026-10-12 | S51: Shopper | T51: No | U51: docs/qa/regression/e2e/E2E-18-storefront.md
A52: E2E-18-006 | B52: End-to-End | C52: E2E-18 · Storefront chrome and search (shop experience) | D52: Cart | E52: Move to wishlist and Complete the look | F52: Cart extras work. | G52: Two items in the cart; wishlist on | H52: — | I52: 1. Press Move to wishlist on one line 2. Read Complete the look 3. Add one suggestion 4. Verify the expected result. | J52: The line leaves the cart and the heart count goes up; suggestions come from the same categories and Add to cart adds one. | K52: Move to wishlist took HOPH-504 out of the cart and the wishlist badge went 0 → 1; Complete the look showed glass door handles; Add to cart on HOGDH-612 made 2 items, ₹1,898. | L52: Pass | M52: Medium | N52: Functional | O52: Claude (in-app browser) | P52: 2026-10-12 | S52: Shopper | T52: No | U52: docs/qa/regression/e2e/E2E-18-storefront.md
A53: E2E-18-007 | B53: End-to-End | C53: E2E-18 · Storefront chrome and search (shop experience) | D53: Motion | E53: Light animations that respect reduced motion | F53: Sections, hero words, menus, quick add and counts move lightly, and stay still for visitors who reduce motion. | G53: Store selling; a browser with scroll-driven animations (Chrome, Edge) | H53: Windows: Settings → Accessibility → Visual effects → Animation effects off | I53: 1. Scroll the home page 2. Swipe the hero 3. Open a menu, Quick add, a heart and Add to cart 4. Turn animations off in the system and reload 5. Owner: Store settings → Branding → untick Animations on the store, Save; reload the store 6. Verify the expected result. | J53: Sections rise in as they arrive, hero words follow their slide, menus and the quick add sheet ease in, the cart and wishlist counts bump; with system animations off everything shows at once and nothing moves (the benefits line stops); with the store switch off the same motion stops for every shopper. | K53: Home: sections below the first rise in while scrolling, hero words follow a half-swiped slide (50%); menu dropdown and phone menu ease in; quick add sheet slides up with a fading backdrop; cart and heart bump. Checked with the browser's animation timings. Store switch: with animations off in the store's settings the page carries data-motion="off" and no scroll animations run; the page renders the same. Lighthouse mobile on the production build: accessibility, best practices and SEO 100 on home, listing and product; layout shift 0. | L53: Pass | M53: Medium | N53: UI/UX | O53: Claude (in-app browser) | P53: 2026-10-12 | R53: Reduced-motion run not done in the in-app browser (it cannot switch the OS setting); the switch was set in the database, not by saving the CMS form (no CMS sign-in in this run). | S53: Shopper, Store owner | T53: No | U53: docs/qa/regression/e2e/E2E-18-storefront.md

Sheet Defect Log
A1: Defect ID | B1: Linked Test Case | C1: Portal | D1: Module | E1: Description | F1: Severity | G1: Steps to Reproduce | H1: Expected Result | I1: Actual Result | J1: Status | K1: Reported By | L1: Date | M1: Remarks
A2: DEF-001 | B2: SA-03-001 | C2: Super Admin | D2: SA-01 · Sign in and two-step verification | E2: An admin link opened from outside the admin (email, chat, browser extension) bounced a signed-in person to the sign-in page, which then sent them to the dashboard instead of the page they asked for. | F2: High | G2: 1. Sign in as super admin. 2. Open http://localhost:3000/admin/collections/tenants from outside the admin (a link in another site or the extension's navigate). 3. Watch where you land. | H2: All vendors opens (signing in first only when actually signed out). | I2: Payload ignores the session cookie on cross-site navigations (CSRF rule), redirects to /admin/login?redirect=…; our sign-in page saw the person was signed in and redirected to /admin, dropping the redirect. | J2: Closed | K2: Claude | L2: 2026-10-10 | M2: Fixed: SignInView now redirects a signed-in visitor to the requested /admin path (safeRedirect, unit tested; outside paths and the sign-in page fall back to the dashboard). Retested in Chrome: lands on the vendor page.
A3: DEF-002 | B3: SA-05-005 | C3: Super Admin | D3: SA-05 · Vendor overview and store status | E3: Plan usage always showed "Orders this month 0": nothing updated the tenant's ordersThisMonth counter, so the meter and the 90% limit warning never moved. | F3: Medium | G3: 1. Have orders this month for Home Orbit (pnpm demo:orders home-orbit or a storefront order). 2. Open All vendors → Home Orbit → Plan usage. | H3: Orders this month counts the orders placed this month. | I3: 0 / 1,000 while the dashboard showed 8 sold orders and 18 placed this month. | J3: Closed | K3: Claude | L3: 2026-10-10 | M3: Fixed: counted from the orders (reports ordersThisMonth / ordersPlacedByStore) on the vendor overview, the store's plan card and the dashboard's limit warnings. Retested: 18 / 1,000. Open question for the product: the monthly order limit is shown but never enforced at checkout.
A4: DEF-003 | B4: E2E-04-008 | C4: End-to-End | D4: E2E-04 · Order to cash | E4: After placing an order, the same browser could not add anything to the cart: the server rejected every Add to cart until the cart cookie expired (30 days). | F4: Critical | G4: 1. Place an order on the store (E2E-04-001). 2. Open any category. 3. Press Add to cart on a card. | H4: The cart count goes to 1. | I4: Nothing was added; the dev log showed "ValidationError: The following field is invalid: tenant" from saveCart. The ordered cart kept the shopper's cart token, and tokens are unique per store, so the new cart could not be created. | J4: Closed | K4: Claude | L4: 2026-10-12 | M4: Fixed: markCartConverted gives the ordered cart a fresh token, and saveCart frees the token from any older ordered cart before creating a new one (integration test in tests/integration/offers.test.ts). Retested: Add to cart works after an order.

Sheet Test Data & Preconditions
A1: Item | B1: Value | C1: Used by | D1: Notes
A2: Environment | B2: Local QA: admin http://localhost:3000/admin; store http://home-orbit.localhost:3000; database tenantecom_qa (Docker Mongo replica set rs0) | C2: All | D2: Start the `app-qa` launch entry or `pnpm dev:fresh` with DATABASE_URI pointing at tenantecom_qa. Never run destructive cases on real data.
A3: Browser | B3: Chrome (or Edge/Firefox); *.localhost opens without setup | C3: All | D3: Use a normal window for the super admin and private windows or other browsers for store staff and shoppers.
A4: Super admin | B4: admin@tenantecom.local | C4: SA-*, E2E-* | D4: Password: SEED_SUPER_ADMIN_PASSWORD in .env (never in this sheet). Two-step required: the tester's own authenticator app.
A5: Support teammate | B5: support.qa@tenantecom.local (invite in SA-14) | C5: SA-01, SA-15 | D5: Sets two-step at first sign-in.
A6: Home Orbit owner | B6: owner@homeorbit.example | C6: VC-*, E2E-* | D6: Set the password from the invite link (SA-11 Resend invite prints it in the `pnpm dev` terminal), e.g. HomeOrbit@2026.
A7: Demo Sanitary owner | B7: owner@demo-sanitary.example | C7: E2E-11 | D7: Invite link from the seed output or Resend invite.
A8: Demo Clothing owner | B8: owner@demo-clothing.example | C8: SA-01 lockout | D8: Use for the lockout case so no real account is locked.
A9: Store staff to invite | B9: editor@ (Catalog editor), orders@ (Order manager), content@ (Content editor), manager@ (Manager) @homeorbit.example | C9: VC-28, E2E-10 | D9: Starter allows 3 staff: remove one before inviting the next, or switch the plan to Enterprise.
A10: Shopper | B10: Rahul Kulkarni, rahul.k@example.com, mobile 98765 43210 | C10: E2E-04, E2E-17 | D10: Login codes print in the `pnpm dev` terminal ("Your code to log in to Home Orbit").
A11: Delivery pincodes | B11: 411045 (Pune, Maharashtra), 110001 (Delhi), 744101 (remote zone), 12345 (invalid) | C11: VC-24, E2E-04
A12: GSTINs | B12: Valid 29AABCT1234F1ZM, 27AAPFU0939F1ZV; invalid checksum 29AABCT1234F1ZN | C12: SA-04, SA-05 | D12: Sample GSTINs from the GST portal documentation, not real businesses.
A13: Products | B13: HOPH-504 Feather pull handle; HOGDH-610 Lotus glass door handle; HOAL-101 aldrop | C13: VC-04, E2E-03 | D13: Home Orbit catalogue from `pnpm seed:home-orbit` (110 products).
A14: Sample prices and COD | B14: `pnpm demo:selling home-orbit` | C14: Selling cases | D14: Local only: puts sample prices, stock, COD (₹49) and two zones on the store.
A15: Sample orders | B15: `pnpm demo:orders home-orbit` | C15: SA-02, VC-02 | D15: 24 COD orders over 14 days for the dashboards.
A16: Razorpay test keys | B16: rzp_test_… (your own test keys, optional) | C16: VC-25, E2E-09 | D16: Made-up keys test the refusal path; never live keys.
A17: Coupons and schemes | B17: HOME200 (₹200 off above ₹1,000); Diwali 2026 (10% off, max ₹1,500) | C17: VC-14, VC-15, E2E-05 | D17: Created during the cases.
A18: Emails and WhatsApp | B18: Printed in the `pnpm dev` terminal as [dev-log email] / [dev-log whatsapp] | C18: Messaging cases | D18: Nothing is really sent locally.
A19: Reset | B19: docker compose down -v; up -d mongo; pnpm seed; pnpm seed:home-orbit (with DATABASE_URI set to the QA database) | C19: After destructive runs | D19: Uploaded files stay in media/.
A20: Run order | B20: SA-01 → SA-03 → SA-05/06 → VC-01 → VC-03 → VC-04…; selling cases after `pnpm demo:selling`; E2E after the modules they depend on | C20: All | D20: See docs/qa/coverage.md "Dependencies".
